Workbook

Sheet Cover
A8: =Language!$B$4 -> Select language ☛ | D8: English
A10: =Language!B416 -> Genomics costing tool, second edition
A12: =Language!B459 -> Genomics costing tool, second edition is an Excel-based interactive costing tool. Step-by-step guidance on how to use the tool for cost estimation can be found in the publication Genomics costing tool: user manual, second edition. Geneva: World Health Organization; 2026.
A13: =Language!B419 -> Genomics costing tool: user manual, second edition. Geneva: World Health Organization; 2026.
A14: https://iris.who.int/handle/10665/384933
A15: =Language!B458 -> Licence: CC BY-NC-SA 3.0 IGO.
A17: =Language!B421 -> For further information, please contact
A18: eulab@who.int
A20: =Language!B423 -> Please review the Genomics costing tool: user manual, second edition. Geneva: World Health Organization; 2026. https://iris.who.int/handle/10665/384933. Licence: CC BY-NC-SA 3.0 IGO. carefully before using this tool. The tool is completed in a series of steps:
A21: =Language!B424 -> Step 1. Data entry sheet: Complete the information on the genomic sequencing for which you are performing the costing. Ensure that you complete the tool from top to bottom. If a note is asking you to complete cells in a different line, do so first before moving down. Refer to the colour-coding key below.
A24: =Language!$B$247 -> Fixed titles and totals
A25: =Language!$B$248 -> General information and legends
A26: =Language!$B$44 -> Fixed or formula (cannot be edited)
A27: =Language!$B$43 -> Select from drop-down options
A28: =Language!$B$42 -> Fillable (free text)
A29: =Language!$B$412 -> Prefilled data (contains free text) – edit information or value if necessary (will not affect calculation/formulas)
A30: =Language!$B$45 -> Prefilled data (contains formulas) – edit information or value if necessary/with caution (formula will be deleted)
A31: =Language!$B$409 -> A cell that had contained a formula, which was deleted by the user
A33: =Language!B425 -> Step 2. Once the “Data entry” sheet is completed, review the output in the “Reagents and consumables” and “Equipment” sheets, especially the prices. Complete any missing information
A36: =Language!B426 -> Step 3. Fill in the rest of the sheets: “Personnel and training”, “Facility and transport”, “Bioinformatics”, and “Quality management”
A38: =Language!B427 -> Step 4. Once the tool is completed and the data is carefully reviewed, go to the “Results – USD” sheet for the breakdown of costs. If you enter a USD-local currency conversion rate in the “Reagents and consumables” sheet in cell O2, you can view the breakdowns in the local currency in the “Results - local currency” sheet
A43: =Language!B428 -> © World Health Organization 2026
A44: =Language!B429 -> Some rights reserved. This work is available under the Creative Commons Attribution-NonCommercial-ShareAlike 3.0 IGO licence (CC BY-NC-SA 3.0 IGO; https://creativecommons.org/licenses/by-nc-sa/3.0/igo). Under the terms of this licence, you may copy, redistribute and adapt the work for non-commercial purposes, provided the work is appropriately cited, as indicated below. In any use of this work, there should be no suggestion that WHO endorses any specific organization, products or services. The use of the WHO logo is not permitted. If you adapt the work, then you must license your work under the same or equivalent Creative Commons licence. If you create a translation of this work, you should add the following disclaimer along with the suggested citation: “This translation was not created by the World Health Organization (WHO). WHO is not responsible for the content or accuracy of this translation. The original English edition shall be the binding and authentic edition”. Any mediation relating to disputes arising under the licence shall be conducted in accordance with the mediation rules of the World Intellectual Property Organization (http://www.wipo.int/amc/en/mediation/rules/). Suggested citation. Genomics costing tool, second edition. Geneva: World Health Organization; 2026. https://doi.org/10.2471/B09722. Licence: CC BY-NC-SA 3.0 IGO. Cataloguing-in-Publication (CIP) data. CIP data are available at https://iris.who.int/. Sales, rights and licensing. To purchase WHO publications, see https://www.who.int/publications/book-orders. To submit requests for commercial use and queries on rights and licensing, see https://www.who.int/copyright. Third-party materials. If you wish to reuse material from this work that is attributed to a third party, such as tables, figures or images, it is your responsibility to determine whether permission is needed for that reuse and to obtain permission from the copyright holder. The risk of claims resulting from infringement of any third-party-owned component in the work rests solely with the user. General disclaimers. The designations employed and the presentation of the material in this publication do not imply the expression of any opinion whatsoever on the part of WHO concerning the legal status of any country, territory, city or area or of its authorities, or concerning the delimitation of its frontiers or boundaries. Dotted and dashed lines on maps represent approximate border lines for which there may not yet be full agreement. The mention of specific companies or of certain manufacturers’ products does not imply that they are endorsed or recommended by WHO in preference to others of a similar nature that are not mentioned. Errors and omissions excepted, the names of proprietary products are distinguished by initial capital letters. All reasonable precautions have been taken by WHO to verify the information contained in this publication. However, the published material is being distributed without warranty of any kind, either expressed or implied. The responsibility for the interpretation and use of the material lies with the reader. In no event shall WHO be liable for damages arising from its use.
A76: =Language!B438 -> Acknowledgements
A77: =Language!B439 -> The World Health Organization (WHO) would like to thank the many individuals who contributed to the development of this costing tool. The second edition of the Genomics Costing Tool (GCT) and its user manual were co-developed by four institutions: the Association of Public Health Laboratories (APHL), FIND, the United Kingdom Health Security Agency (UKHSA) and WHO.
A78: =Language!B440 -> Leadership and coordination
A79: =Language!B441 -> WHO provided leadership and coordination for the development and publication of the GCT. The technical development of the tool was led by Alexandr Jaguparov (Infectious Hazard Management, WHO Regional Office for Europe) under the supervision of Joanna Salvi Le Garrec Zwetyenga (Infectious Hazard Management, WHO Regional Office for Europe). The development of the user manual was co-led by Ashley Bolding (APHL, United States of America) and Toni Whistler (APHL, USA). Oluwatosin Wuraola Akande (Department of Epidemic and Pandemic Management, WHO headquarters) led the overall coordination of the GCT project.
A80: =Language!B442 -> Core technical team
A81: =Language!B443 -> The following members of the GCT working group made substantial intellectual input by contributing to the scoping, technical concept, development, writing and review of the GCT and its user manual: Babak Afrough (UKHSA, United Kingdom of Great Britain and Northern Ireland), Oluwatosin Wuraola Akande (Department of Epidemic and Pandemic Management, WHO headquarters), Ashley Bolding (APHL, USA), Alexandr Jaguparov (Infectious Hazard Management, WHO Regional Office for Europe), Beatrix Kele (UKHSA, United Kingdom), Marco Marklewitz (FIND, Switzerland), Biran Musul (WHO Country Office for Türkiye), Angela Poates (APHL, USA), Joanna Salvi Le Garrec Zwetyenga (Infectious Hazard Management, WHO Regional Office for Europe), Toni Whistler (APHL, USA), Aude Wilhelm (UKHSA, United Kingdom; WHO Hub for Pandemic and Epidemic Intelligence, WHO headquarters).
A82: =Language!B444 -> Contributors
A83: =Language!B445 -> The following provided support to the scoping and review of the tool: Silvia Argimon (WHO Hub for Pandemic and Epidemic Intelligence, WHO headquarters), Josefina Campos (WHO Hub for Pandemic and Epidemic Intelligence, WHO headquarters), Soudeh Ehsani (Division of Communicable Diseases, Environment and Health, WHO Regional Office for Europe), Sophia Georghiou (Global Programme on Tuberculosis and Lung Health, WHO headquarters), Nicksy Gumede-Moeletsi (WHO Regional Office for Africa), Noah Hull (APHL, USA), Adolfo Lara (APHL, USA), Miguel Moreno-Molina (FIND, Switzerland), Dmitriy Pereyaslov (Department of Epidemic and Pandemic Management, WHO headquarters), Julia Pringle (APHL, USA), Jessica Rowland (APHL, USA), Anita Suresh (FIND, Switzerland), Swapna Uplekar (FIND, Switzerland).
A84: =Language!B446 -> External reviewers
A85: =Language!B447 -> The GCT working group extends its sincere appreciation to all the institutions and public health laboratories whose collaborative efforts in the tool review and pilot exercise were instrumental in validating the second edition of the GCT: Zhyldyz Atambekova (Kyrgyz Research Institute of Veterinary Medicine named after Arstanbek Duisheev of the Ministry of Agriculture of the Kyrgyz Republic, Kyrgyzstan), Soany Mariela Avilez (National Health Surveillance Laboratory/ National Virology Laboratory of the Ministry of Health (SESAL), Honduras), Zhyldyz Bekturova (Laboratory of Molecular Genetics and Virology, Department of Disease Prevention and State Sanitary and Epidemiological Surveillance of the Ministry of Health of the Kyrgyz Republic, Kyrgyzstan), Veronica Burlac (National Reference Laboratory in Genomic Sequencing, National Agency for Public Health, Ministry of Health of the Republic of Moldova, Republic of Moldova), Valeria Ceban (National Reference Laboratory in Genomic Sequencing, National Agency for Public Health, Ministry of Health of the Republic of Moldova, Republic of Moldova), Elena Chesov (Laboratory of Genetics, Center of Personalized Medicine, State University of Medicine and Pharmacy “Nicolae Testemițanu”, Republic of Moldova), Nelly Ciobanu (National Tuberculosis Reference Laboratory, PMSI Institute of Pneumology “Chiril Draganiuc”, Republic of Moldova), Alexandru Codreanu (National Tuberculosis Reference Laboratory, PMSI Institute of Pneumology “Chiril Draganiuc”, Republic of Moldova), Svetlana Colac (National Reference Laboratory in Genomic Sequencing, National Agency for Public Health, Ministry of Health of the Republic of Moldova, Republic of Moldova), Tolkun Isakova (National reference laboratory for TB, National Center of Phthisiology of the Ministry of Health of the Kyrgyz Republic, Kyrgyzstan), Baarinisa Iskanova (Reference laboratory for the diagnosis of viral hepatitis and HIV, Republican Center for the Control of Blood-Borne Viral Hepatitis and HIV, Ministry of Health of the Kyrgyz Republic, Kyrgyzstan), Gulmira Kalmambetova (National reference laboratory for TB, National Center of Phthisiology of the Ministry of Health of the Kyrgyz Republic, Kyrgyzstan), Khoo Yoong Khean (Duke-NUS Centre for Outbreak Preparedness, Singapore), Shurendar Selva Kumar (Duke-NUS Centre for Outbreak Preparedness, Singapore), Gulshan Mataeva (National reference laboratory for TB, National Center of Phthisiology of the Ministry of Health of the Kyrgyz Republic, Kyrgyzstan), Gulmira Orozalieva (Laboratory of Molecular Genetics and Virology, Department of Disease Prevention and State Sanitary and Epidemiological Surveillance of the Ministry of Health of the Kyrgyz Republic, Kyrgyzstan), Paul Michael Pronyk (Duke-NUS Centre for Outbreak Preparedness, Singapore), Stela Racovita (Laboratory of Genetics, Center of Personalized Medicine, State University of Medicine and Pharmacy “Nicolae Testemițanu”, Republic of Moldova), Karla Dariela Romero (National Health Surveillance Laboratory/ National Virology Laboratory of the Ministry of Health (SESAL), Honduras), Adyl Ryspaev (Laboratory of Molecular Genetics and Virology, Department of Disease Prevention and State Sanitary and Epidemiological Surveillance of the Ministry of Health of the Kyrgyz Republic, Kyrgyzstan), Gulbarchyn Saparova (National reference laboratory for TB, National Center of Phthisiology of the Ministry of Health of the Kyrgyz Republic, Kyrgyzstan), Victor Sitnic (National Reference Laboratory in Genomic Sequencing, National Agency for Public Health, Ministry of Health of the Republic of Moldova, Republic of Moldova), Alexandra Suruceanu (National Reference Laboratory in Genomic Sequencing, National Agency for Public Health, Ministry of Health of the Republic of Moldova, Republic of Moldova), Meerbubu Sydykova (National reference laboratory for TB, National Center of Phthisiology of the Ministry of Health of the Kyrgyz Republic, Kyrgyzstan), Ada Mariela Vidal (National Health Surveillance Laboratory/ National Virology Laboratory of the Ministry of Health (SESAL), Honduras), Ecaterina Zazuc (National Reference Laboratory in Genomic Sequencing, National Agency for Public Health, Ministry of Health of the Republic of Moldova, Republic of Moldova).

Sheet Data entry
B4: =Language!$B$5 -> Genomics costing tool, second edition
B6: =Language!$B$6 -> User inputs
B8: =Language!$B$7 -> Name of the laboratory
B9: =Language!$B$8 -> Country
B10: =Language!$B$9 -> Year
B12: =Language!B362 -> Sequencer 1 | E12: =Language!B363 -> Sequencer 2
B13: =Language!$B$341 -> Pathogen type | C13: Bacterial | E13: =Language!$B$341 -> Pathogen type | F13: Bacterial
B14: =Language!$B$12 -> Pathogen | C14: Salmonella spp. | E14: =Language!$B$12 -> Pathogen | F14: Escherichia coli
B15: =Language!$B$342 -> Genome size (in Mb) | C15: =IFERROR(VLOOKUP($C$14, 'Annex4_Coverage Sample Calc'!$C$27:'Annex4_Coverage Sample Calc'!$G$44,4,FALSE),"Enter value") -> 4.8 | D15: =IF($C$13='Annex1_Library Prep'!W7,Language!B381,IF($C$15='Annex4_Coverage Sample Calc'!F39,Language!B378,"")) | E15: =Language!$B$342 -> Genome size (in Mb) | F15: =IFERROR(VLOOKUP($F$14, 'Annex4_Coverage Sample Calc'!$C$27:'Annex4_Coverage Sample Calc'!$G$44,4,FALSE),"Enter value") -> 5 | G15: =IF($F$13='Annex1_Library Prep'!W7,Language!B381,IF($F$15='Annex4_Coverage Sample Calc'!F39,Language!B378,""))
B16: =Language!$B$14 -> Estimated number of samples per year | C16: 500 | E16: =Language!$B$14 -> Estimated number of samples per year | F16: 300
B17: =Language!$B$15 -> Next-generation sequencing platform | C17: Illumina MiSeq | E17: =Language!$B$15 -> Next-generation sequencing platform | F17: ONT GridION (Project Pack)
B18: =Language!$B$16 -> Sequencing reagents | C18: MiSeq Reagent Kit v2 (300 cycle) | D18: =IFERROR(IF($C$18='Annex3_Reagents and Consumables'!N2,Language!$B$359,IF(MATCH($C$18,'Annex3_Reagents and Consumables'!B42:B58,0),Language!B361,"")),"") | E18: =Language!$B$16 -> Sequencing reagents | F18: Other sequencing kit | G18: =IFERROR(IF($F$18='Annex3_Reagents and Consumables'!O2,Language!$B$359,IF(MATCH($F$18,'Annex3_Reagents and Consumables'!B42:B58,0),Language!B361,"")),"") -> Enter required reagent specifications in rows 38–40 below
B19: =Language!$B$343 -> Sequencing coverage | C19: =IFERROR(VLOOKUP($C$14, 'Annex4_Coverage Sample Calc'!$C$27:'Annex4_Coverage Sample Calc'!$G$45,5,FALSE),"Enter value") -> 50 | D19: =IF($C$13='Annex1_Library Prep'!W7,Language!B397, IF($C$19='Annex4_Coverage Sample Calc'!G39,Language!B379,"")) | E19: =Language!$B$343 -> Sequencing coverage | F19: =IFERROR(VLOOKUP($F$14, 'Annex4_Coverage Sample Calc'!$C$27:'Annex4_Coverage Sample Calc'!$G$44,5,FALSE),"Enter value") -> 50 | G19: =IF($F$13='Annex1_Library Prep'!W7,Language!B397, IF($F$19='Annex4_Coverage Sample Calc'!G39,Language!B379,""))
B20: =Language!B398 -> Buffer capacity accounting for off-target reads (unusable reads) (in %) | C20: =IF(C13='Annex1_Library Prep'!W5,0.2,IF(C13='Annex1_Library Prep'!W6,0.3,IF(C13='Annex1_Library Prep'!W7,0,0.2))) -> 0.3 | E20: =Language!B398 -> Buffer capacity accounting for off-target reads (unusable reads) (in %) | F20: =IF(F13='Annex1_Library Prep'!W5,0.2,IF(F13='Annex1_Library Prep'!W6,0.3,IF(F13='Annex1_Library Prep'!W7,0,0.2))) -> 0.3
B21: =Language!$B$22 -> Library preparation/index kit | C21: Illumina DNA Prep, (M) Tagmentation (96 Samples, IPB) | D21: =IF($C$21='Annex1_Library Prep'!P4,Language!$B$360,"") | E21: =Language!$B$22 -> Library preparation/index kit | F21: Other library preparation kit | G21: =IF($F$21='Annex1_Library Prep'!T4,Language!$B$360,"") -> Enter required reagent specifications in rows 36–37 below
B22: =Language!$B$332 -> Enrichment protocol used (Y/N) | C22: No | E22: =Language!$B$332 -> Enrichment protocol used (Y/N) | F22: No
B23: =Language!$B$24 -> Sample retests (sequencing) (%) | C23: 0.05 | E23: =Language!$B$24 -> Sample retests (sequencing) (%) | F23: 0.02
B24: =Language!$B$17 -> Maximum number of samples per flow cell (within library preparation barcoding limit) | C24: =IF('Annex4_Coverage Sample Calc'!$C$19>=0,'Annex4_Coverage Sample Calc'!$C$19,0) -> 12 | D24: =IF($C$14='Annex4_Coverage Sample Calc'!C41,Language!B380,"") | E24: =Language!$B$17 -> Maximum number of samples per flow cell (within library preparation barcoding limit) | F24: =IF('Annex4_Coverage Sample Calc'!$D$19>=0,'Annex4_Coverage Sample Calc'!$D$19,0) -> 16 | G24: =IF($F$14='Annex4_Coverage Sample Calc'!C41,Language!B380,"")
B25: =Language!B347 -> Number of sequencing runs per year (maximum loading capacity) | C25: ='Annex4_Coverage Sample Calc'!$C$20 -> 44 | D25: =IF($C$25>52,Language!$B$348,"") | E25: =Language!B347 -> Number of sequencing runs per year (maximum loading capacity) | F25: ='Annex4_Coverage Sample Calc'!$D$20 -> 20 | G25: =IF($F$25>52,Language!$B$348,"")
B26: =Language!$B$334 -> Average number of samples per run (average loading) | C26: 10 | D26: =IF($C$26>$C$24,Language!$B$333,"") | E26: =Language!$B$334 -> Average number of samples per run (average loading) | F26: 15 | G26: =IF($F$26>$F$24,Language!$B$333,"")
B27: =Language!$B$337 -> Average number of controls per run | C27: 2 | E27: =Language!$B$337 -> Average number of controls per run | F27: 2
B28: =Language!$B$338 -> Number of sequencing runs per year (average loading) | C28: =IFERROR(ROUNDUP(('Data entry'!$C$16+'Data entry'!$C$16*'Data entry'!$C$23)/$C$26,0),0) -> 53 | D28: =IF( OR( AND(OR(C17=Annex2_Equipment!C10, C17=Annex2_Equipment!C15, C17=Annex2_Equipment!C18, C17=Annex2_Equipment!C19, C17=Annex2_Equipment!C21, C17=Annex2_Equipment!C23), C28>104), AND(C17=Annex2_Equipment!C14, C28>260), AND(C17=Annex2_Equipment!C16, C28>1248), AND(NOT(OR( C17=Annex2_Equipment!C10, C17=Annex2_Equipment!C15, C17=Annex2_Equipment!C18, C17=Annex2_Equipment!C19, C17=Annex2_Equipment!C21, C17=Annex2_Equipment!C23, C17=Annex2_Equipment!C14, C17=Annex2_Equipment!C16 )), C28>52) ), Language!$B$348, "" ) -> Consider higher throughput sequencing items | E28: =Language!$B$338 -> Number of sequencing runs per year (average loading) | F28: =IFERROR(ROUNDUP(('Data entry'!$F$16+'Data entry'!$F$16*'Data entry'!$F$23)/$F$26,0),0) -> 21 | G28: =IF( OR( AND(OR(F17=Annex2_Equipment!C10, F17=Annex2_Equipment!C15, F17=Annex2_Equipment!C18, F17=Annex2_Equipment!C19, F17=Annex2_Equipment!C21, F17=Annex2_Equipment!C23), F28>104), AND(F17=Annex2_Equipment!C14, F28>260), AND(F17=Annex2_Equipment!C16, F28>1248), AND(NOT(OR( F17=Annex2_Equipment!C10, F17=Annex2_Equipment!C15, F17=Annex2_Equipment!C18, F17=Annex2_Equipment!C19, F17=Annex2_Equipment!C21, F17=Annex2_Equipment!C23, F17=Annex2_Equipment!C14, F17=Annex2_Equipment!C16 )), F28>52) ), Language!$B$348, "" )
B29: =Language!$B$339 -> % sequencer loading capacity per run (average loading) | C29: =IFERROR($C$26/$C$24,0) -> 0.83333333 | D29: =IF(C$29=0,"",IF($C$29<=0.5,Language!$B$331,IF($C$29>1,Language!$B$335,""))) | E29: =Language!$B$339 -> % sequencer loading capacity per run (average loading) | F29: =IFERROR($F$26/$F$24,0) -> 0.9375 | G29: =IF(F$29=0,"",IF($F$29<=0.5,Language!$B$331,IF($F$29>1,Language!$B$335,"")))
B31: =Language!$B$365 -> Inputs applied to both sequencing devices | E31: =Language!$B$364 -> Total number of reactions across two sequencers (including retests) | F31: =ROUNDUP('Data entry'!$C$16+'Data entry'!$C$16*'Data entry'!$C$23+'Data entry'!$F$16+'Data entry'!$F$16*'Data entry'!$F$23,0) -> 831
B32: =Language!$B$23 -> Bioinformatics | C32: Hybrid, in-house and cloud-based | E32: =Language!B400 -> Total number of samples sequenced across both sequencers | F32: =C16+F16 -> 800
B33: =Language!B353 -> Dead volume for library preparation handler in % (if used)
B35: =Language!$B$366 -> Additional required specifications for selected sequencing and library preparation items | E35: =Language!$B$366 -> Additional required specifications for selected sequencing and library preparation items
B36: =Language!B354 -> Maximum number of barcodes available for your library preparation kit (e.g. 16, 24, 96, 384, 768) | D36: =IF(C21='Annex1_Library Prep'!P4,Language!B437,"") | E36: =Language!B354 -> Maximum number of barcodes available for your library preparation kit (e.g. 16, 24, 96, 384, 768) | F36: 384 | G36: =IF(F21='Annex1_Library Prep'!T4,Language!B437,"") -> The number of barcodes is equivalent to the number of samples as per the instruction for use (where available)
B37: =Language!B358 -> Number of barcodes per pack | E37: =Language!B358 -> Number of barcodes per pack | F37: 96
B38: =Language!B355 -> Maximum output of the flow cell in bytes (e.g. 1.2 GB is 1200000000 b (1.2*10^9)) | E38: =Language!B355 -> Maximum output of the flow cell in bytes (e.g. 1.2 GB is 1200000000 b (1.2*10^9)) | F38: 180000000000
B39: =Language!B356 -> Read length for your sequencing reagent kit (in bp) | E39: =Language!B356 -> Read length for your sequencing reagent kit (in bp) | F39: 10000
B40: =Language!B357 -> Number of sequencing kit packs needed per one run | E40: =Language!B357 -> Number of sequencing kit packs needed per one run | F40: 1
B41: =Language!B393 -> Enter number of single reads per sample as recommended by the manufacturer (e.g. if 1M reads, enter 1000000) | C41: 1000000 | E41: =Language!B393 -> Enter number of single reads per sample as recommended by the manufacturer (e.g. if 1M reads, enter 1000000) | F41: 1000000
B44: =Language!B41 -> Key:
B45: =Language!$B$247 -> Fixed titles and totals
B46: =Language!$B$248 -> General information and legends
B47: =Language!$B$44 -> Fixed or formula (cannot be edited)
B48: =Language!$B$43 -> Select from drop-down options
B49: =Language!$B$42 -> Fillable (free text)
B50: =Language!$B$412 -> Prefilled data (contains free text) – edit information or value if necessary (will not affect calculation/formulas)
B51: =Language!$B$45 -> Prefilled data (contains formulas) – edit information or value if necessary/with caution (formula will be deleted)
B52: =Language!$B$409 -> A cell that had contained a formula, which was deleted by the user

Sheet Reagents and consumables
B2: =Language!B62 -> Reagents and consumables | P2: =Language!B70 -> <--Enter exchange rate USD to XX (if applicable)
B3: =Language!B31 -> Sample receipt | C3: =Language!B32 -> Nucleic acid extraction | D3: =Language!B33 -> PCR testing | E3: =Language!B34 -> NGS library preparation | F3: =Language!B35 -> Sequencing | G3: =Language!B64 -> Reagent/consumable | H3: =Language!B65 -> Item | I3: =Language!B66 -> Quantity | J3: =Language!B67 -> Price per unit | K3: =Language!B68 -> Total cost | L3: =Language!B367 -> Distributed cost – per workflow | O3: =Language!B69 -> Local currency (reference only)
F4: =Language!B63 -> Workflow step | G4: =Language!B64 -> Reagent/consumable | H4: =Language!B65 -> Item | I4: =Language!B66 -> Quantity | J4: =Language!B67 -> Price per unit | K4: =Language!B68 -> Total cost | O4: local currency (reference only)
B5: No | C5: No | D5: No | E5: No | F5: Yes | G5: ='Annex3_Reagents and Consumables'!B113 -> Reagent | H5: =IFERROR(IF('Data entry'!$C$18='Annex3_Reagents and Consumables'!N2,Language!B386,'Data entry'!$C$18),"") -> MiSeq Reagent Kit v2 (300 cycle) | I5: =IFERROR(IF('Data entry'!$C$21='Annex1_Library Prep'!$D$86,0, IF('Data entry'!$C$18='Annex3_Reagents and Consumables'!$N$2,'Data entry'!$C$40*'Data entry'!$C$28,VLOOKUP('Data entry'!$C$18,'Annex3_Reagents and Consumables'!$B$3:$E$83, 4,FALSE))),"") -> 53 | J5: =IFERROR(VLOOKUP('Data entry'!$C$18,'Annex3_Reagents and Consumables'!$B$3:$E$83, 2,FALSE),"") -> 1194 | K5: =IFERROR(I5*J5,0) -> 63282 | L5: =IFERROR($K5/(COUNTIF($B5:$F5,"Yes")),0) -> 63282 | O5: =(IFERROR($O$2*K5,"")) -> 0
B6: No | C6: No | D6: No | E6: Yes | F6: No | G6: =Language!B34 -> NGS library preparation | H6: {=IF('Data entry'!$C$21='Annex1_Library Prep'!$P$4,Language!B388,IF('Data entry'!$C$21='Annex1_Library Prep'!$D$52, 'Annex1_Library Prep'!$E$52:$E$54,IF('Data entry'!$C$21='Annex1_Library Prep'!$D$55, 'Annex1_Library Prep'!$E$55:$E$58,IF('Data entry'!$C$21='Annex1_Library Prep'!$D$59, 'Annex1_Library Prep'!$E$59:$E$61,IF('Data entry'!$C$21='Annex1_Library Prep'!$D$62, 'Annex1_Library Prep'!$E$62,IF('Data entry'!$C$21='Annex1_Library Prep'!$D$63, 'Annex1_Library Prep'!$E$63:$E$65,IF('Data entry'!$C$21='Annex1_Library Prep'!$D$66, 'Annex1_Library Prep'!$E$66,IF('Data entry'!$C$21='Annex1_Library Prep'!$D$67, 'Annex1_Library Prep'!$E$67:$E$70,IF('Data entry'!$C$21='Annex1_Library Prep'!$D$71, 'Annex1_Library Prep'!$E$71:$E$72,IF('Data entry'!$C$21='Annex1_Library Prep'!$D$73, 'Annex1_Library Prep'!$E$73,IF('Data entry'!$C$21='Annex1_Library Prep'!$D$74, 'Annex1_Library Prep'!$E$74:$E$77,IF('Data entry'!$C$21='Annex1_Library Prep'!$D$78, 'Annex1_Library Prep'!$E$78:$E$81,IF('Data entry'!$C$21='Annex1_Library Prep'!$D$82, 'Annex1_Library Prep'!$E$82:$E$85,IF('Data entry'!$C$21='Annex1_Library Prep'!$D$86, 'Annex1_Library Prep'!$E$86:$E$88,IF('Data entry'!$C$21='Annex1_Library Prep'!$D$89, 'Annex1_Library Prep'!$E$89:$E$97,IF('Data entry'!$C$21='Annex1_Library Prep'!$D$98, 'Annex1_Library Prep'!$E$98:$E$104,IF('Data entry'!$C$21='Annex1_Library Prep'!$D$105, 'Annex1_Library Prep'!$E$105:$E$111,IF('Data entry'!$C$21='Annex1_Library Prep'!$D$112, 'Annex1_Library Prep'!$E$112:$E$118,IF('Data entry'!$C$21='Annex1_Library Prep'!$D$119, 'Annex1_Library Prep'!$E$119:$E$124, IF('Data entry'!$C$21='Annex1_Library Prep'!$D$125, 'Annex1_Library Prep'!$E$125:$E$130,IF('Data entry'!$C$21='Annex1_Library Prep'!$D$131, 'Annex1_Library Prep'!$E$131:$E$134, IF('Data entry'!$C$21='Annex1_Library Prep'!$D$135, 'Annex1_Library Prep'!$E$135:$E$138,IF('Data entry'!$C$21='Annex1_Library Prep'!$D$139, 'Annex1_Library Prep'!$E$139:$E$143,IF('Data entry'!$C$21='Annex1_Library Prep'!$D$144, 'Annex1_Library Prep'!$E$144:$E$146,IF('Data entry'!$C$21='Annex1_Library Prep'!$D$147, 'Annex1_Library Prep'!$E$147:$E$148,IF('Data entry'!$C$21='Annex1_Library Prep'!$D$149, 'Annex1_Library Prep'!$E$149:$E$153,IF('Data entry'!$C$21='Annex1_Library Prep'!$D$154, 'Annex1_Library Prep'!$E$154:$E$158,IF('Data entry'!$C$21='Annex1_Library Prep'!$D$159, 'Annex1_Library Prep'!$E$159:$E$162,IF('Data entry'!$C$21='Annex1_Library Prep'!$D$163, 'Annex1_Library Prep'!$E$163:$E$166,IF('Data entry'!$C$21='Annex1_Library Prep'!$D$167, 'Annex1_Library Prep'!$E$167:$E$170,IF('Data entry'!$C$21='Annex1_Library Prep'!$D$171, 'Annex1_Library Prep'!$E$171:$E$172,IF('Data entry'!$C$21='Annex1_Library Prep'!$D$173, 'Annex1_Library Prep'!$E$173:$E$176,IF('Data entry'!$C$21='Annex1_Library Prep'!$D$177, 'Annex1_Library Prep'!$E$177:$E$180,IF('Data entry'!$C$21='Annex1_Library Prep'!$D$181, 'Annex1_Library Prep'!$E$181:$E$184,IF('Data entry'!$C$21='Annex1_Library Prep'!$D$185, 'Annex1_Library Prep'!$E$185:$E$188,IF('Data entry'!$C$21='Annex1_Library Prep'!$D$189, 'Annex1_Library Prep'!$E$189:$E$193,IF('Data entry'!$C$21='Annex1_Library Prep'!$D$194, 'Annex1_Library Prep'!$E$194:$E$195,IF('Data entry'!$C$21='Annex1_Library Prep'!$D$196, 'Annex1_Library Prep'!$E$196:$E$200, Language!B388))))))))))))))))))))))))))))))))))))))} -> Illumina DNA Prep, (M) Tagmentation (96 Samples, IPB) | I6: =IF('Data entry'!$C$21='Annex1_Library Prep'!$P$4, IF(Equipment!$H$42>=1, ROUNDUP(((1+'Data entry'!$C$33)*((1/'Data entry'!$C$37)*(('Data entry'!$C$16+'Data entry'!$C$16*'Data entry'!$C$23)+'Annex1_Library Prep'!$H$50))),0), ROUNDUP((1/'Data entry'!$C$37)*(('Data entry'!$C$16+'Data entry'!$C$16*'Data entry'!$C$23)+'Annex1_Library Prep'!$H$50),0)), IFERROR(VLOOKUP(H6,'Annex1_Library Prep'!$E$52:$K$200,4,FALSE),"") ) -> 7 | J6: =IFERROR(VLOOKUP(H6,'Annex1_Library Prep'!$E$52:$K$200,7,FALSE),"") -> 4153 | K6: =IFERROR(I6*J6,0) -> 29071 | L6: =IFERROR($K6/(COUNTIF($B6:$F6,"Yes")),0) -> 29071 | O6: =(IFERROR($O$2*K6,"")) -> 0
B7: No | C7: No | D7: No | E7: Yes | F7: No | H7: Illumina DNA/RNA Unique Dual Indexes Sets A, B, C, D, Tagmentation (96 Indexes, 96 Samples/set) | I7: =IFERROR(VLOOKUP(H7,'Annex1_Library Prep'!$E$52:$K$200,4,FALSE),"") -> 7 | J7: =IFERROR(VLOOKUP(H7,'Annex1_Library Prep'!$E$52:$K$200,7,FALSE),"") -> 408 | K7: =IFERROR(I7*J7,0) -> 2856 | L7: =IFERROR($K7/(COUNTIF($B7:$F7,"Yes")),0) -> 2856 | M7: =IF($J$7=0, Language!$B$396,"") | O7: =(IFERROR($O$2*K7,"")) -> 0
B8: No | C8: No | D8: No | E8: Yes | F8: No | H8: RT-PCR reagents | I8: =IFERROR(VLOOKUP(H8,'Annex1_Library Prep'!$E$52:$K$200,4,FALSE),"") -> 7 | J8: =IFERROR(VLOOKUP(H8,'Annex1_Library Prep'!$E$52:$K$200,7,FALSE),"") -> 460 | K8: =IFERROR(I8*J8,0) -> 3220 | L8: =IFERROR($K8/(COUNTIF($B8:$F8,"Yes")),0) -> 3220 | O8: =(IFERROR($O$2*K8,"")) -> 0
B9: No | C9: No | D9: No | E9: Yes | F9: No | H9: Target specific primers | I9: =IFERROR(VLOOKUP(H9,'Annex1_Library Prep'!$E$52:$K$200,4,FALSE),"") -> 1 | J9: =IFERROR(VLOOKUP(H9,'Annex1_Library Prep'!$E$52:$K$200,7,FALSE),"") -> 65 | K9: =IFERROR(I9*J9,0) -> 65 | L9: =IFERROR($K9/(COUNTIF($B9:$F9,"Yes")),0) -> 65 | O9: =(IFERROR($O$2*K9,"")) -> 0
B10: No | C10: No | D10: No | E10: Yes | F10: No | I10: =IFERROR(VLOOKUP(H10,'Annex1_Library Prep'!$E$52:$K$200,4,FALSE),"") | J10: =IFERROR(VLOOKUP(H10,'Annex1_Library Prep'!$E$52:$K$200,7,FALSE),"") | K10: =IFERROR(I10*J10,0) -> 0 | L10: =IFERROR($K10/(COUNTIF($B10:$F10,"Yes")),0) -> 0 | O10: =(IFERROR($O$2*K10,"")) -> 0
B11: No | C11: No | D11: No | E11: Yes | F11: No | I11: =IFERROR(VLOOKUP(H11,'Annex1_Library Prep'!$E$52:$K$200,4,FALSE),"") | J11: =IFERROR(VLOOKUP(H11,'Annex1_Library Prep'!$E$52:$K$200,7,FALSE),"") | K11: =IFERROR(I11*J11,0) -> 0 | L11: =IFERROR($K11/(COUNTIF($B11:$F11,"Yes")),0) -> 0 | O11: =(IFERROR($O$2*K11,"")) -> 0
B12: No | C12: No | D12: No | E12: Yes | F12: No | I12: =IFERROR(VLOOKUP(H12,'Annex1_Library Prep'!$E$52:$K$200,4,FALSE),"") | J12: =IFERROR(VLOOKUP(H12,'Annex1_Library Prep'!$E$52:$K$200,7,FALSE),"") | K12: =IFERROR(I12*J12,0) -> 0 | L12: =IFERROR($K12/(COUNTIF($B12:$F12,"Yes")),0) -> 0 | O12: =(IFERROR($O$2*K12,"")) -> 0
B13: No | C13: No | D13: No | E13: Yes | F13: No | I13: =IFERROR(VLOOKUP(H13,'Annex1_Library Prep'!$E$52:$K$200,4,FALSE),"") | J13: =IFERROR(VLOOKUP(H13,'Annex1_Library Prep'!$E$52:$K$200,7,FALSE),"") | K13: =IFERROR(I13*J13,0) -> 0 | L13: =IFERROR($K13/(COUNTIF($B13:$F13,"Yes")),0) -> 0 | O13: =(IFERROR($O$2*K13,"")) -> 0
B14: No | C14: No | D14: No | E14: Yes | F14: No | I14: =IFERROR(VLOOKUP(H14,'Annex1_Library Prep'!$E$52:$K$200,4,FALSE),"") | J14: =IFERROR(VLOOKUP(H14,'Annex1_Library Prep'!$E$52:$K$200,7,FALSE),"") | K14: =IFERROR(I14*J14,0) -> 0 | L14: =IFERROR($K14/(COUNTIF($B14:$F14,"Yes")),0) -> 0 | O14: =(IFERROR($O$2*K14,"")) -> 0
B15: No | C15: No | D15: No | E15: No | F15: Yes | G15: ='Annex3_Reagents and Consumables'!B113 -> Reagent | H15: =IFERROR(IF('Data entry'!$F$18='Annex3_Reagents and Consumables'!O2,Language!B387,'Data entry'!$F$18),"") -> Enter the name of the sequencing reagent for platform 2 here | I15: =IFERROR(IF('Data entry'!$F$21='Annex1_Library Prep'!$D$86,0, IF('Data entry'!$F$18='Annex3_Reagents and Consumables'!$O$2,'Data entry'!$F$40*'Data entry'!$F$28,VLOOKUP('Data entry'!$F$18,'Annex3_Reagents and Consumables'!$B$3:$F$83, 5,FALSE))),"") -> 21 | J15: =IFERROR(VLOOKUP('Data entry'!$F$18,'Annex3_Reagents and Consumables'!$B$3:$F$83, 2,FALSE),"") | K15: =IFERROR(I15*J15,0) -> 0 | L15: =IFERROR($K15/(COUNTIF($B15:$F15,"Yes")),0) -> 0 | O15: =(IFERROR($O$2*K15,"")) -> 0
B16: No | C16: No | D16: No | E16: Yes | F16: No | G16: =Language!B34 -> NGS library preparation | H16: {=IF('Data entry'!$F$21='Annex1_Library Prep'!$T$4,Language!B389,IF('Data entry'!$F$21='Annex1_Library Prep'!$D$52, 'Annex1_Library Prep'!$E$52:$E$54,IF('Data entry'!$F$21='Annex1_Library Prep'!$D$55, 'Annex1_Library Prep'!$E$55:$E$58,IF('Data entry'!$F$21='Annex1_Library Prep'!$D$59, 'Annex1_Library Prep'!$E$59:$E$61,IF('Data entry'!$F$21='Annex1_Library Prep'!$D$62, 'Annex1_Library Prep'!$E$62,IF('Data entry'!$F$21='Annex1_Library Prep'!$D$63, 'Annex1_Library Prep'!$E$63:$E$65,IF('Data entry'!$F$21='Annex1_Library Prep'!$D$66, 'Annex1_Library Prep'!$E$66,IF('Data entry'!$F$21='Annex1_Library Prep'!$D$67, 'Annex1_Library Prep'!$E$67:$E$70,IF('Data entry'!$F$21='Annex1_Library Prep'!$D$71, 'Annex1_Library Prep'!$E$71:$E$72,IF('Data entry'!$F$21='Annex1_Library Prep'!$D$73, 'Annex1_Library Prep'!$E$73,IF('Data entry'!$F$21='Annex1_Library Prep'!$D$74, 'Annex1_Library Prep'!$E$74:$E$77,IF('Data entry'!$F$21='Annex1_Library Prep'!$D$78, 'Annex1_Library Prep'!$E$78:$E$81,IF('Data entry'!$F$21='Annex1_Library Prep'!$D$82, 'Annex1_Library Prep'!$E$82:$E$85,IF('Data entry'!$F$21='Annex1_Library Prep'!$D$86, 'Annex1_Library Prep'!$E$86:$E$88,IF('Data entry'!$F$21='Annex1_Library Prep'!$D$89, 'Annex1_Library Prep'!$E$89:$E$97,IF('Data entry'!$F$21='Annex1_Library Prep'!$D$98, 'Annex1_Library Prep'!$E$98:$E$104,IF('Data entry'!$F$21='Annex1_Library Prep'!$D$105, 'Annex1_Library Prep'!$E$105:$E$111,IF('Data entry'!$F$21='Annex1_Library Prep'!$D$112, 'Annex1_Library Prep'!$E$112:$E$118,IF('Data entry'!$F$21='Annex1_Library Prep'!$D$119, 'Annex1_Library Prep'!$E$119:$E$124, IF('Data entry'!$F$21='Annex1_Library Prep'!$D$125, 'Annex1_Library Prep'!$E$125:$E$130,IF('Data entry'!$F$21='Annex1_Library Prep'!$D$131, 'Annex1_Library Prep'!$E$131:$E$134, IF('Data entry'!$F$21='Annex1_Library Prep'!$D$135, 'Annex1_Library Prep'!$E$135:$E$138,IF('Data entry'!$F$21='Annex1_Library Prep'!$D$139, 'Annex1_Library Prep'!$E$139:$E$143,IF('Data entry'!$F$21='Annex1_Library Prep'!$D$144, 'Annex1_Library Prep'!$E$144:$E$146,IF('Data entry'!$F$21='Annex1_Library Prep'!$D$147, 'Annex1_Library Prep'!$E$147:$E$148,IF('Data entry'!$F$21='Annex1_Library Prep'!$D$149, 'Annex1_Library Prep'!$E$149:$E$153,IF('Data entry'!$F$21='Annex1_Library Prep'!$D$154, 'Annex1_Library Prep'!$E$154:$E$158,IF('Data entry'!$F$21='Annex1_Library Prep'!$D$159, 'Annex1_Library Prep'!$E$159:$E$162,IF('Data entry'!$F$21='Annex1_Library Prep'!$D$163, 'Annex1_Library Prep'!$E$163:$E$166,IF('Data entry'!$F$21='Annex1_Library Prep'!$D$167, 'Annex1_Library Prep'!$E$167:$E$170,IF('Data entry'!$F$21='Annex1_Library Prep'!$D$171, 'Annex1_Library Prep'!$E$171:$E$172,IF('Data entry'!$F$21='Annex1_Library Prep'!$D$173, 'Annex1_Library Prep'!$E$173:$E$176,IF('Data entry'!$F$21='Annex1_Library Prep'!$D$177, 'Annex1_Library Prep'!$E$177:$E$180,IF('Data entry'!$F$21='Annex1_Library Prep'!$D$181, 'Annex1_Library Prep'!$E$181:$E$184,IF('Data entry'!$F$21='Annex1_Library Prep'!$D$185, 'Annex1_Library Prep'!$E$185:$E$188,IF('Data entry'!$F$21='Annex1_Library Prep'!$D$189, 'Annex1_Library Prep'!$E$189:$E$193,IF('Data entry'!$F$21='Annex1_Library Prep'!$D$194, 'Annex1_Library Prep'!$E$194:$E$195,IF('Data entry'!$F$21='Annex1_Library Prep'!$D$196, 'Annex1_Library Prep'!$E$196:$E$200, Language!B388))))))))))))))))))))))))))))))))))))))} -> Enter the name of the library preparation kit for platform 2 here | I16: =IF('Data entry'!$F$21='Annex1_Library Prep'!$T$4, IF(Equipment!$H$42>=1, ROUNDUP(((1+'Data entry'!$C$33)*((1/'Data entry'!$F$37)*(('Data entry'!$F$16+'Data entry'!$F$16*'Data entry'!$F$23)+'Annex1_Library Prep'!$I$50))),0), ROUNDUP((1/'Data entry'!$F$37)*(('Data entry'!$F$16+'Data entry'!$F$16*'Data entry'!$F$23)+'Annex1_Library Prep'!$I$50),0)), IFERROR(VLOOKUP(H16,'Annex1_Library Prep'!$E$52:$K$200,5,FALSE),"") ) -> 4 | J16: =IFERROR(VLOOKUP(H16,'Annex1_Library Prep'!$E$52:$K$200,7,FALSE),"") | K16: =IFERROR(I16*J16,0) -> 0 | L16: =IFERROR($K16/(COUNTIF($B16:$F16,"Yes")),0) -> 0 | O16: =(IFERROR($O$2*K16,"")) -> 0
B17: No | C17: No | D17: No | E17: Yes | F17: No | I17: =IFERROR(VLOOKUP(H17,'Annex1_Library Prep'!$E$52:$K$200,5,FALSE),"") | J17: =IFERROR(VLOOKUP(H17,'Annex1_Library Prep'!$E$52:$K$200,7,FALSE),"") | K17: =IFERROR(I17*J17,0) -> 0 | L17: =IFERROR($K17/(COUNTIF($B17:$F17,"Yes")),0) -> 0 | M17: =IF($J$17=0,Language!$B$396,"") | O17: =(IFERROR($O$2*K17,"")) -> 0
B18: No | C18: No | D18: No | E18: Yes | F18: No | I18: =IFERROR(VLOOKUP(H18,'Annex1_Library Prep'!$E$52:$K$200,5,FALSE),"") | J18: =IFERROR(VLOOKUP(H18,'Annex1_Library Prep'!$E$52:$K$200,7,FALSE),"") | K18: =IFERROR(I18*J18,0) -> 0 | L18: =IFERROR($K18/(COUNTIF($B18:$F18,"Yes")),0) -> 0 | O18: =(IFERROR($O$2*K18,"")) -> 0
B19: No | C19: No | D19: No | E19: Yes | F19: No | I19: =IFERROR(VLOOKUP(H19,'Annex1_Library Prep'!$E$52:$K$200,5,FALSE),"") | J19: =IFERROR(VLOOKUP(H19,'Annex1_Library Prep'!$E$52:$K$200,7,FALSE),"") | K19: =IFERROR(I19*J19,0) -> 0 | L19: =IFERROR($K19/(COUNTIF($B19:$F19,"Yes")),0) -> 0 | O19: =(IFERROR($O$2*K19,"")) -> 0
B20: No | C20: No | D20: No | E20: Yes | F20: No | I20: =IFERROR(VLOOKUP(H20,'Annex1_Library Prep'!$E$52:$K$200,5,FALSE),"") | J20: =IFERROR(VLOOKUP(H20,'Annex1_Library Prep'!$E$52:$K$200,7,FALSE),"") | K20: =IFERROR(I20*J20,0) -> 0 | L20: =IFERROR($K20/(COUNTIF($B20:$F20,"Yes")),0) -> 0 | O20: =(IFERROR($O$2*K20,"")) -> 0
B21: No | C21: No | D21: No | E21: Yes | F21: No | I21: =IFERROR(VLOOKUP(H21,'Annex1_Library Prep'!$E$52:$K$200,5,FALSE),"") | J21: =IFERROR(VLOOKUP(H21,'Annex1_Library Prep'!$E$52:$K$200,7,FALSE),"") | K21: =IFERROR(I21*J21,0) -> 0 | L21: =IFERROR($K21/(COUNTIF($B21:$F21,"Yes")),0) -> 0 | O21: =(IFERROR($O$2*K21,"")) -> 0
B22: No | C22: No | D22: No | E22: Yes | F22: No | I22: =IFERROR(VLOOKUP(H22,'Annex1_Library Prep'!$E$52:$K$200,5,FALSE),"") | J22: =IFERROR(VLOOKUP(H22,'Annex1_Library Prep'!$E$52:$K$200,7,FALSE),"") | K22: =IFERROR(I22*J22,0) -> 0 | L22: =IFERROR($K22/(COUNTIF($B22:$F22,"Yes")),0) -> 0 | O22: =(IFERROR($O$2*K22,"")) -> 0
B23: No | C23: No | D23: No | E23: Yes | F23: No | I23: =IFERROR(VLOOKUP(H23,'Annex1_Library Prep'!$E$52:$K$200,5,FALSE),"") | J23: =IFERROR(VLOOKUP(H23,'Annex1_Library Prep'!$E$52:$K$200,7,FALSE),"") | K23: =IFERROR(I23*J23,0) -> 0 | L23: =IFERROR($K23/(COUNTIF($B23:$F23,"Yes")),0) -> 0 | O23: =(IFERROR($O$2*K23,"")) -> 0
B24: No | C24: No | D24: No | E24: Yes | F24: No | I24: =IFERROR(VLOOKUP(H24,'Annex1_Library Prep'!$E$52:$K$200,5,FALSE),"") | J24: =IFERROR(VLOOKUP(H24,'Annex1_Library Prep'!$E$52:$K$200,7,FALSE),"") | K24: =IFERROR(I24*J24,0) -> 0 | L24: =IFERROR($K24/(COUNTIF($B24:$F24,"Yes")),0) -> 0 | O24: =(IFERROR($O$2*K24,"")) -> 0
B25: No | C25: No | D25: No | E25: Yes | F25: No | G25: =IF('Data entry'!$C$22='Annex1_Library Prep'!$Z$5, IF('Data entry'!C21='Annex1_Library Prep'!P4, Language!B383, IF(VLOOKUP('Data entry'!$C$21, 'Annex1_Library Prep'!$D$52:$L$200, 9, FALSE)='Annex1_Library Prep'!$Z$5, "", Language!B383) ), "" ) | H25: =IF('Data entry'!$C$22='Annex1_Library Prep'!$Z$5, IF('Data entry'!C21='Annex1_Library Prep'!P4, Language!B384, IF(VLOOKUP('Data entry'!$C$21, 'Annex1_Library Prep'!$D$52:$L$200, 9, FALSE)='Annex1_Library Prep'!$Z$5, "", Language!B384) ), "" ) | K25: =IFERROR(I25*J25,0) -> 0 | L25: =IFERROR($K25/(COUNTIF($B25:$F25,"Yes")),0) -> 0 | M25: =IF(ISNUMBER(SEARCH(Language!B384,$H$25)),Language!B456,"") | O25: =(IFERROR($O$2*K25,"")) -> 0
B26: No | C26: No | D26: No | E26: Yes | F26: No | G26: =IF('Data entry'!$F$22='Annex1_Library Prep'!$Z$5, IF('Data entry'!F21='Annex1_Library Prep'!T4, Language!B383, IF(VLOOKUP('Data entry'!$F$21, 'Annex1_Library Prep'!$D$52:$L$200, 9, FALSE)='Annex1_Library Prep'!$Z$5, "", Language!B383)), "") | H26: =IF('Data entry'!$F$22='Annex1_Library Prep'!$Z$5, IF('Data entry'!F21='Annex1_Library Prep'!T4, Language!B385, IF(VLOOKUP('Data entry'!$F$21, 'Annex1_Library Prep'!$D$52:$L$200, 9, FALSE)='Annex1_Library Prep'!$Z$5, "", Language!B385)), "") | K26: =IFERROR(I26*J26,0) -> 0 | L26: =IFERROR($K26/(COUNTIF($B26:$F26,"Yes")),0) -> 0 | M26: =IF(ISNUMBER(SEARCH(Language!B385,$H$26)),Language!B457,"") | O26: =(IFERROR($O$2*K26,"")) -> 0
B27: =Language!B31 -> Sample receipt | C27: =Language!B32 -> Nucleic acid extraction | D27: =Language!B33 -> PCR testing | E27: =Language!B34 -> NGS library preparation | F27: =Language!B35 -> Sequencing | G27: =Language!B64 -> Reagent/consumable | H27: =Language!B65 -> Item | I27: =Language!B66 -> Quantity | J27: =Language!B67 -> Price per unit | K27: =Language!B68 -> Total cost | L27: =Language!B367 -> Distributed cost – per workflow | O27: =$O$2*K27 -> #VALUE!
F28: Workflow step | G28: Reagent/Consumable | H28: Item | I28: Quantity | J28: Price per unit | K28: Total cost | O28: =$O$2*K28 -> #VALUE!
B29: Yes | C29: No | D29: No | E29: No | F29: No | G29: ='Annex3_Reagents and Consumables'!B93 -> Consumable | H29: ='Annex3_Reagents and Consumables'!C93 -> Viral transport media sampling kits with 10 ml tubes and swabs (50-pck) | I29: =IFERROR(VLOOKUP(H29,'Annex3_Reagents and Consumables'!$C$93:$J$129,7,FALSE),0) -> 20 | J29: =IFERROR(VLOOKUP(H29,'Annex3_Reagents and Consumables'!$C$93:$J$129,8,FALSE),0) -> 78 | K29: =IFERROR(I29*J29,0) -> 1560 | L29: =IFERROR($K29/(COUNTIF($B29:$F29,"Yes")),0) -> 1560 | O29: =IFERROR($O$2*K29,"") -> 0
B30: Yes | C30: No | D30: No | E30: No | F30: No | G30: ='Annex3_Reagents and Consumables'!B94 -> Consumable | H30: ='Annex3_Reagents and Consumables'!C94 -> Specimen transport packaging (ambient) (150-pck) | I30: =IFERROR(VLOOKUP(H30,'Annex3_Reagents and Consumables'!$C$93:$J$129,7,FALSE),0) -> 8 | J30: =IFERROR(VLOOKUP(H30,'Annex3_Reagents and Consumables'!$C$93:$J$129,8,FALSE),0) -> 472.68 | K30: =IFERROR(I30*J30,0) -> 3781.44 | L30: =IFERROR($K30/(COUNTIF($B30:$F30,"Yes")),0) -> 3781.44 | O30: =IFERROR($O$2*K30,"") -> 0
B31: Yes | C31: No | D31: No | E31: No | F31: No | G31: ='Annex3_Reagents and Consumables'!B95 -> Consumable | H31: ='Annex3_Reagents and Consumables'!C95 -> Specimen transport packaging (2–8C) (150-pck) | I31: =IFERROR(VLOOKUP(H31,'Annex3_Reagents and Consumables'!$C$93:$J$129,7,FALSE),0) -> 8 | J31: =IFERROR(VLOOKUP(H31,'Annex3_Reagents and Consumables'!$C$93:$J$129,8,FALSE),0) -> 472.68 | K31: =IFERROR(I31*J31,0) -> 3781.44 | L31: =IFERROR($K31/(COUNTIF($B31:$F31,"Yes")),0) -> 3781.44 | O31: =IFERROR($O$2*K31,"") -> 0
B32: Yes | C32: No | D32: No | E32: No | F32: No | G32: ='Annex3_Reagents and Consumables'!B96 -> Consumable | H32: ='Annex3_Reagents and Consumables'!C96 -> Specimen transport packaging (-20C) (150-pck) | I32: =IFERROR(VLOOKUP(H32,'Annex3_Reagents and Consumables'!$C$93:$J$129,7,FALSE),0) -> 8 | J32: =IFERROR(VLOOKUP(H32,'Annex3_Reagents and Consumables'!$C$93:$J$129,8,FALSE),0) -> 472.68 | K32: =IFERROR(I32*J32,0) -> 3781.44 | L32: =IFERROR($K32/(COUNTIF($B32:$F32,"Yes")),0) -> 3781.44 | O32: =IFERROR($O$2*K32,"") -> 0
B33: Yes | C33: No | D33: No | E33: No | F33: No | G33: ='Annex3_Reagents and Consumables'!B97 -> Consumable | H33: ='Annex3_Reagents and Consumables'!C97 -> Cold packs (24-pck) | I33: =IFERROR(VLOOKUP(H33,'Annex3_Reagents and Consumables'!$C$93:$J$129,7,FALSE),0) -> 2 | J33: =IFERROR(VLOOKUP(H33,'Annex3_Reagents and Consumables'!$C$93:$J$129,8,FALSE),0) -> 179.664 | K33: =IFERROR(I33*J33,0) -> 359.328 | L33: =IFERROR($K33/(COUNTIF($B33:$F33,"Yes")),0) -> 359.328 | O33: =IFERROR($O$2*K33,"") -> 0
B34: No | C34: Yes | D34: Yes | E34: No | F34: No | G34: ='Annex3_Reagents and Consumables'!B98 -> Consumable | H34: ='Annex3_Reagents and Consumables'!C98 -> PCR plates (10/pack) 96-well reaction plate | I34: =IFERROR(VLOOKUP(H34,'Annex3_Reagents and Consumables'!$C$93:$J$129,7,FALSE),0) -> 9 | J34: =IFERROR(VLOOKUP(H34,'Annex3_Reagents and Consumables'!$C$93:$J$129,8,FALSE),0) -> 33.168 | K34: =IFERROR(I34*J34,0) -> 298.512 | L34: =IFERROR($K34/(COUNTIF($B34:$F34,"Yes")),0) -> 149.256 | O34: =IFERROR($O$2*K34,"") -> 0
B35: No | C35: Yes | D35: Yes | E35: No | F35: No | G35: ='Annex3_Reagents and Consumables'!B99 -> Consumable | H35: ='Annex3_Reagents and Consumables'!C99 -> PCR plate covers adhesive film (1 cover per plate) | I35: =IFERROR(VLOOKUP(H35,'Annex3_Reagents and Consumables'!$C$93:$J$129,7,FALSE),0) -> 2 | J35: =IFERROR(VLOOKUP(H35,'Annex3_Reagents and Consumables'!$C$93:$J$129,8,FALSE),0) -> 141.588 | K35: =IFERROR(I35*J35,0) -> 283.176 | L35: =IFERROR($K35/(COUNTIF($B35:$F35,"Yes")),0) -> 141.588 | O35: =IFERROR($O$2*K35,"") -> 0
B36: No | C36: Yes | D36: Yes | E36: Yes | F36: Yes | G36: ='Annex3_Reagents and Consumables'!B100 -> Consumable | H36: ='Annex3_Reagents and Consumables'!C100 -> Pipette filter tips 10uL (96 tips x 10 racks) | I36: =IFERROR(VLOOKUP(H36,'Annex3_Reagents and Consumables'!$C$93:$J$129,7,FALSE),0) -> 9 | J36: =IFERROR(VLOOKUP(H36,'Annex3_Reagents and Consumables'!$C$93:$J$129,8,FALSE),0) -> 184.8 | K36: =IFERROR(I36*J36,0) -> 1663.2 | L36: =IFERROR($K36/(COUNTIF($B36:$F36,"Yes")),0) -> 415.8 | O36: =IFERROR($O$2*K36,"") -> 0
B37: No | C37: Yes | D37: Yes | E37: Yes | F37: Yes | G37: ='Annex3_Reagents and Consumables'!B102 -> Consumable | H37: ='Annex3_Reagents and Consumables'!C102 -> Pipette filter tips 200uL (96 tips x 10 racks) | I37: =IFERROR(VLOOKUP(H37,'Annex3_Reagents and Consumables'!$C$93:$J$129,7,FALSE),0) -> 9 | J37: =IFERROR(VLOOKUP(H37,'Annex3_Reagents and Consumables'!$C$93:$J$129,8,FALSE),0) -> 56.4 | K37: =IFERROR(I37*J37,0) -> 507.6 | L37: =IFERROR($K37/(COUNTIF($B37:$F37,"Yes")),0) -> 126.9 | O37: =IFERROR($O$2*K37,"") -> 0
B38: No | C38: Yes | D38: Yes | E38: Yes | F38: Yes | G38: ='Annex3_Reagents and Consumables'!B103 -> Consumable | H38: ='Annex3_Reagents and Consumables'!C103 -> Pipette filter tips 1000uL (96 tips x 10 racks) | I38: =IFERROR(VLOOKUP(H38,'Annex3_Reagents and Consumables'!$C$93:$J$129,7,FALSE),0) -> 6 | J38: =IFERROR(VLOOKUP(H38,'Annex3_Reagents and Consumables'!$C$93:$J$129,8,FALSE),0) -> 163.2 | K38: =IFERROR(I38*J38,0) -> 979.2 | L38: =IFERROR($K38/(COUNTIF($B38:$F38,"Yes")),0) -> 244.8 | O38: =IFERROR($O$2*K38,"") -> 0
B39: No | C39: Yes | D39: Yes | E39: No | F39: No | G39: ='Annex3_Reagents and Consumables'!B104 -> Consumable | H39: ='Annex3_Reagents and Consumables'!C104 -> 0.2mL PCR tubes, thin-walled (1000; strips) | I39: =IFERROR(VLOOKUP(H39,'Annex3_Reagents and Consumables'!$C$93:$J$129,7,FALSE),0) -> 7 | J39: =IFERROR(VLOOKUP(H39,'Annex3_Reagents and Consumables'!$C$93:$J$129,8,FALSE),0) -> 145.2 | K39: =IFERROR(I39*J39,0) -> 1016.4 | L39: =IFERROR($K39/(COUNTIF($B39:$F39,"Yes")),0) -> 508.2 | O39: =IFERROR($O$2*K39,"") -> 0
B40: No | C40: Yes | D40: Yes | E40: Yes | F40: Yes | G40: ='Annex3_Reagents and Consumables'!B105 -> Consumable | H40: ='Annex3_Reagents and Consumables'!C105 -> 1.5mL PCR tubes, LoBind (250) | I40: =IFERROR(VLOOKUP(H40,'Annex3_Reagents and Consumables'!$C$93:$J$129,7,FALSE),0) -> 9 | J40: =IFERROR(VLOOKUP(H40,'Annex3_Reagents and Consumables'!$C$93:$J$129,8,FALSE),0) -> 13.2 | K40: =IFERROR(I40*J40,0) -> 118.8 | L40: =IFERROR($K40/(COUNTIF($B40:$F40,"Yes")),0) -> 29.7 | O40: =IFERROR($O$2*K40,"") -> 0
B41: No | C41: Yes | D41: No | E41: Yes | F41: No | G41: ='Annex3_Reagents and Consumables'!B106 -> Consumable | H41: ='Annex3_Reagents and Consumables'!C106 -> 50mL conical tubes (100) | I41: =IFERROR(VLOOKUP(H41,'Annex3_Reagents and Consumables'!$C$93:$J$129,7,FALSE),0) -> 6 | J41: =IFERROR(VLOOKUP(H41,'Annex3_Reagents and Consumables'!$C$93:$J$129,8,FALSE),0) -> 160.8 | K41: =IFERROR(I41*J41,0) -> 964.8 | L41: =IFERROR($K41/(COUNTIF($B41:$F41,"Yes")),0) -> 482.4 | O41: =IFERROR($O$2*K41,"") -> 0
B42: No | C42: Yes | D42: No | E42: No | F42: No | G42: ='Annex3_Reagents and Consumables'!B110 -> Reagent | H42: ='Annex3_Reagents and Consumables'!C110 -> RNA extraction kit (250 reactions) | I42: =IFERROR(VLOOKUP(H42,'Annex3_Reagents and Consumables'!$C$93:$J$129,7,FALSE),0) -> 5 | J42: =IFERROR(VLOOKUP(H42,'Annex3_Reagents and Consumables'!$C$93:$J$129,8,FALSE),0) -> 722.592 | K42: =IFERROR(I42*J42,0) -> 3612.96 | L42: =IFERROR($K42/(COUNTIF($B42:$F42,"Yes")),0) -> 3612.96 | O42: =IFERROR($O$2*K42,"") -> 0
B43: No | C43: No | D43: Yes | E43: No | F43: No | G43: ='Annex3_Reagents and Consumables'!B111 -> Reagent | H43: ='Annex3_Reagents and Consumables'!C111 -> PCR testing kit (96 reactions) | I43: =IFERROR(VLOOKUP(H43,'Annex3_Reagents and Consumables'!$C$93:$J$129,7,FALSE),0) -> 11 | J43: =IFERROR(VLOOKUP(H43,'Annex3_Reagents and Consumables'!$C$93:$J$129,8,FALSE),0) -> 384 | K43: =IFERROR(I43*J43,0) -> 4224 | L43: =IFERROR($K43/(COUNTIF($B43:$F43,"Yes")),0) -> 4224 | O43: =IFERROR($O$2*K43,"") -> 0
B44: No | C44: No | D44: No | E44: Yes | F44: No | G44: ='Annex3_Reagents and Consumables'!B113 -> Reagent | H44: ='Annex3_Reagents and Consumables'!C113 -> Fluorometer DNA HS assay kit (500) | I44: =IFERROR(VLOOKUP(H44,'Annex3_Reagents and Consumables'!$C$93:$J$129,7,FALSE),0) -> 3 | J44: =IFERROR(VLOOKUP(H44,'Annex3_Reagents and Consumables'!$C$93:$J$129,8,FALSE),0) -> 210.54 | K44: =IFERROR(I44*J44,0) -> 631.62 | L44: =IFERROR($K44/(COUNTIF($B44:$F44,"Yes")),0) -> 631.62 | O44: =IFERROR($O$2*K44,"") -> 0
B45: No | C45: No | D45: No | E45: Yes | F45: No | G45: ='Annex3_Reagents and Consumables'!B114 -> Consumable | H45: ='Annex3_Reagents and Consumables'!C114 -> Fluorometer assay tubes (500) | I45: =IFERROR(VLOOKUP(H45,'Annex3_Reagents and Consumables'!$C$93:$J$129,7,FALSE),0) -> 3 | J45: =IFERROR(VLOOKUP(H45,'Annex3_Reagents and Consumables'!$C$93:$J$129,8,FALSE),0) -> 82 | K45: =IFERROR(I45*J45,0) -> 246 | L45: =IFERROR($K45/(COUNTIF($B45:$F45,"Yes")),0) -> 246 | O45: =IFERROR($O$2*K45,"") -> 0
B46: No | C46: Yes | D46: Yes | E46: Yes | F46: Yes | G46: ='Annex3_Reagents and Consumables'!B123 -> Reagent | H46: ='Annex3_Reagents and Consumables'!C123 -> (Molecular grade) nuclease free H2O | I46: =IFERROR(VLOOKUP(H46,'Annex3_Reagents and Consumables'!$C$93:$J$129,7,FALSE),0) -> 6 | J46: =IFERROR(VLOOKUP(H46,'Annex3_Reagents and Consumables'!$C$93:$J$129,8,FALSE),0) -> 123.6 | K46: =IFERROR(I46*J46,0) -> 741.6 | L46: =IFERROR($K46/(COUNTIF($B46:$F46,"Yes")),0) -> 185.4 | O46: =IFERROR($O$2*K46,"") -> 0
B47: No | C47: Yes | D47: No | E47: Yes | F47: No | G47: ='Annex3_Reagents and Consumables'!B122 -> Reagent | H47: ='Annex3_Reagents and Consumables'!C122 -> Ethanol, 99% lab grade, 1L | I47: =IFERROR(VLOOKUP(H47,'Annex3_Reagents and Consumables'!$C$93:$J$129,7,FALSE),0) -> 2 | J47: =IFERROR(VLOOKUP(H47,'Annex3_Reagents and Consumables'!$C$93:$J$129,8,FALSE),0) -> 222.5 | K47: =IFERROR(I47*J47,0) -> 445 | L47: =IFERROR($K47/(COUNTIF($B47:$F47,"Yes")),0) -> 222.5 | O47: =IFERROR($O$2*K47,"") -> 0
B48: No | C48: No | D48: No | E48: Yes | F48: No | G48: ='Annex3_Reagents and Consumables'!B118 -> Consumable | H48: ='Annex3_Reagents and Consumables'!C118 -> Reagent reservoir, sterile (pack of 50) | I48: =IFERROR(VLOOKUP(H48,'Annex3_Reagents and Consumables'!$C$93:$J$129,7,FALSE),0) -> 2 | J48: =IFERROR(VLOOKUP(H48,'Annex3_Reagents and Consumables'!$C$93:$J$129,8,FALSE),0) -> 141 | K48: =IFERROR(I48*J48,0) -> 282 | L48: =IFERROR($K48/(COUNTIF($B48:$F48,"Yes")),0) -> 282 | O48: =IFERROR($O$2*K48,"") -> 0
B49: No | C49: No | D49: No | E49: No | F49: Yes | G49: ='Annex3_Reagents and Consumables'!B119 -> Reagent | H49: ='Annex3_Reagents and Consumables'!C119 -> NaOH, 1N 100mL | I49: =IFERROR(VLOOKUP(H49,'Annex3_Reagents and Consumables'!$C$93:$J$129,7,FALSE),0) -> 1 | J49: =IFERROR(VLOOKUP(H49,'Annex3_Reagents and Consumables'!$C$93:$J$129,8,FALSE),0) -> 133.1 | K49: =IFERROR(I49*J49,0) -> 133.1 | L49: =IFERROR($K49/(COUNTIF($B49:$F49,"Yes")),0) -> 133.1 | O49: =IFERROR($O$2*K49,"") -> 0
B50: No | C50: No | D50: No | E50: No | F50: Yes | G50: ='Annex3_Reagents and Consumables'!B120 -> Reagent | H50: ='Annex3_Reagents and Consumables'!C120 -> Bleach, lab grade (4-6%, 1L) | I50: =IFERROR(VLOOKUP(H50,'Annex3_Reagents and Consumables'!$C$93:$J$129,7,FALSE),0) -> 1 | J50: =IFERROR(VLOOKUP(H50,'Annex3_Reagents and Consumables'!$C$93:$J$129,8,FALSE),0) -> 136.6 | K50: =IFERROR(I50*J50,0) -> 136.6 | L50: =IFERROR($K50/(COUNTIF($B50:$F50,"Yes")),0) -> 136.6 | O50: =IFERROR($O$2*K50,"") -> 0
B51: No | C51: No | D51: No | E51: No | F51: Yes | G51: ='Annex3_Reagents and Consumables'!B121 -> Reagent | H51: ='Annex3_Reagents and Consumables'!C121 -> Tween 20, 500 mL | I51: =IFERROR(VLOOKUP(H51,'Annex3_Reagents and Consumables'!$C$93:$J$129,7,FALSE),0) -> 2 | J51: =IFERROR(VLOOKUP(H51,'Annex3_Reagents and Consumables'!$C$93:$J$129,8,FALSE),0) -> 50.4 | K51: =IFERROR(I51*J51,0) -> 100.8 | L51: =IFERROR($K51/(COUNTIF($B51:$F51,"Yes")),0) -> 100.8 | O51: =IFERROR($O$2*K51,"") -> 0
B52: No | C52: No | D52: Yes | E52: No | F52: No | G52: ='Annex3_Reagents and Consumables'!B125 -> Reagent | H52: ='Annex3_Reagents and Consumables'!$C$125 -> Q5 Hot Start HiFi DNA Polymerase (500 units) | I52: =IFERROR(VLOOKUP(H52,'Annex3_Reagents and Consumables'!$C$93:$J$129,7,FALSE),0) -> 3 | J52: =IFERROR(VLOOKUP(H52,'Annex3_Reagents and Consumables'!$C$93:$J$129,8,FALSE),0) -> 600 | K52: =IFERROR(I52*J52,0) -> 1800 | L52: =IFERROR($K52/(COUNTIF($B52:$F52,"Yes")),0) -> 1800 | O52: =IFERROR($O$2*K52,"") -> 0
B53: No | C53: No | D53: Yes | E53: No | F53: No | G53: ='Annex3_Reagents and Consumables'!B126 -> Reagent | H53: ='Annex3_Reagents and Consumables'!$C$126 -> 10mM dNTP (5x1mL) | I53: =IFERROR(VLOOKUP(H53,'Annex3_Reagents and Consumables'!$C$93:$J$129,7,FALSE),0) -> 2 | J53: =IFERROR(VLOOKUP(H53,'Annex3_Reagents and Consumables'!$C$93:$J$129,8,FALSE),0) -> 1040 | K53: =IFERROR(I53*J53,0) -> 2080 | L53: =IFERROR($K53/(COUNTIF($B53:$F53,"Yes")),0) -> 2080 | O53: =IFERROR($O$2*K53,"") -> 0
B54: No | C54: No | D54: Yes | E54: No | F54: No | G54: ='Annex3_Reagents and Consumables'!B127 -> Reagent | H54: ='Annex3_Reagents and Consumables'!$C$127 -> dS DNA HS assay kit for fluoremeter (500) | I54: =IFERROR(VLOOKUP(H54,'Annex3_Reagents and Consumables'!$C$93:$J$129,7,FALSE),0) -> 3 | J54: =IFERROR(VLOOKUP(H54,'Annex3_Reagents and Consumables'!$C$93:$J$129,8,FALSE),0) -> 193 | K54: =IFERROR(I54*J54,0) -> 579 | L54: =IFERROR($K54/(COUNTIF($B54:$F54,"Yes")),0) -> 579 | O54: =IFERROR($O$2*K54,"") -> 0
B55: No | C55: No | D55: Yes | E55: No | F55: No | G55: ='Annex3_Reagents and Consumables'!B128 -> Reagent | H55: ='Annex3_Reagents and Consumables'!$C$128 -> High sensitivity DNA assay kit for bioanalyser (110 samples) | I55: =IFERROR(VLOOKUP(H55,'Annex3_Reagents and Consumables'!$C$93:$J$129,7,FALSE),0) -> 8 | J55: =IFERROR(VLOOKUP(H55,'Annex3_Reagents and Consumables'!$C$93:$J$129,8,FALSE),0) -> 824 | K55: =IFERROR(I55*J55,0) -> 6592 | L55: =IFERROR($K55/(COUNTIF($B55:$F55,"Yes")),0) -> 6592 | O55: =IFERROR($O$2*K55,"") -> 0
B56: No | C56: No | D56: Yes | E56: No | F56: No | G56: ='Annex3_Reagents and Consumables'!B124 -> Reagent | H56: ='Annex3_Reagents and Consumables'!$C$124 -> Universal One-Step RT-qPCR Kit (200 rxns) | I56: =IFERROR(VLOOKUP(H56,'Annex3_Reagents and Consumables'!$C$93:$J$129,7,FALSE),0) -> 5 | J56: =IFERROR(VLOOKUP(H56,'Annex3_Reagents and Consumables'!$C$93:$J$129,8,FALSE),0) -> 345 | K56: =IFERROR(I56*J56,0) -> 1725 | L56: =IFERROR($K56/(COUNTIF($B56:$F56,"Yes")),0) -> 1725 | O56: =IFERROR($O$2*K56,"") -> 0
B57: No | C57: No | D57: No | E57: Yes | F57: No | G57: ='Annex3_Reagents and Consumables'!B127 -> Reagent | H57: =IF('Annex1_Library Prep'!$M$5=TRUE,'Annex3_Reagents and Consumables'!$C$129, IF('Annex1_Library Prep'!$Q$5=TRUE,'Annex3_Reagents and Consumables'!$C$129,"")) -> ONT Flow cell wash kit | J57: =IFERROR(VLOOKUP(H57,'Annex3_Reagents and Consumables'!$C$93:$J$129,8,FALSE),0) -> 99 | K57: =IFERROR(I57*J57,0) -> 0 | L57: =IFERROR($K57/(COUNTIF($B57:$F57,"Yes")),0) -> 0 | O57: =IFERROR($O$2*K57,"") -> 0
K58: =IFERROR(I58*J58,0) -> 0 | L58: =IFERROR($K58/(COUNTIF($B58:$F58,"Yes")),0) -> 0 | O58: =IFERROR($O$2*K58,"") -> 0
K59: =IFERROR(I59*J59,0) -> 0 | L59: =IFERROR($K59/(COUNTIF($B59:$F59,"Yes")),0) -> 0 | O59: =IFERROR($O$2*K59,"") -> 0
K60: =IFERROR(I60*J60,0) -> 0 | L60: =IFERROR($K60/(COUNTIF($B60:$F60,"Yes")),0) -> 0 | O60: =IFERROR($O$2*K60,"") -> 0
K61: =IFERROR(I61*J61,0) -> 0 | L61: =IFERROR($K61/(COUNTIF($B61:$F61,"Yes")),0) -> 0 | O61: =IFERROR($O$2*K61,"") -> 0
K62: =IFERROR(I62*J62,0) -> 0 | L62: =IFERROR($K62/(COUNTIF($B62:$F62,"Yes")),0) -> 0 | O62: =IFERROR($O$2*K62,"") -> 0
K63: =IFERROR(I63*J63,0) -> 0 | L63: =IFERROR($K63/(COUNTIF($B63:$F63,"Yes")),0) -> 0 | O63: =IFERROR($O$2*K63,"") -> 0
K64: =IFERROR(I64*J64,0) -> 0 | L64: =IFERROR($K64/(COUNTIF($B64:$F64,"Yes")),0) -> 0 | O64: =IFERROR($O$2*K64,"") -> 0
K65: =IFERROR(I65*J65,0) -> 0 | L65: =IFERROR($K65/(COUNTIF($B65:$F65,"Yes")),0) -> 0 | O65: =IFERROR($O$2*K65,"") -> 0
K66: =IFERROR(I66*J66,0) -> 0 | L66: =IFERROR($K66/(COUNTIF($B66:$F66,"Yes")),0) -> 0 | O66: =IFERROR($O$2*K66,"") -> 0
K67: =IFERROR(I67*J67,0) -> 0 | L67: =IFERROR($K67/(COUNTIF($B67:$F67,"Yes")),0) -> 0 | O67: =IFERROR($O$2*K67,"") -> 0
K68: =IFERROR(I68*J68,0) -> 0 | L68: =IFERROR($K68/(COUNTIF($B68:$F68,"Yes")),0) -> 0 | O68: =IFERROR($O$2*K68,"") -> 0
K69: =IFERROR(I69*J69,0) -> 0 | L69: =IFERROR($K69/(COUNTIF($B69:$F69,"Yes")),0) -> 0 | O69: =IFERROR($O$2*K69,"") -> 0
... K105: =IFERROR(I105*J105,0) -> 0 | L105: =IFERROR($K105/(COUNTIF($B105:$F105,"Yes")),0) -> 0 | O105: =IFERROR($O$2*K105,"") -> 0
H108: =Language!B435 -> Calculated costs – Reagents and consumables
I109: =Language!B368 -> Both sequencers | J109: =Language!B362 -> Sequencer 1 | K109: =Language!B363 -> Sequencer 2
H110: =Language!B72 -> Sequencing and library preparation reagent cost with sample retests: | I110: =SUM(J110:K110) -> 98494 | J110: =SUM($K$5:$K$14,K25) -> 98494 | K110: =SUM($K$15:$K$24,K26) -> 0
H111: =Language!B399 -> Other reagents cost with sample retests: | I111: =SUM(J111:K111) -> 42425.016 | J111: =SUM(K29:K105)/'Data entry'!F31*('Data entry'!$C$16+'Data entry'!$C$16*'Data entry'!$C$23) -> 26802.808 | K111: =SUM(K29:K105)/'Data entry'!F31*('Data entry'!$F$16+'Data entry'!$F$16*'Data entry'!$F$23) -> 15622.208
H112: =Language!B73 -> Incidentals (waste bags, PPE, ethanol, etc.): | I112: =SUM(J112:K112) -> 12134.88 | J112: ='Annex3_Reagents and Consumables'!$K$146 -> 7182.29 | K112: ='Annex3_Reagents and Consumables'!$L$146 -> 4952.59
H113: =Language!B75 -> Anticipated annual cost due to sample retests: | I113: =SUM(J113:K113) -> 6711.9559 | J113: =SUM(J110:J112)/(1+'Data entry'!C23)*'Data entry'!C23 -> 6308.5285 | K113: =SUM(K110:K112)/(1+'Data entry'!F23)*'Data entry'!F23 -> 403.42741
H114: =Language!B74 -> Annual reagent and consumable cost without sample retests: | I114: =SUM(J114:K114) -> 146341.94 | J114: =SUM(J110:J112)-J113 -> 126170.57 | K114: =SUM(K110:K112)-K113 -> 20171.371
H115: =Language!B76 -> Total annual reagent and consumable cost: | I115: =SUM(J115:K115) -> 153053.9 | J115: =SUM(J110:J112) -> 132479.1 | K115: =SUM(K110:K112) -> 20574.798
H116: =Language!B77 -> Total reagent and consumable cost per sample: | I116: =$I$115/('Data entry'!$C$16+'Data entry'!$F$16) -> 191.31737 | J116: =IFERROR(J115/('Data entry'!$C$16),"") -> 264.9582 | K116: =IFERROR(K115/('Data entry'!$F$16),"") -> 68.58266

Sheet Equipment
A2: =Language!B78 -> Equipment | AA2: =Language!B92 -> Potential items for purchase to reach recommended equipment quantities
A3: =Language!B79 -> Flag for equipment | B3: =Language!B31 -> Sample receipt | C3: =Language!B32 -> Nucleic acid extraction | D3: =Language!B33 -> PCR testing | E3: =Language!B34 -> NGS library preparation | F3: =Language!B35 -> Sequencing | G3: =Language!B81 -> Item | H3: =Language!B82 -> Recommended quantity | I3: =Language!B83 -> Actual quantity (enter 0 if none) | J3: =Language!B84 -> Unit cost | K3: =Language!B85 -> Total cost | L3: =Language!B86 -> Recommended lifetime (years) | M3: =Language!B87 -> Age of equipment (new=0) | N3: =Language!B88 -> Depreciation value | O3: =Language!B89 -> Maintenance and calibration contract cost per year (default = 15%) | P3: =Language!B90 -> Percentage of use for sequencing of selected pathogens | Q3: =Language!B91 -> Annual equipment depreciation cost | R3: =Language!B344 -> Total annual equipment maintenance and calibration cost | S3: =Language!B345 -> Annual equipment operational cost | T3: =Language!B367 -> Distributed cost – per workflow | V3: =Language!B69 -> Local currency (reference only) | AA3: =Language!B93 -> Total cost | AB3: =Language!B94 -> Quantity | AC3: =Language!B95 -> Item
A4: Note for equipment | C4: Column2 | D4: Column3 | E4: Column1 | F4: Workflow step | G4: Item | H4: Recommended Quantity | I4: Actual Quantity (enter 0 if none) | J4: Unit cost | K4: Total cost | L4: Recommended lifetime (years) | M4: Age of equipment (new=0) | N4: Amortization value | O4: Maintenance contract cost per year | P4: Percentage of use for sequencing | Q4: Annual equipment armotization and maintenance cost | V4: local currency (reference only) | AA4: Total Cost | AB4: Quantity | AC4: Item
A5: =IF(AB5<>"","Buy", "") | B5: No | C5: No | D5: No | E5: No | F5: Yes | G5: =IF('Data entry'!$C$17=Annex2_Equipment!C4,Language!B391,'Data entry'!$C$17) -> Illumina MiSeq | H5: =IF($G5="Select Item",0,1) -> 1 | I5: 1 | J5: =IFERROR(VLOOKUP(G5,Annex2_Equipment!$C$5:$D$23,2,FALSE),0) -> 99000 | K5: =I5*J5 -> 99000 | L5: 8 | M5: 5 | N5: =IFERROR(K5/L5,0) -> 12375 | O5: =(I5*J5)*0.15 -> 14850 | P5: 1 | Q5: =N5*P5 -> 12375 | R5: =O5*P5 -> 14850 | S5: =Q5+R5 -> 27225 | T5: =IFERROR($S5/COUNTIF($B5:$F5,"Yes"),0) -> 27225 | V5: =IFERROR('Reagents and consumables'!$O$2*S5,"") -> 0 | AA5: =IF($M5<$L5,IF($I5<$H5,($H5-$I5)*$J5,""),$H5*$J5) | AB5: =IF($AA5<>"",$AA5/$J5,"") | AC5: =IF($AA5<>"",$G5,"")
A6: =IF(AB6<>"","Buy", "") | B6: No | C6: No | D6: No | E6: No | F6: Yes | G6: =IF('Data entry'!$F$17=Annex2_Equipment!C4,Language!B392,'Data entry'!$F$17) -> ONT GridION (Project Pack) | H6: =IF($G6="Select Item",0,1) -> 1 | I6: 1 | J6: =IFERROR(VLOOKUP(G6,Annex2_Equipment!$C$5:$D$23,2,FALSE),0) -> 67000 | K6: =I6*J6 -> 67000 | L6: 8 | M6: 5 | N6: =IFERROR(K6/L6,0) -> 8375 | O6: =(I6*J6)*0.15 -> 10050 | P6: 1 | Q6: =N6*P6 -> 8375 | R6: =O6*P6 -> 10050 | S6: =Q6+R6 -> 18425 | T6: =IFERROR($S6/COUNTIF($B6:$F6,"Yes"),0) -> 18425 | V6: =IFERROR('Reagents and consumables'!$O$2*S6,"") -> 0 | AA6: =IF($M6<$L6,IF($I6<$H6,($H6-$I6)*$J6,""),$H6*$J6) | AB6: =IF($AA6<>"",$AA6/$J6,"") | AC6: =IF($AA6<>"",$G6,"")
A7: =IF(AB7<>"","Buy", "") -> Buy | B7: No | C7: No | D7: Yes | E7: Yes | F7: No | G7: =Annex2_Equipment!C26 -> PCR workstation | H7: =VLOOKUP($G7,Annex2_Equipment!$C$26:$E$66,3,FALSE) -> 2 | I7: 1 | J7: =VLOOKUP($G7,Annex2_Equipment!$C$26:$E$66,2,FALSE) -> 3837.57 | K7: =I7*J7 -> 3837.57 | L7: 10 | M7: 2 | N7: =IFERROR(K7/L7,0) -> 383.757 | O7: =(I7*J7)*0.15 -> 575.6355 | P7: 0.5 | Q7: =N7*P7 -> 191.8785 | R7: =O7*P7 -> 287.81775 | S7: =Q7+R7 -> 479.69625 | T7: =IFERROR($S7/COUNTIF($B7:$F7,"Yes"),0) -> 239.84812 | V7: =IFERROR('Reagents and consumables'!$O$2*S7,"") -> 0 | AA7: =IF($M7<$L7,IF($I7<$H7,($H7-$I7)*$J7,""),$H7*$J7) -> 3837.57 | AB7: =IF($AA7<>"",$AA7/$J7,"") -> 1 | AC7: =IF($AA7<>"",$G7,"") -> PCR workstation
A8: =IF(AB8<>"","Buy", "") | B8: No | C8: No | D8: No | E8: Yes | F8: No | G8: =Annex2_Equipment!C27 -> Plate magnet (for 96 well plate) | H8: =VLOOKUP($G8,Annex2_Equipment!$C$26:$E$66,3,FALSE) -> 2 | I8: 2 | J8: =VLOOKUP($G8,Annex2_Equipment!$C$26:$E$66,2,FALSE) -> 1323.3 | K8: =I8*J8 -> 2646.6 | L8: 10 | N8: =IFERROR(K8/L8,0) -> 264.66 | O8: =(I8*J8)*0.15 -> 396.99 | P8: 1 | Q8: =N8*P8 -> 264.66 | R8: =O8*P8 -> 396.99 | S8: =Q8+R8 -> 661.65 | T8: =IFERROR($S8/COUNTIF($B8:$F8,"Yes"),0) -> 661.65 | V8: =IFERROR('Reagents and consumables'!$O$2*S8,"") -> 0 | AA8: =IF($M8<$L8,IF($I8<$H8,($H8-$I8)*$J8,""),$H8*$J8) | AB8: =IF($AA8<>"",$AA8/$J8,"") | AC8: =IF($AA8<>"",$G8,"")
A9: =IF(AB9<>"","Buy", "") | B9: No | C9: No | D9: No | E9: Yes | F9: No | G9: =Annex2_Equipment!C28 -> Magnetic rack (for 12 1.5–2.0 mL tubes) | H9: =VLOOKUP($G9,Annex2_Equipment!$C$26:$E$66,3,FALSE) -> 4 | I9: 4 | J9: =VLOOKUP($G9,Annex2_Equipment!$C$26:$E$66,2,FALSE) -> 374.133 | K9: =I9*J9 -> 1496.532 | L9: 10 | N9: =IFERROR(K9/L9,0) -> 149.6532 | O9: =(I9*J9)*0.15 -> 224.4798 | P9: 1 | Q9: =N9*P9 -> 149.6532 | R9: =O9*P9 -> 224.4798 | S9: =Q9+R9 -> 374.133 | T9: =IFERROR($S9/COUNTIF($B9:$F9,"Yes"),0) -> 374.133 | V9: =IFERROR('Reagents and consumables'!$O$2*S9,"") -> 0 | AA9: =IF($M9<$L9,IF($I9<$H9,($H9-$I9)*$J9,""),$H9*$J9) | AB9: =IF($AA9<>"",$AA9/$J9,"") | AC9: =IF($AA9<>"",$G9,"")
A10: =IF(AB10<>"","Buy", "") -> Buy | B10: No | C10: No | D10: Yes | E10: Yes | F10: No | G10: =Annex2_Equipment!C29 -> PCR cooling plates/strip holders | H10: =VLOOKUP($G10,Annex2_Equipment!$C$26:$E$66,3,FALSE) -> 4 | I10: 1 | J10: =VLOOKUP($G10,Annex2_Equipment!$C$26:$E$66,2,FALSE) -> 84.21 | K10: =I10*J10 -> 84.21 | L10: 10 | N10: =IFERROR(K10/L10,0) -> 8.421 | O10: =(I10*J10)*0.15 -> 12.6315 | P10: 1 | Q10: =N10*P10 -> 8.421 | R10: =O10*P10 -> 12.6315 | S10: =Q10+R10 -> 21.0525 | T10: =IFERROR($S10/COUNTIF($B10:$F10,"Yes"),0) -> 10.52625 | V10: =IFERROR('Reagents and consumables'!$O$2*S10,"") -> 0 | AA10: =IF($M10<$L10,IF($I10<$H10,($H10-$I10)*$J10,""),$H10*$J10) -> 252.63 | AB10: =IF($AA10<>"",$AA10/$J10,"") -> 3 | AC10: =IF($AA10<>"",$G10,"") -> PCR cooling plates/strip holders
A11: =IF(AB11<>"","Buy", "") | B11: No | C11: No | D11: No | E11: No | F11: Yes | G11: =Annex2_Equipment!C30 -> Dry bath (heat block) | H11: =VLOOKUP($G11,Annex2_Equipment!$C$26:$E$66,3,FALSE) -> 1 | I11: 1 | J11: =VLOOKUP($G11,Annex2_Equipment!$C$26:$E$66,2,FALSE) -> 324.81 | K11: =I11*J11 -> 324.81 | L11: 10 | N11: =IFERROR(K11/L11,0) -> 32.481 | O11: =(I11*J11)*0.15 -> 48.7215 | P11: 1 | Q11: =N11*P11 -> 32.481 | R11: =O11*P11 -> 48.7215 | S11: =Q11+R11 -> 81.2025 | T11: =IFERROR($S11/COUNTIF($B11:$F11,"Yes"),0) -> 81.2025 | V11: =IFERROR('Reagents and consumables'!$O$2*S11,"") -> 0 | AA11: =IF($M11<$L11,IF($I11<$H11,($H11-$I11)*$J11,""),$H11*$J11) | AB11: =IF($AA11<>"",$AA11/$J11,"") | AC11: =IF($AA11<>"",$G11,"")
A12: =IF(AB12<>"","Buy", "") | B12: No | C12: Yes | D12: No | E12: No | F12: No | G12: =Annex2_Equipment!C31 -> Biosafety cabinet, class II, type A2 | H12: =VLOOKUP($G12,Annex2_Equipment!$C$26:$E$66,3,FALSE) -> 1 | I12: 1 | J12: =VLOOKUP($G12,Annex2_Equipment!$C$26:$E$66,2,FALSE) -> 12030 | K12: =I12*J12 -> 12030 | L12: 10 | N12: =IFERROR(K12/L12,0) -> 1203 | O12: =(I12*J12)*0.15 -> 1804.5 | P12: 1 | Q12: =N12*P12 -> 1203 | R12: =O12*P12 -> 1804.5 | S12: =Q12+R12 -> 3007.5 | T12: =IFERROR($S12/COUNTIF($B12:$F12,"Yes"),0) -> 3007.5 | V12: =IFERROR('Reagents and consumables'!$O$2*S12,"") -> 0 | AA12: =IF($M12<$L12,IF($I12<$H12,($H12-$I12)*$J12,""),$H12*$J12) | AB12: =IF($AA12<>"",$AA12/$J12,"") | AC12: =IF($AA12<>"",$G12,"")
A13: =IF(AB13<>"","Buy", "") | B13: No | C13: Yes | D13: No | E13: No | F13: No | G13: =Annex2_Equipment!C32 -> Water bath 5L | H13: =VLOOKUP($G13,Annex2_Equipment!$C$26:$E$66,3,FALSE) -> 1 | I13: 1 | J13: =VLOOKUP($G13,Annex2_Equipment!$C$26:$E$66,2,FALSE) -> 668.868 | K13: =I13*J13 -> 668.868 | L13: 10 | N13: =IFERROR(K13/L13,0) -> 66.8868 | O13: =(I13*J13)*0.15 -> 100.3302 | P13: 1 | Q13: =N13*P13 -> 66.8868 | R13: =O13*P13 -> 100.3302 | S13: =Q13+R13 -> 167.217 | T13: =IFERROR($S13/COUNTIF($B13:$F13,"Yes"),0) -> 167.217 | V13: =IFERROR('Reagents and consumables'!$O$2*S13,"") -> 0 | AA13: =IF($M13<$L13,IF($I13<$H13,($H13-$I13)*$J13,""),$H13*$J13) | AB13: =IF($AA13<>"",$AA13/$J13,"") | AC13: =IF($AA13<>"",$G13,"")
A14: =IF(AB14<>"","Buy", "") | B14: No | C14: Yes | D14: No | E14: No | F14: No | G14: =Annex2_Equipment!C33 -> Autoclave benchtop | H14: =VLOOKUP($G14,Annex2_Equipment!$C$26:$E$66,3,FALSE) -> 1 | I14: 1 | J14: =VLOOKUP($G14,Annex2_Equipment!$C$26:$E$66,2,FALSE) -> 4210.5 | K14: =I14*J14 -> 4210.5 | L14: 10 | N14: =IFERROR(K14/L14,0) -> 421.05 | O14: =(I14*J14)*0.15 -> 631.575 | P14: 1 | Q14: =N14*P14 -> 421.05 | R14: =O14*P14 -> 631.575 | S14: =Q14+R14 -> 1052.625 | T14: =IFERROR($S14/COUNTIF($B14:$F14,"Yes"),0) -> 1052.625 | V14: =IFERROR('Reagents and consumables'!$O$2*S14,"") -> 0 | AA14: =IF($M14<$L14,IF($I14<$H14,($H14-$I14)*$J14,""),$H14*$J14) | AB14: =IF($AA14<>"",$AA14/$J14,"") | AC14: =IF($AA14<>"",$G14,"")
A15: =IF(AB15<>"","Buy", "") | B15: No | C15: Yes | D15: Yes | E15: Yes | F15: No | G15: =Annex2_Equipment!C34 -> Vortex | H15: =VLOOKUP($G15,Annex2_Equipment!$C$26:$E$66,3,FALSE) -> 2 | I15: 2 | J15: =VLOOKUP($G15,Annex2_Equipment!$C$26:$E$66,2,FALSE) -> 351.276 | K15: =I15*J15 -> 702.552 | L15: 10 | N15: =IFERROR(K15/L15,0) -> 70.2552 | O15: =(I15*J15)*0.15 -> 105.3828 | P15: 1 | Q15: =N15*P15 -> 70.2552 | R15: =O15*P15 -> 105.3828 | S15: =Q15+R15 -> 175.638 | T15: =IFERROR($S15/COUNTIF($B15:$F15,"Yes"),0) -> 58.546 | V15: =IFERROR('Reagents and consumables'!$O$2*S15,"") -> 0 | AA15: =IF($M15<$L15,IF($I15<$H15,($H15-$I15)*$J15,""),$H15*$J15) | AB15: =IF($AA15<>"",$AA15/$J15,"") | AC15: =IF($AA15<>"",$G15,"")
A16: =IF(AB16<>"","Buy", "") | B16: No | C16: Yes | D16: No | E16: No | F16: No | G16: =Annex2_Equipment!C35 -> Analytical balance | H16: =VLOOKUP($G16,Annex2_Equipment!$C$26:$E$66,3,FALSE) -> 1 | I16: 1 | J16: =VLOOKUP($G16,Annex2_Equipment!$C$26:$E$66,2,FALSE) -> 994.881 | K16: =I16*J16 -> 994.881 | L16: 10 | N16: =IFERROR(K16/L16,0) -> 99.4881 | O16: =(I16*J16)*0.15 -> 149.23215 | P16: 1 | Q16: =N16*P16 -> 99.4881 | R16: =O16*P16 -> 149.23215 | S16: =Q16+R16 -> 248.72025 | T16: =IFERROR($S16/COUNTIF($B16:$F16,"Yes"),0) -> 248.72025 | V16: =IFERROR('Reagents and consumables'!$O$2*S16,"") -> 0 | AA16: =IF($M16<$L16,IF($I16<$H16,($H16-$I16)*$J16,""),$H16*$J16) | AB16: =IF($AA16<>"",$AA16/$J16,"") | AC16: =IF($AA16<>"",$G16,"")
A17: =IF(AB17<>"","Buy", "") | B17: Yes | C17: Yes | D17: Yes | E17: Yes | F17: Yes | G17: =Annex2_Equipment!C36 -> (-)20 freezer | H17: =VLOOKUP($G17,Annex2_Equipment!$C$26:$E$66,3,FALSE) -> 1 | I17: 1 | J17: =VLOOKUP($G17,Annex2_Equipment!$C$26:$E$66,2,FALSE) -> 1039.392 | K17: =I17*J17 -> 1039.392 | L17: 10 | N17: =IFERROR(K17/L17,0) -> 103.9392 | O17: =(I17*J17)*0.15 -> 155.9088 | P17: 1 | Q17: =N17*P17 -> 103.9392 | R17: =O17*P17 -> 155.9088 | S17: =Q17+R17 -> 259.848 | T17: =IFERROR($S17/COUNTIF($B17:$F17,"Yes"),0) -> 51.9696 | V17: =IFERROR('Reagents and consumables'!$O$2*S17,"") -> 0 | AA17: =IF($M17<$L17,IF($I17<$H17,($H17-$I17)*$J17,""),$H17*$J17) | AB17: =IF($AA17<>"",$AA17/$J17,"") | AC17: =IF($AA17<>"",$G17,"")
A18: =IF(AB18<>"","Buy", "") | B18: Yes | C18: Yes | D18: Yes | E18: Yes | F18: Yes | G18: =Annex2_Equipment!C37 -> (-)80 freezer | H18: =VLOOKUP($G18,Annex2_Equipment!$C$26:$E$66,3,FALSE) -> 1 | I18: 1 | J18: =VLOOKUP($G18,Annex2_Equipment!$C$26:$E$66,2,FALSE) -> 13719.012 | K18: =I18*J18 -> 13719.012 | L18: 10 | N18: =IFERROR(K18/L18,0) -> 1371.9012 | O18: =(I18*J18)*0.15 -> 2057.8518 | P18: 1 | Q18: =N18*P18 -> 1371.9012 | R18: =O18*P18 -> 2057.8518 | S18: =Q18+R18 -> 3429.753 | T18: =IFERROR($S18/COUNTIF($B18:$F18,"Yes"),0) -> 685.9506 | V18: =IFERROR('Reagents and consumables'!$O$2*S18,"") -> 0 | AA18: =IF($M18<$L18,IF($I18<$H18,($H18-$I18)*$J18,""),$H18*$J18) | AB18: =IF($AA18<>"",$AA18/$J18,"") | AC18: =IF($AA18<>"",$G18,"")
A19: =IF(AB19<>"","Buy", "") | B19: Yes | C19: Yes | D19: Yes | E19: Yes | F19: Yes | G19: =Annex2_Equipment!C38 -> Refrigerator (4C) | H19: =VLOOKUP($G19,Annex2_Equipment!$C$26:$E$66,3,FALSE) -> 1 | I19: 1 | J19: =VLOOKUP($G19,Annex2_Equipment!$C$26:$E$66,2,FALSE) -> 1200 | K19: =I19*J19 -> 1200 | L19: 10 | N19: =IFERROR(K19/L19,0) -> 120 | O19: =(I19*J19)*0.15 -> 180 | P19: 1 | Q19: =N19*P19 -> 120 | R19: =O19*P19 -> 180 | S19: =Q19+R19 -> 300 | T19: =IFERROR($S19/COUNTIF($B19:$F19,"Yes"),0) -> 60 | V19: =IFERROR('Reagents and consumables'!$O$2*S19,"") -> 0 | AA19: =IF($M19<$L19,IF($I19<$H19,($H19-$I19)*$J19,""),$H19*$J19) | AB19: =IF($AA19<>"",$AA19/$J19,"") | AC19: =IF($AA19<>"",$G19,"")
A20: =IF(AB20<>"","Buy", "") | B20: No | C20: No | D20: No | E20: No | F20: Yes | G20: =Annex2_Equipment!C40 -> Uninterrupted power supply (1500V) | H20: =VLOOKUP($G20,Annex2_Equipment!$C$26:$E$66,3,FALSE) -> 1 | I20: 1 | J20: =VLOOKUP($G20,Annex2_Equipment!$C$26:$E$66,2,FALSE) -> 1000 | K20: =I20*J20 -> 1000 | L20: 10 | N20: =IFERROR(K20/L20,0) -> 100 | O20: =(I20*J20)*0.15 -> 150 | P20: 1 | Q20: =N20*P20 -> 100 | R20: =O20*P20 -> 150 | S20: =Q20+R20 -> 250 | T20: =IFERROR($S20/COUNTIF($B20:$F20,"Yes"),0) -> 250 | V20: =IFERROR('Reagents and consumables'!$O$2*S20,"") -> 0 | AA20: =IF($M20<$L20,IF($I20<$H20,($H20-$I20)*$J20,""),$H20*$J20) | AB20: =IF($AA20<>"",$AA20/$J20,"") | AC20: =IF($AA20<>"",$G20,"")
A21: =IF(AB21<>"","Buy", "") | B21: No | C21: No | D21: Yes | E21: No | F21: No | G21: =Annex2_Equipment!C41 -> Uninterrupted power supply (600V); | H21: =VLOOKUP($G21,Annex2_Equipment!$C$26:$E$66,3,FALSE) -> 1 | I21: 1 | J21: =VLOOKUP($G21,Annex2_Equipment!$C$26:$E$66,2,FALSE) -> 600 | K21: =I21*J21 -> 600 | L21: 10 | N21: =IFERROR(K21/L21,0) -> 60 | O21: =(I21*J21)*0.15 -> 90 | P21: 1 | Q21: =N21*P21 -> 60 | R21: =O21*P21 -> 90 | S21: =Q21+R21 -> 150 | T21: =IFERROR($S21/COUNTIF($B21:$F21,"Yes"),0) -> 150 | V21: =IFERROR('Reagents and consumables'!$O$2*S21,"") -> 0 | AA21: =IF($M21<$L21,IF($I21<$H21,($H21-$I21)*$J21,""),$H21*$J21) | AB21: =IF($AA21<>"",$AA21/$J21,"") | AC21: =IF($AA21<>"",$G21,"")
A22: =IF(AB22<>"","Buy", "") | B22: No | C22: No | D22: No | E22: Yes | F22: No | G22: =Annex2_Equipment!C42 -> Thermal cycler (conventional) | H22: =VLOOKUP($G22,Annex2_Equipment!$C$26:$E$66,3,FALSE) -> 1 | I22: 1 | J22: =VLOOKUP($G22,Annex2_Equipment!$C$26:$E$66,2,FALSE) -> 9000 | K22: =I22*J22 -> 9000 | L22: 10 | N22: =IFERROR(K22/L22,0) -> 900 | O22: =(I22*J22)*0.15 -> 1350 | P22: 1 | Q22: =N22*P22 -> 900 | R22: =O22*P22 -> 1350 | S22: =Q22+R22 -> 2250 | T22: =IFERROR($S22/COUNTIF($B22:$F22,"Yes"),0) -> 2250 | V22: =IFERROR('Reagents and consumables'!$O$2*S22,"") -> 0 | AA22: =IF($M22<$L22,IF($I22<$H22,($H22-$I22)*$J22,""),$H22*$J22) | AB22: =IF($AA22<>"",$AA22/$J22,"") | AC22: =IF($AA22<>"",$G22,"")
A23: =IF(AB23<>"","Buy", "") | B23: No | C23: No | D23: Yes | E23: No | F23: No | G23: =Annex2_Equipment!C43 -> Thermal cycler (realtime) | H23: =VLOOKUP($G23,Annex2_Equipment!$C$26:$E$66,3,FALSE) -> 1 | I23: 1 | J23: =VLOOKUP($G23,Annex2_Equipment!$C$26:$E$66,2,FALSE) -> 18000 | K23: =I23*J23 -> 18000 | L23: 10 | N23: =IFERROR(K23/L23,0) -> 1800 | O23: =(I23*J23)*0.15 -> 2700 | P23: 1 | Q23: =N23*P23 -> 1800 | R23: =O23*P23 -> 2700 | S23: =Q23+R23 -> 4500 | T23: =IFERROR($S23/COUNTIF($B23:$F23,"Yes"),0) -> 4500 | V23: =IFERROR('Reagents and consumables'!$O$2*S23,"") -> 0 | AA23: =IF($M23<$L23,IF($I23<$H23,($H23-$I23)*$J23,""),$H23*$J23) | AB23: =IF($AA23<>"",$AA23/$J23,"") | AC23: =IF($AA23<>"",$G23,"")
A24: =IF(AB24<>"","Buy", "") | B24: No | C24: Yes | D24: No | E24: No | F24: No | G24: =Annex2_Equipment!C44 -> Water purification system | H24: =VLOOKUP($G24,Annex2_Equipment!$C$26:$E$66,3,FALSE) -> 1 | I24: 1 | J24: =VLOOKUP($G24,Annex2_Equipment!$C$26:$E$66,2,FALSE) -> 8408.97 | K24: =I24*J24 -> 8408.97 | L24: 10 | N24: =IFERROR(K24/L24,0) -> 840.897 | O24: =(I24*J24)*0.15 -> 1261.3455 | P24: 1 | Q24: =N24*P24 -> 840.897 | R24: =O24*P24 -> 1261.3455 | S24: =Q24+R24 -> 2102.2425 | T24: =IFERROR($S24/COUNTIF($B24:$F24,"Yes"),0) -> 2102.2425 | V24: =IFERROR('Reagents and consumables'!$O$2*S24,"") -> 0 | AA24: =IF($M24<$L24,IF($I24<$H24,($H24-$I24)*$J24,""),$H24*$J24) | AB24: =IF($AA24<>"",$AA24/$J24,"") | AC24: =IF($AA24<>"",$G24,"")
A25: =IF(AB25<>"","Buy", "") | B25: No | C25: Yes | D25: Yes | E25: Yes | F25: No | G25: =Annex2_Equipment!C45 -> Single channel pipette 100–1000μL | H25: =VLOOKUP($G25,Annex2_Equipment!$C$26:$E$66,3,FALSE) -> 3 | I25: 3 | J25: =VLOOKUP($G25,Annex2_Equipment!$C$26:$E$66,2,FALSE) -> 234.585 | K25: =I25*J25 -> 703.755 | L25: 10 | N25: =IFERROR(K25/L25,0) -> 70.3755 | O25: =(I25*J25)*0.15 -> 105.56325 | P25: 1 | Q25: =N25*P25 -> 70.3755 | R25: =O25*P25 -> 105.56325 | S25: =Q25+R25 -> 175.93875 | T25: =IFERROR($S25/COUNTIF($B25:$F25,"Yes"),0) -> 58.64625 | V25: =IFERROR('Reagents and consumables'!$O$2*S25,"") -> 0 | AA25: =IF($M25<$L25,IF($I25<$H25,($H25-$I25)*$J25,""),$H25*$J25) | AB25: =IF($AA25<>"",$AA25/$J25,"") | AC25: =IF($AA25<>"",$G25,"")
A26: =IF(AB26<>"","Buy", "") -> Buy | B26: No | C26: Yes | D26: Yes | E26: Yes | F26: No | G26: =Annex2_Equipment!C46 -> Single channel pipette 20–200μL | H26: =VLOOKUP($G26,Annex2_Equipment!$C$26:$E$66,3,FALSE) -> 3 | I26: 2 | J26: =VLOOKUP($G26,Annex2_Equipment!$C$26:$E$66,2,FALSE) -> 269.472 | K26: =I26*J26 -> 538.944 | L26: 10 | N26: =IFERROR(K26/L26,0) -> 53.8944 | O26: =(I26*J26)*0.15 -> 80.8416 | P26: 1 | Q26: =N26*P26 -> 53.8944 | R26: =O26*P26 -> 80.8416 | S26: =Q26+R26 -> 134.736 | T26: =IFERROR($S26/COUNTIF($B26:$F26,"Yes"),0) -> 44.912 | V26: =IFERROR('Reagents and consumables'!$O$2*S26,"") -> 0 | AA26: =IF($M26<$L26,IF($I26<$H26,($H26-$I26)*$J26,""),$H26*$J26) -> 269.472 | AB26: =IF($AA26<>"",$AA26/$J26,"") -> 1 | AC26: =IF($AA26<>"",$G26,"") -> Single channel pipette 20–200μL
A27: =IF(AB27<>"","Buy", "") | B27: No | C27: Yes | D27: Yes | E27: Yes | F27: No | G27: =Annex2_Equipment!C47 -> Single channel pipette 2–20μL | H27: =VLOOKUP($G27,Annex2_Equipment!$C$26:$E$66,3,FALSE) -> 3 | I27: 3 | J27: =VLOOKUP($G27,Annex2_Equipment!$C$26:$E$66,2,FALSE) -> 257.442 | K27: =I27*J27 -> 772.326 | L27: 10 | N27: =IFERROR(K27/L27,0) -> 77.2326 | O27: =(I27*J27)*0.15 -> 115.8489 | P27: 1 | Q27: =N27*P27 -> 77.2326 | R27: =O27*P27 -> 115.8489 | S27: =Q27+R27 -> 193.0815 | T27: =IFERROR($S27/COUNTIF($B27:$F27,"Yes"),0) -> 64.3605 | V27: =IFERROR('Reagents and consumables'!$O$2*S27,"") -> 0 | AA27: =IF($M27<$L27,IF($I27<$H27,($H27-$I27)*$J27,""),$H27*$J27) | AB27: =IF($AA27<>"",$AA27/$J27,"") | AC27: =IF($AA27<>"",$G27,"")
A28: =IF(AB28<>"","Buy", "") | B28: No | C28: No | D28: Yes | E28: No | F28: No | G28: =Annex2_Equipment!C49 -> Single channel pipette 0.2–2μL | H28: =VLOOKUP($G28,Annex2_Equipment!$C$26:$E$66,3,FALSE) -> 3 | I28: 3 | J28: =VLOOKUP($G28,Annex2_Equipment!$C$26:$E$66,2,FALSE) -> 234.585 | K28: =I28*J28 -> 703.755 | L28: 10 | N28: =IFERROR(K28/L28,0) -> 70.3755 | O28: =(I28*J28)*0.15 -> 105.56325 | P28: 1 | Q28: =N28*P28 -> 70.3755 | R28: =O28*P28 -> 105.56325 | S28: =Q28+R28 -> 175.93875 | T28: =IFERROR($S28/COUNTIF($B28:$F28,"Yes"),0) -> 175.93875 | V28: =IFERROR('Reagents and consumables'!$O$2*S28,"") -> 0 | AA28: =IF($M28<$L28,IF($I28<$H28,($H28-$I28)*$J28,""),$H28*$J28) | AB28: =IF($AA28<>"",$AA28/$J28,"") | AC28: =IF($AA28<>"",$G28,"")
A29: =IF(AB29<>"","Buy", "") | B29: No | C29: No | D29: No | E29: Yes | F29: No | G29: =Annex2_Equipment!C50 -> 8-channel multichannel pipettes 10–100μL | H29: =VLOOKUP($G29,Annex2_Equipment!$C$26:$E$66,3,FALSE) -> 3 | I29: 3 | J29: =VLOOKUP($G29,Annex2_Equipment!$C$26:$E$66,2,FALSE) -> 678.492 | K29: =I29*J29 -> 2035.476 | L29: 10 | N29: =IFERROR(K29/L29,0) -> 203.5476 | O29: =(I29*J29)*0.15 -> 305.3214 | P29: 1 | Q29: =N29*P29 -> 203.5476 | R29: =O29*P29 -> 305.3214 | S29: =Q29+R29 -> 508.869 | T29: =IFERROR($S29/COUNTIF($B29:$F29,"Yes"),0) -> 508.869 | V29: =IFERROR('Reagents and consumables'!$O$2*S29,"") -> 0 | AA29: =IF($M29<$L29,IF($I29<$H29,($H29-$I29)*$J29,""),$H29*$J29) | AB29: =IF($AA29<>"",$AA29/$J29,"") | AC29: =IF($AA29<>"",$G29,"")
A30: =IF(AB30<>"","Buy", "") | B30: No | C30: Yes | D30: Yes | E30: Yes | F30: No | G30: =Annex2_Equipment!C51 -> Tube racks | H30: =VLOOKUP($G30,Annex2_Equipment!$C$26:$E$66,3,FALSE) -> 5 | I30: 5 | J30: =VLOOKUP($G30,Annex2_Equipment!$C$26:$E$66,2,FALSE) -> 39.699 | K30: =I30*J30 -> 198.495 | L30: 10 | N30: =IFERROR(K30/L30,0) -> 19.8495 | O30: =(I30*J30)*0.15 -> 29.77425 | P30: 1 | Q30: =N30*P30 -> 19.8495 | R30: =O30*P30 -> 29.77425 | S30: =Q30+R30 -> 49.62375 | T30: =IFERROR($S30/COUNTIF($B30:$F30,"Yes"),0) -> 16.54125 | V30: =IFERROR('Reagents and consumables'!$O$2*S30,"") -> 0 | AA30: =IF($M30<$L30,IF($I30<$H30,($H30-$I30)*$J30,""),$H30*$J30) | AB30: =IF($AA30<>"",$AA30/$J30,"") | AC30: =IF($AA30<>"",$G30,"")
A31: =IF(AB31<>"","Buy", "") | B31: No | C31: Yes | D31: Yes | E31: Yes | F31: No | G31: =Annex2_Equipment!C52 -> Cooling block (tube strips) | H31: =VLOOKUP($G31,Annex2_Equipment!$C$26:$E$66,3,FALSE) -> 2 | I31: 2 | J31: =VLOOKUP($G31,Annex2_Equipment!$C$26:$E$66,2,FALSE) -> 291.126 | K31: =I31*J31 -> 582.252 | L31: 10 | N31: =IFERROR(K31/L31,0) -> 58.2252 | O31: =(I31*J31)*0.15 -> 87.3378 | P31: 1 | Q31: =N31*P31 -> 58.2252 | R31: =O31*P31 -> 87.3378 | S31: =Q31+R31 -> 145.563 | T31: =IFERROR($S31/COUNTIF($B31:$F31,"Yes"),0) -> 48.521 | V31: =IFERROR('Reagents and consumables'!$O$2*S31,"") -> 0 | AA31: =IF($M31<$L31,IF($I31<$H31,($H31-$I31)*$J31,""),$H31*$J31) | AB31: =IF($AA31<>"",$AA31/$J31,"") | AC31: =IF($AA31<>"",$G31,"")
A32: =IF(AB32<>"","Buy", "") | B32: No | C32: No | D32: Yes | E32: No | F32: No | G32: =Annex2_Equipment!C53 -> Cooling block (96 well plate) | H32: =VLOOKUP($G32,Annex2_Equipment!$C$26:$E$66,3,FALSE) -> 1 | I32: 1 | J32: =VLOOKUP($G32,Annex2_Equipment!$C$26:$E$66,2,FALSE) -> 175.74 | K32: =I32*J32 -> 175.74 | L32: 10 | N32: =IFERROR(K32/L32,0) -> 17.574 | O32: =(I32*J32)*0.15 -> 26.361 | P32: 1 | Q32: =N32*P32 -> 17.574 | R32: =O32*P32 -> 26.361 | S32: =Q32+R32 -> 43.935 | T32: =IFERROR($S32/COUNTIF($B32:$F32,"Yes"),0) -> 43.935 | V32: =IFERROR('Reagents and consumables'!$O$2*S32,"") -> 0 | AA32: =IF($M32<$L32,IF($I32<$H32,($H32-$I32)*$J32,""),$H32*$J32) | AB32: =IF($AA32<>"",$AA32/$J32,"") | AC32: =IF($AA32<>"",$G32,"")
A33: =IF(AB33<>"","Buy", "") | B33: No | C33: No | D33: Yes | E33: Yes | F33: No | G33: =Annex2_Equipment!C54 -> Ice bucket | H33: =VLOOKUP($G33,Annex2_Equipment!$C$26:$E$66,3,FALSE) -> 1 | I33: 1 | J33: =VLOOKUP($G33,Annex2_Equipment!$C$26:$E$66,2,FALSE) -> 173.9 | K33: =I33*J33 -> 173.9 | L33: 10 | N33: =IFERROR(K33/L33,0) -> 17.39 | O33: =(I33*J33)*0.15 -> 26.085 | P33: 1 | Q33: =N33*P33 -> 17.39 | R33: =O33*P33 -> 26.085 | S33: =Q33+R33 -> 43.475 | T33: =IFERROR($S33/COUNTIF($B33:$F33,"Yes"),0) -> 21.7375 | V33: =IFERROR('Reagents and consumables'!$O$2*S33,"") -> 0 | AA33: =IF($M33<$L33,IF($I33<$H33,($H33-$I33)*$J33,""),$H33*$J33) | AB33: =IF($AA33<>"",$AA33/$J33,"") | AC33: =IF($AA33<>"",$G33,"")
A34: =IF(AB34<>"","Buy", "") | B34: No | C34: No | D34: No | E34: Yes | F34: No | G34: =Annex2_Equipment!C55 -> Fluorometer, single assay | H34: =VLOOKUP($G34,Annex2_Equipment!$C$26:$E$66,3,FALSE) -> 1 | I34: 1 | J34: =VLOOKUP($G34,Annex2_Equipment!$C$26:$E$66,2,FALSE) -> 3035 | K34: =I34*J34 -> 3035 | L34: 10 | N34: =IFERROR(K34/L34,0) -> 303.5 | O34: =(I34*J34)*0.15 -> 455.25 | P34: 1 | Q34: =N34*P34 -> 303.5 | R34: =O34*P34 -> 455.25 | S34: =Q34+R34 -> 758.75 | T34: =IFERROR($S34/COUNTIF($B34:$F34,"Yes"),0) -> 758.75 | V34: =IFERROR('Reagents and consumables'!$O$2*S34,"") -> 0 | AA34: =IF($M34<$L34,IF($I34<$H34,($H34-$I34)*$J34,""),$H34*$J34) | AB34: =IF($AA34<>"",$AA34/$J34,"") | AC34: =IF($AA34<>"",$G34,"")
A35: =IF(AB35<>"","Buy", "") | B35: No | C35: No | D35: No | E35: Yes | F35: No | G35: =Annex2_Equipment!C56 -> Fluorometer, strip tube capable | H35: =VLOOKUP($G35,Annex2_Equipment!$C$26:$E$66,3,FALSE) -> 0 | J35: =VLOOKUP($G35,Annex2_Equipment!$C$26:$E$66,2,FALSE) -> 6600 | K35: =I35*J35 -> 0 | L35: 10 | N35: =IFERROR(K35/L35,0) -> 0 | O35: =(I35*J35)*0.15 -> 0 | P35: 1 | Q35: =N35*P35 -> 0 | R35: =O35*P35 -> 0 | S35: =Q35+R35 -> 0 | T35: =IFERROR($S35/COUNTIF($B35:$F35,"Yes"),0) -> 0 | V35: =IFERROR('Reagents and consumables'!$O$2*S35,"") -> 0 | AA35: =IF($M35<$L35,IF($I35<$H35,($H35-$I35)*$J35,""),$H35*$J35) | AB35: =IF($AA35<>"",$AA35/$J35,"") | AC35: =IF($AA35<>"",$G35,"")
A36: =IF(AB36<>"","Buy", "") | B36: No | C36: No | D36: No | E36: No | F36: Yes | G36: =Annex2_Equipment!C57 -> Air conditioners | H36: =VLOOKUP($G36,Annex2_Equipment!$C$26:$E$66,3,FALSE) -> 3 | I36: 3 | J36: =VLOOKUP($G36,Annex2_Equipment!$C$26:$E$66,2,FALSE) -> 500 | K36: =I36*J36 -> 1500 | L36: 10 | N36: =IFERROR(K36/L36,0) -> 150 | O36: =(I36*J36)*0.15 -> 225 | P36: 1 | Q36: =N36*P36 -> 150 | R36: =O36*P36 -> 225 | S36: =Q36+R36 -> 375 | T36: =IFERROR($S36/COUNTIF($B36:$F36,"Yes"),0) -> 375 | V36: =IFERROR('Reagents and consumables'!$O$2*S36,"") -> 0 | AA36: =IF($M36<$L36,IF($I36<$H36,($H36-$I36)*$J36,""),$H36*$J36) | AB36: =IF($AA36<>"",$AA36/$J36,"") | AC36: =IF($AA36<>"",$G36,"")
A37: =IF(AB37<>"","Buy", "") | B37: No | C37: Yes | D37: No | E37: No | F37: Yes | G37: =Annex2_Equipment!C58 -> Temperature logger | H37: =VLOOKUP($G37,Annex2_Equipment!$C$26:$E$66,3,FALSE) -> 3 | I37: 3 | J37: =VLOOKUP($G37,Annex2_Equipment!$C$26:$E$66,2,FALSE) -> 170.4 | K37: =I37*J37 -> 511.2 | L37: 10 | N37: =IFERROR(K37/L37,0) -> 51.12 | O37: =(I37*J37)*0.15 -> 76.68 | P37: 1 | Q37: =N37*P37 -> 51.12 | R37: =O37*P37 -> 76.68 | S37: =Q37+R37 -> 127.8 | T37: =IFERROR($S37/COUNTIF($B37:$F37,"Yes"),0) -> 63.9 | V37: =IFERROR('Reagents and consumables'!$O$2*S37,"") -> 0 | AA37: =IF($M37<$L37,IF($I37<$H37,($H37-$I37)*$J37,""),$H37*$J37) | AB37: =IF($AA37<>"",$AA37/$J37,"") | AC37: =IF($AA37<>"",$G37,"")
A38: =IF(AB38<>"","Buy", "") -> Buy | B38: No | C38: No | D38: No | E38: Yes | F38: No | G38: =Annex2_Equipment!C59 -> Centrifuge (plate) | H38: =VLOOKUP($G38,Annex2_Equipment!$C$26:$E$66,3,FALSE) -> 2 | I38: 1 | J38: =VLOOKUP($G38,Annex2_Equipment!$C$26:$E$66,2,FALSE) -> 670.5 | K38: =I38*J38 -> 670.5 | L38: 10 | N38: =IFERROR(K38/L38,0) -> 67.05 | O38: =(I38*J38)*0.15 -> 100.575 | P38: 1 | Q38: =N38*P38 -> 67.05 | R38: =O38*P38 -> 100.575 | S38: =Q38+R38 -> 167.625 | T38: =IFERROR($S38/COUNTIF($B38:$F38,"Yes"),0) -> 167.625 | V38: =IFERROR('Reagents and consumables'!$O$2*S38,"") -> 0 | AA38: =IF($M38<$L38,IF($I38<$H38,($H38-$I38)*$J38,""),$H38*$J38) -> 670.5 | AB38: =IF($AA38<>"",$AA38/$J38,"") -> 1 | AC38: =IF($AA38<>"",$G38,"") -> Centrifuge (plate)
A39: =IF(AB39<>"","Buy", "") -> Buy | B39: No | C39: Yes | D39: Yes | E39: No | F39: No | G39: =Annex2_Equipment!C60 -> Microcentrifuge (can hold 24 tubes of 1.5/2.0 mL) | H39: =VLOOKUP($G39,Annex2_Equipment!$C$26:$E$66,3,FALSE) -> 2 | I39: 1 | J39: =VLOOKUP($G39,Annex2_Equipment!$C$26:$E$66,2,FALSE) -> 5760 | K39: =I39*J39 -> 5760 | L39: 10 | N39: =IFERROR(K39/L39,0) -> 576 | O39: =(I39*J39)*0.15 -> 864 | P39: 1 | Q39: =N39*P39 -> 576 | R39: =O39*P39 -> 864 | S39: =Q39+R39 -> 1440 | T39: =IFERROR($S39/COUNTIF($B39:$F39,"Yes"),0) -> 720 | V39: =IFERROR('Reagents and consumables'!$O$2*S39,"") -> 0 | AA39: =IF($M39<$L39,IF($I39<$H39,($H39-$I39)*$J39,""),$H39*$J39) -> 5760 | AB39: =IF($AA39<>"",$AA39/$J39,"") -> 1 | AC39: =IF($AA39<>"",$G39,"") -> Microcentrifuge (can hold 24 tubes of 1.5/2.0 mL)
A40: =IF(AB40<>"","Buy", "") | B40: No | C40: Yes | D40: No | E40: No | F40: No | G40: =Annex2_Equipment!C61 -> Centrifuge, refrigerated | H40: =VLOOKUP($G40,Annex2_Equipment!$C$26:$E$66,3,FALSE) -> 2 | I40: 2 | J40: =VLOOKUP($G40,Annex2_Equipment!$C$26:$E$66,2,FALSE) -> 5554.8 | K40: =I40*J40 -> 11109.6 | L40: 10 | N40: =IFERROR(K40/L40,0) -> 1110.96 | O40: =(I40*J40)*0.15 -> 1666.44 | P40: 1 | Q40: =N40*P40 -> 1110.96 | R40: =O40*P40 -> 1666.44 | S40: =Q40+R40 -> 2777.4 | T40: =IFERROR($S40/COUNTIF($B40:$F40,"Yes"),0) -> 2777.4 | V40: =IFERROR('Reagents and consumables'!$O$2*S40,"") -> 0 | AA40: =IF($M40<$L40,IF($I40<$H40,($H40-$I40)*$J40,""),$H40*$J40) | AB40: =IF($AA40<>"",$AA40/$J40,"") | AC40: =IF($AA40<>"",$G40,"")
A41: =IF(AB41<>"","Buy", "") | B41: No | C41: No | D41: No | E41: Yes | F41: No | G41: =Annex2_Equipment!C64 -> Bioanalyzer/TapeStation | H41: =VLOOKUP($G41,Annex2_Equipment!$C$26:$E$66,3,FALSE) -> 1 | I41: 1 | J41: =VLOOKUP($G41,Annex2_Equipment!$C$26:$E$66,2,FALSE) -> 42000 | K41: =I41*J41 -> 42000 | L41: 10 | N41: =IFERROR(K41/L41,0) -> 4200 | O41: =(I41*J41)*0.15 -> 6300 | P41: 1 | Q41: =N41*P41 -> 4200 | R41: =O41*P41 -> 6300 | S41: =Q41+R41 -> 10500 | T41: =IFERROR($S41/COUNTIF($B41:$F41,"Yes"),0) -> 10500 | V41: =IFERROR('Reagents and consumables'!$O$2*S41,"") -> 0 | AA41: =IF($M41<$L41,IF($I41<$H41,($H41-$I41)*$J41,""),$H41*$J41) | AB41: =IF($AA41<>"",$AA41/$J41,"") | AC41: =IF($AA41<>"",$G41,"")
A42: =IF(AB42<>"","Buy", "") | B42: No | C42: No | D42: No | E42: Yes | F42: No | G42: =Annex2_Equipment!C65 -> Liquid handler – library preparation | H42: =VLOOKUP($G42,Annex2_Equipment!$C$26:$E$66,3,FALSE) -> 0 | J42: =VLOOKUP($G42,Annex2_Equipment!$C$26:$E$66,2,FALSE) -> 96000 | K42: =I42*J42 -> 0 | L42: 10 | N42: =IFERROR(K42/L42,0) -> 0 | O42: =(I42*J42)*0.15 -> 0 | P42: 1 | Q42: =N42*P42 -> 0 | R42: =O42*P42 -> 0 | S42: =Q42+R42 -> 0 | T42: =IFERROR($S42/COUNTIF($B42:$F42,"Yes"),0) -> 0 | V42: =IFERROR('Reagents and consumables'!$O$2*S42,"") -> 0 | AA42: =IF($M42<$L42,IF($I42<$H42,($H42-$I42)*$J42,""),$H42*$J42) | AB42: =IF($AA42<>"",$AA42/$J42,"") | AC42: =IF($AA42<>"",$G42,"")
A43: =IF(AB43<>"","Buy", "") | B43: No | C43: No | D43: No | E43: No | F43: Yes | G43: =Annex2_Equipment!C66 -> Desktop computer | H43: =VLOOKUP($G43,Annex2_Equipment!$C$26:$E$66,3,FALSE) -> 1 | I43: 1 | J43: =VLOOKUP($G43,Annex2_Equipment!$C$26:$E$66,2,FALSE) -> 478.8 | K43: =I43*J43 -> 478.8 | L43: 10 | N43: =IFERROR(K43/L43,0) -> 47.88 | O43: =(I43*J43)*0.15 -> 71.82 | P43: 1 | Q43: =N43*P43 -> 47.88 | R43: =O43*P43 -> 71.82 | S43: =Q43+R43 -> 119.7 | T43: =IFERROR($S43/COUNTIF($B43:$F43,"Yes"),0) -> 119.7 | V43: =IFERROR('Reagents and consumables'!$O$2*S43,"") -> 0 | AA43: =IF($M43<$L43,IF($I43<$H43,($H43-$I43)*$J43,""),$H43*$J43) | AB43: =IF($AA43<>"",$AA43/$J43,"") | AC43: =IF($AA43<>"",$G43,"")
K44: =I44*J44 -> 0 | N44: =IFERROR(K44/L44,0) -> 0 | O44: =(I44*J44)*0.15 -> 0 | Q44: =N44*P44 -> 0 | R44: =O44*P44 -> 0 | S44: =Q44+R44 -> 0 | T44: =IFERROR($S44/COUNTIF($B44:$F44,"Yes"),0) -> 0 | V44: =IFERROR('Reagents and consumables'!$O$2*S44,"") -> 0
K45: =I45*J45 -> 0 | N45: =IFERROR(K45/L45,0) -> 0 | O45: =(I45*J45)*0.15 -> 0 | Q45: =N45*P45 -> 0 | R45: =O45*P45 -> 0 | S45: =Q45+R45 -> 0 | T45: =IFERROR($S45/COUNTIF($B45:$F45,"Yes"),0) -> 0 | V45: =IFERROR('Reagents and consumables'!$O$2*S45,"") -> 0
K46: =I46*J46 -> 0 | N46: =IFERROR(K46/L46,0) -> 0 | O46: =(I46*J46)*0.15 -> 0 | Q46: =N46*P46 -> 0 | R46: =O46*P46 -> 0 | S46: =Q46+R46 -> 0 | T46: =IFERROR($S46/COUNTIF($B46:$F46,"Yes"),0) -> 0 | V46: =IFERROR('Reagents and consumables'!$O$2*S46,"") -> 0
K47: =I47*J47 -> 0 | N47: =IFERROR(K47/L47,0) -> 0 | O47: =(I47*J47)*0.15 -> 0 | Q47: =N47*P47 -> 0 | R47: =O47*P47 -> 0 | S47: =Q47+R47 -> 0 | T47: =IFERROR($S47/COUNTIF($B47:$F47,"Yes"),0) -> 0 | V47: =IFERROR('Reagents and consumables'!$O$2*S47,"") -> 0
K48: =I48*J48 -> 0 | N48: =IFERROR(K48/L48,0) -> 0 | O48: =(I48*J48)*0.15 -> 0 | Q48: =N48*P48 -> 0 | R48: =O48*P48 -> 0 | S48: =Q48+R48 -> 0 | T48: =IFERROR($S48/COUNTIF($B48:$F48,"Yes"),0) -> 0 | V48: =IFERROR('Reagents and consumables'!$O$2*S48,"") -> 0
K49: =I49*J49 -> 0 | N49: =IFERROR(K49/L49,0) -> 0 | O49: =(I49*J49)*0.15 -> 0 | Q49: =N49*P49 -> 0 | R49: =O49*P49 -> 0 | S49: =Q49+R49 -> 0 | T49: =IFERROR($S49/COUNTIF($B49:$F49,"Yes"),0) -> 0 | V49: =IFERROR('Reagents and consumables'!$O$2*S49,"") -> 0
K50: =I50*J50 -> 0 | N50: =IFERROR(K50/L50,0) -> 0 | O50: =(I50*J50)*0.15 -> 0 | Q50: =N50*P50 -> 0 | R50: =O50*P50 -> 0 | S50: =Q50+R50 -> 0 | T50: =IFERROR($S50/COUNTIF($B50:$F50,"Yes"),0) -> 0 | V50: =IFERROR('Reagents and consumables'!$O$2*S50,"") -> 0
K51: =I51*J51 -> 0 | N51: =IFERROR(K51/L51,0) -> 0 | O51: =(I51*J51)*0.15 -> 0 | Q51: =N51*P51 -> 0 | R51: =O51*P51 -> 0 | S51: =Q51+R51 -> 0 | T51: =IFERROR($S51/COUNTIF($B51:$F51,"Yes"),0) -> 0 | V51: =IFERROR('Reagents and consumables'!$O$2*S51,"") -> 0
K52: =I52*J52 -> 0 | N52: =IFERROR(K52/L52,0) -> 0 | O52: =(I52*J52)*0.15 -> 0 | Q52: =N52*P52 -> 0 | R52: =O52*P52 -> 0 | S52: =Q52+R52 -> 0 | T52: =IFERROR($S52/COUNTIF($B52:$F52,"Yes"),0) -> 0 | V52: =IFERROR('Reagents and consumables'!$O$2*S52,"") -> 0
K53: =I53*J53 -> 0 | N53: =IFERROR(K53/L53,0) -> 0 | O53: =(I53*J53)*0.15 -> 0 | Q53: =N53*P53 -> 0 | R53: =O53*P53 -> 0 | S53: =Q53+R53 -> 0 | T53: =IFERROR($S53/COUNTIF($B53:$F53,"Yes"),0) -> 0 | V53: =IFERROR('Reagents and consumables'!$O$2*S53,"") -> 0
K54: =I54*J54 -> 0 | N54: =IFERROR(K54/L54,0) -> 0 | O54: =(I54*J54)*0.15 -> 0 | Q54: =N54*P54 -> 0 | R54: =O54*P54 -> 0 | S54: =Q54+R54 -> 0 | T54: =IFERROR($S54/COUNTIF($B54:$F54,"Yes"),0) -> 0 | V54: =IFERROR('Reagents and consumables'!$O$2*S54,"") -> 0
K55: =I55*J55 -> 0 | N55: =IFERROR(K55/L55,0) -> 0 | O55: =(I55*J55)*0.15 -> 0 | Q55: =N55*P55 -> 0 | R55: =O55*P55 -> 0 | S55: =Q55+R55 -> 0 | T55: =IFERROR($S55/COUNTIF($B55:$F55,"Yes"),0) -> 0 | V55: =IFERROR('Reagents and consumables'!$O$2*S55,"") -> 0
... K99: =I99*J99 -> 0 | N99: =IFERROR(K99/L99,0) -> 0 | O99: =(I99*J99)*0.15 -> 0 | Q99: =N99*P99 -> 0 | R99: =O99*P99 -> 0 | S99: =Q99+R99 -> 0 | T99: =IFERROR($S99/COUNTIF($B99:$F99,"Yes"),0) -> 0 | V99: =IFERROR('Reagents and consumables'!$O$2*S99,"") -> 0
P102: =Language!B436 -> Calculated costs – Equipment
P103: =Language!$B$97 -> Total recommended equipment cost | Q103: =SUM($J$5*$H$5,$J$6*$H$6)+SUMPRODUCT($J$7:$J$43,$H$7:$H$43) -> 327703.81
P104: =Language!B92 -> Potential items for purchase to reach recommended equipment quantities | Q104: =SUM($AA$5:$AA$43) -> 10790.172
P105: =Language!$B$99 -> Total annual equipment depreciation cost | Q105: =SUM($Q$5,$Q$6,$Q$7:$Q$99) -> 35649.485
P106: =Language!$B$344 -> Total annual equipment maintenance and calibration cost | Q106: =SUM($R$5,$R$6,$R$7:$R$99) -> 47249.228
P107: =Language!$B$346 -> Total annual equipment operational cost | Q107: =SUM($S$5,$S$6,$S$7:$S$99) -> 82898.714
P108: =Language!$B$100 -> Total equipment cost per sample | Q108: =$Q$107/'Data entry'!F32 -> 103.62339

Sheet Personnel and training
B2: =Language!B101 -> Personnel and training
B3: =Language!B102 -> NGS workforce | C3: =Language!B103 -> Annual salary and benefit costs | D3: =Language!B104 -> Percentage of time spent on sequencing of selected pathogens | E3: =Language!B105 -> Annual personnel cost | F3: =Language!B106 -> Personnel cost per sample | I3: =Language!B69 -> Local currency (reference only)
B4: NGS Workforce | C4: Annual salary | D4: Percentage of time spent on sequencing | E4: Annual personnel cost | F4: Personnel cost per sample | I4: local currency (reference only)
B5: =Language!B321 -> Clinical microbiologist | C5: 15000 | D5: 0.1 | E5: =C5*D5 -> 1500 | F5: =IFERROR(E5/'Data entry'!$F$32,0) -> 1.875 | I5: =IFERROR('Reagents and consumables'!$O$2*E5,"") -> 0
B6: =Language!B322 -> Laboratory manager | C6: 20000 | D6: 0.02 | E6: =C6*D6 -> 400 | F6: =IFERROR(E6/'Data entry'!$F$32,0) -> 0.5 | I6: =IFERROR('Reagents and consumables'!$O$2*E6,"") -> 0
B7: =Language!B323 -> Bioinformatician | C7: 12000 | D7: 0.3 | E7: =C7*D7 -> 3600 | F7: =IFERROR(E7/'Data entry'!$F$32,0) -> 4.5 | I7: =IFERROR('Reagents and consumables'!$O$2*E7,"") -> 0
B8: =Language!B324 -> Molecular biologist | C8: 15000 | D8: 0.3 | E8: =C8*D8 -> 4500 | F8: =IFERROR(E8/'Data entry'!$F$32,0) -> 5.625 | I8: =IFERROR('Reagents and consumables'!$O$2*E8,"") -> 0
B9: =Language!B325 -> Laboratory technician | C9: 8000 | D9: 0.25 | E9: =C9*D9 -> 2000 | F9: =IFERROR(E9/'Data entry'!$F$32,0) -> 2.5 | I9: =IFERROR('Reagents and consumables'!$O$2*E9,"") -> 0
B10: =Language!B326 -> Laboratory technician | C10: 8000 | D10: 0.75 | E10: =C10*D10 -> 6000 | F10: =IFERROR(E10/'Data entry'!$F$32,0) -> 7.5 | I10: =IFERROR('Reagents and consumables'!$O$2*E10,"") -> 0
E11: =C11*D11 -> 0 | F11: =IFERROR(E11/'Data entry'!$F$32,0) -> 0 | I11: =IFERROR('Reagents and consumables'!$O$2*E11,"") -> 0
E12: =C12*D12 -> 0 | F12: =IFERROR(E12/'Data entry'!$F$32,0) -> 0 | I12: =IFERROR('Reagents and consumables'!$O$2*E12,"") -> 0
E13: =C13*D13 -> 0 | F13: =IFERROR(E13/'Data entry'!$F$32,0) -> 0 | I13: =IFERROR('Reagents and consumables'!$O$2*E13,"") -> 0
E14: =C14*D14 -> 0 | F14: =IFERROR(E14/'Data entry'!$F$32,0) -> 0 | I14: =IFERROR('Reagents and consumables'!$O$2*E14,"") -> 0
E15: =C15*D15 -> 0 | F15: =IFERROR(E15/'Data entry'!$F$32,0) -> 0 | I15: =IFERROR('Reagents and consumables'!$O$2*E15,"") -> 0
E16: =C16*D16 -> 0 | F16: =IFERROR(E16/'Data entry'!$F$32,0) -> 0 | I16: =IFERROR('Reagents and consumables'!$O$2*E16,"") -> 0
E17: =C17*D17 -> 0 | F17: =IFERROR(E17/'Data entry'!$F$32,0) -> 0 | I17: =IFERROR('Reagents and consumables'!$O$2*E17,"") -> 0
E18: =C18*D18 -> 0 | F18: =IFERROR(E18/'Data entry'!$F$32,0) -> 0 | I18: =IFERROR('Reagents and consumables'!$O$2*E18,"") -> 0
E19: =C19*D19 -> 0 | F19: =IFERROR(E19/'Data entry'!$F$32,0) -> 0 | I19: =IFERROR('Reagents and consumables'!$O$2*E19,"") -> 0
E20: =C20*D20 -> 0 | F20: =IFERROR(E20/'Data entry'!$F$32,0) -> 0 | I20: =IFERROR('Reagents and consumables'!$O$2*E20,"") -> 0
E21: =C21*D21 -> 0 | F21: =IFERROR(E21/'Data entry'!$F$32,0) -> 0 | I21: =IFERROR('Reagents and consumables'!$O$2*E21,"") -> 0
E22: =C22*D22 -> 0 | F22: =IFERROR(E22/'Data entry'!$F$32,0) -> 0 | I22: =IFERROR('Reagents and consumables'!$O$2*E22,"") -> 0
... E36: =C36*D36 -> 0 | F36: =IFERROR(E36/'Data entry'!$F$32,0) -> 0 | I36: =IFERROR('Reagents and consumables'!$O$2*E36,"") -> 0
B40: =Language!B108 -> Additional admin cost percentage | E40: =Language!B110 -> Annual sequencing/bioinformatics training cost for the selected pathogens | F40: =Language!B111 -> Training cost per sample
B41: 0.1 | C41: =SUM(E5:E36)*B41 -> 1800 | E41: 5000 | F41: =IFERROR(E41/'Data entry'!F32,0) -> 6.25
B43: =Language!B109 -> Comments | E43: =Language!B434 -> Calculated costs – Personnel and training
E44: =Language!B112 -> Total annual personnel cost | F44: =Language!B113 -> Total personnel cost per sample
E45: =SUM(E5:E36,C41,E41) -> 24800 | F45: =IFERROR(E45/'Data entry'!F32,0) -> 31

Sheet Facility and transport
B2: =Language!B114 -> Facility and transport
B4: =Language!B115 -> Facility | K4: =Language!B69 -> Local currency (reference only)
B5: =Language!B116 -> Facility services | C5: =Language!B117 -> Cost per month | E5: =Language!B431 -> Calculated costs – Facility
B6: Facility services | C6: Cost per month
B7: =Language!B118 -> Rent | C7: 0 | E7: =Language!B130 -> Total facility cost/month | G7: =SUM(C7:C32) -> 2850 | K7: =IFERROR('Reagents and consumables'!$O$2*G7,"") -> 0
B8: =Language!B119 -> Building maintenance | C8: 200 | E8: =Language!B131 -> Percentage of the facility used for sequencing of selected pathogens | G8: 0.2
B9: =Language!B120 -> Gas and heating | C9: 200 | E9: =Language!B132 -> Annual facility cost | G9: =G7*G8*12 -> 6840 | K9: =IFERROR('Reagents and consumables'!$O$2*G9,"") -> 0
B10: =Language!B121 -> Water | C10: 100 | E10: =Language!B133 -> Facility cost per sample | G10: =IFERROR(G9/('Data entry'!$F$32),0) -> 8.55 | K10: =IFERROR('Reagents and consumables'!$O$2*G10,"") -> 0
B11: =Language!B122 -> Electricity | C11: 500
B12: =Language!B123 -> Internet | C12: 200
B13: =Language!B124 -> Telephone | C13: 100
B14: =Language!B125 -> Waste management | C14: 1000
B15: =Language!B126 -> Generator maintenance | C15: 100
B16: =Language!B127 -> Ventilation system maintenance | C16: 300
B17: =Language!B128 -> Generator fuel | C17: 50
B18: =Language!B394 -> Laboratory information management system (LIMS) | C18: 100
E22: =Language!B134 -> Transport
E23: =Language!B135 -> Transportation services | F23: =Language!B136 -> Shipment method | G23: =Language!B137 -> Annual cost | H23: =Language!B330 -> Percentage for sequencing of selected pathogens | I23: =Language!B138 -> Transportation cost per sample per service | K23: =Language!B69 -> Local currency (reference only)
E24: Transportation services | F24: Shipment method | G24: Annual cost | H24: Column1 | I24: Transportation cost per sample per service | K24: local currency (reference only)
E25: =Language!B143 -> Regional to national reference laboratory | F25: =Language!B147 -> Courier | G25: 1000 | H25: 0.15 | I25: =IFERROR(G25*Table16[[#This Row],[Column1]]/('Data entry'!$F$32),0) -> 0.1875 | K25: =IFERROR('Reagents and consumables'!$O$2*G25,"") -> 0
E26: =Language!B144 -> Insurance (if applicable) | I26: =IFERROR(G26*Table16[[#This Row],[Column1]]/('Data entry'!$F$32),0) -> 0 | K26: =IFERROR('Reagents and consumables'!$O$2*G26,"") -> 0
E27: =Language!B145 -> Exportation fees (if applicable) | I27: =IFERROR(G27*Table16[[#This Row],[Column1]]/('Data entry'!$F$32),0) -> 0 | K27: =IFERROR('Reagents and consumables'!$O$2*G27,"") -> 0
E28: =Language!B146 -> Customs clearance fees | I28: =IFERROR(G28*Table16[[#This Row],[Column1]]/('Data entry'!$F$32),0) -> 0 | K28: =IFERROR('Reagents and consumables'!$O$2*G28,"") -> 0
I29: =IFERROR(G29*Table16[[#This Row],[Column1]]/('Data entry'!$F$32),0) -> 0 | K29: =IFERROR('Reagents and consumables'!$O$2*G29,"") -> 0
I30: =IFERROR(G30*Table16[[#This Row],[Column1]]/('Data entry'!$F$32),0) -> 0 | K30: =IFERROR('Reagents and consumables'!$O$2*G30,"") -> 0
I31: =IFERROR(G31*Table16[[#This Row],[Column1]]/('Data entry'!$F$32),0) -> 0 | K31: =IFERROR('Reagents and consumables'!$O$2*G31,"") -> 0
I32: =IFERROR(G32*Table16[[#This Row],[Column1]]/('Data entry'!$F$32),0) -> 0 | K32: =IFERROR('Reagents and consumables'!$O$2*G32,"") -> 0
I33: =IFERROR(G33*Table16[[#This Row],[Column1]]/('Data entry'!$F$32),0) -> 0 | K33: =IFERROR('Reagents and consumables'!$O$2*G33,"") -> 0
I34: =IFERROR(G34*Table16[[#This Row],[Column1]]/('Data entry'!$F$32),0) -> 0 | K34: =IFERROR('Reagents and consumables'!$O$2*G34,"") -> 0
I35: =IFERROR(G35*Table16[[#This Row],[Column1]]/('Data entry'!$F$32),0) -> 0 | K35: =IFERROR('Reagents and consumables'!$O$2*G35,"") -> 0
I36: =IFERROR(G36*Table16[[#This Row],[Column1]]/('Data entry'!$F$32),0) -> 0 | K36: =IFERROR('Reagents and consumables'!$O$2*G36,"") -> 0
I37: =IFERROR(G37*Table16[[#This Row],[Column1]]/('Data entry'!$F$32),0) -> 0 | K37: =IFERROR('Reagents and consumables'!$O$2*G37,"") -> 0
I38: =IFERROR(G38*Table16[[#This Row],[Column1]]/('Data entry'!$F$32),0) -> 0 | K38: =IFERROR('Reagents and consumables'!$O$2*G38,"") -> 0
I39: =IFERROR(G39*Table16[[#This Row],[Column1]]/('Data entry'!$F$32),0) -> 0 | K39: =IFERROR('Reagents and consumables'!$O$2*G39,"") -> 0
I40: =IFERROR(G40*Table16[[#This Row],[Column1]]/('Data entry'!$F$32),0) -> 0 | K40: =IFERROR('Reagents and consumables'!$O$2*G40,"") -> 0
... I43: =IFERROR(G43*Table16[[#This Row],[Column1]]/('Data entry'!$F$32),0) -> 0 | K43: =IFERROR('Reagents and consumables'!$O$2*G43,"") -> 0
F45: =Language!B245 -> Total annual transport-related cost | G45: =SUMPRODUCT(Table16[Annual cost], Table16[Column1]) -> 150 | H45: =Language!B246 -> Total transport-related cost per sample | I45: =SUM(I25:I43) -> 0.1875 | K45: =IFERROR('Reagents and consumables'!$O$2*G45,"") -> 0
G47: =Language!B433 -> Calculated costs – Facility and transport
G48: =Language!B141 -> Total annual facility and transportation cost | I48: =SUM($G$9,$G$45) -> 6990
G49: =Language!B142 -> Facility and transportation cost per sample | I49: =SUM($G$10,$I$45) -> 8.7375

Sheet Bioinformatics
A2: =Language!B148 -> Bioinformatics cost – by type of bioinformatics equipment or software solution
A3: =Language!B149 -> Please fill out the section as per your selection of bioinformatics in the Data Entry sheet: cloud-based or in-house. For hybrid, please fill out both cloud-based and in-house sections. If you select Cloud-based and this is outsourced, please enter the total purchase cost; the cost per sample will be calculated automatically
A5: =Language!B150 -> Cloud-based analysis software
A6: =Language!B151 -> Software platforms and storage | B6: =Language!B152 -> Description | C6: =Language!B153 -> Price per unit (USD) | D6: =Language!B154 -> Quantity of units | E6: =Language!B414 -> Total number of samples for which the platform is used (for all pathogens) | F6: =Language!B415 -> Number of samples in this costing scenario for which the platform is used (for the costed pathogens) | G6: =Language!B155 -> Total cost for the selected pathogens | H6: =Language!B156 -> Note | K6: =Language!B69 -> Local currency (reference only)
A7: =Language!B223 -> Illumina BaseSpace software and cloud storage | B7: =Language!B158 -> Single user annual licence | C7: 500 | D7: 1 | E7: 1600 | F7: 500 | G7: =IFERROR(C7*D7/E7*F7,0) -> 156.25 | H7: =Language!B165 -> Up to 1 TB storage is free and COVID Lineage App is free | K7: =IFERROR('Reagents and consumables'!$O$2*G7,"") -> 0
A8: =Language!B224 -> Illumina BaseSpace additional cloud storage | B8: =Language!B159 -> For added storage beyond 1 TB over 1 year. If this is utilized, enter 0.36 as Price (USD) | G8: =IFERROR(C8*D8/E8*F8,0) -> 0 | K8: =IFERROR('Reagents and consumables'!$O$2*G8,"") -> 0
A9: =Language!B225 -> Qiagen CLC Genomics Workbench software | B9: =Language!B160 -> Single user annual licence | G9: =IFERROR(C9*D9/E9*F9,0) -> 0 | K9: =IFERROR('Reagents and consumables'!$O$2*G9,"") -> 0
A10: =Language!B226 -> Terra.Bio computing and cloud storage | B10: =Language!B161 -> Computing and storage cost. If this is utilized, enter 0.5 (SARS-CoV-2 analysis) | G10: =IFERROR(C10*D10/E10*F10,0) -> 0 | K10: =IFERROR('Reagents and consumables'!$O$2*G10,"") -> 0
A11: =Language!B227 -> NextFlow tower software | B11: =Language!B162 -> Software plus computational | G11: =IFERROR(C11*D11/E11*F11,0) -> 0 | K11: =IFERROR('Reagents and consumables'!$O$2*G11,"") -> 0
A12: =Language!B228 -> External HDD for storage | B12: =Language!B163 -> External HDD – 1TB for storage | G12: =IFERROR(C12*D12/E12*F12,0) -> 0 | K12: =IFERROR('Reagents and consumables'!$O$2*G12,"") -> 0
A13: =Language!B229 -> Outsourced | B13: =Language!B164 -> If outsourced, enter total fee in Price (USD) column and enter Quantity as 1 | G13: =IFERROR(C13*D13/E13*F13,0) -> 0 | K13: =IFERROR('Reagents and consumables'!$O$2*G13,"") -> 0
A14: =Language!B369 -> Amazon Web Services (AWS) | G14: =IFERROR(C14*D14/E14*F14,0) -> 0 | K14: =IFERROR('Reagents and consumables'!$O$2*G14,"") -> 0
A15: =Language!B370 -> Seqera | G15: =IFERROR(C15*D15/E15*F15,0) -> 0 | K15: =IFERROR('Reagents and consumables'!$O$2*G15,"") -> 0
A16: =Language!B413 -> Deeplex WebApp | G16: =IFERROR(C16*D16/E16*F16,0) -> 0 | K16: =IFERROR('Reagents and consumables'!$O$2*G16,"") -> 0
A17: =Language!B430 -> Geneious | G17: =IFERROR(C17*D17/E17*F17,0) -> 0 | K17: =IFERROR('Reagents and consumables'!$O$2*G17,"") -> 0
G18: =IFERROR(C18*D18/E18*F18,0) -> 0 | K18: =IFERROR('Reagents and consumables'!$O$2*G18,"") -> 0
G19: =IFERROR(C19*D19/E19*F19,0) -> 0 | K19: =IFERROR('Reagents and consumables'!$O$2*G19,"") -> 0
G20: =IFERROR(C20*D20/E20*F20,0) -> 0 | K20: =IFERROR('Reagents and consumables'!$O$2*G20,"") -> 0
G21: =IFERROR(C21*D21/E21*F21,0) -> 0 | K21: =IFERROR('Reagents and consumables'!$O$2*G21,"") -> 0
F23: =Language!B168 -> Total purchase cost | G23: =SUM(G7:G21) -> 156.25
F24: =Language!B169 -> Total cost per sample | G24: =G23/('Data entry'!$F$32) -> 0.1953125
A26: =Language!B170 -> In-house computing
A27: =Language!B171 -> Component | B27: =Language!B152 -> Description | C27: =Language!B153 -> Price per unit (USD) | D27: =Language!B154 -> Quantity of units | E27: =Language!B90 -> Percentage of use for sequencing of selected pathogens | F27: =Language!B155 -> Total cost for the selected pathogens | G27: =Language!B86 -> Recommended lifetime (years) | H27: =Language!B87 -> Age of equipment (new=0) | I27: =Language!B173 -> Depreciation value / year | K27: =Language!B69 -> Local currency (reference only)
A28: =Language!B174 -> High-processing server | B28: =Language!B175 -> Server for bioinformatic storage and processing | F28: =C28*D28*E28 -> 0 | G28: 5 | H28: 1 | I28: =IFERROR(F28/G28,0) -> 0 | K28: =IFERROR('Reagents and consumables'!$O$2*F28,"") -> 0
B29: =Language!B176 -> HPE DL380 Gen10 8SFF CTO server (server chassis) | F29: =C29*D29*E29 -> 0 | I29: =IFERROR(F29/G29,0) -> 0 | K29: =IFERROR('Reagents and consumables'!$O$2*F29,"") -> 0
B30: =Language!B177 -> Intel Xeon-Gold 6234 (3.3GHz/8-core/130W) FIO processor kit for HPE ProLiant DL380 Gen10 | F30: =C30*D30*E30 -> 0 | I30: =IFERROR(F30/G30,0) -> 0 | K30: =IFERROR('Reagents and consumables'!$O$2*F30,"") -> 0
B31: =Language!B178 -> HPE 32GB (1x32GB) Dual Rank x4 DDR4-2933 CAS-21-21-21 registered smart memory kit | F31: =C31*D31*E31 -> 0 | I31: =IFERROR(F31/G31,0) -> 0 | K31: =IFERROR('Reagents and consumables'!$O$2*F31,"") -> 0
B32: =Language!B179 -> HPE NS204i-p x2 Lanes NVMe PCIe3 x8 OS Boot Device (boot drives – solid state storage) | F32: =C32*D32*E32 -> 0 | I32: =IFERROR(F32/G32,0) -> 0 | K32: =IFERROR('Reagents and consumables'!$O$2*F32,"") -> 0
B33: =Language!B180 -> NVIDIA A100 40GB PCIe computational accelerator for HPE (GPU) | F33: =C33*D33*E33 -> 0 | I33: =IFERROR(F33/G33,0) -> 0 | K33: =IFERROR('Reagents and consumables'!$O$2*F33,"") -> 0
B34: =Language!B181 -> HPE Smart Array P408i-a SR Gen10 (8 internal lanes/2GB cache) 12G SAS modular controller | F34: =C34*D34*E34 -> 0 | I34: =IFERROR(F34/G34,0) -> 0 | K34: =IFERROR('Reagents and consumables'!$O$2*F34,"") -> 0
B35: =Language!B182 -> HPE DL Gen10 x16/x16 GPU riser kit | F35: =C35*D35*E35 -> 0 | I35: =IFERROR(F35/G35,0) -> 0 | K35: =IFERROR('Reagents and consumables'!$O$2*F35,"") -> 0
B36: =Language!B183 -> HPE 96W Smart Storage lithium-ion battery with 145mm cable kit (storage battery) | F36: =C36*D36*E36 -> 0 | I36: =IFERROR(F36/G36,0) -> 0 | K36: =IFERROR('Reagents and consumables'!$O$2*F36,"") -> 0
B37: =Language!B184 -> HPE ethernet 10Gb 2-port FLR-SFP+ BCM57414 adapter (networking) | F37: =C37*D37*E37 -> 0 | I37: =IFERROR(F37/G37,0) -> 0 | K37: =IFERROR('Reagents and consumables'!$O$2*F37,"") -> 0
B38: =Language!B185 -> HPE BladeSystem c-Class 10Gb SFP+ SR transceiver (networking) | F38: =C38*D38*E38 -> 0 | I38: =IFERROR(F38/G38,0) -> 0 | K38: =IFERROR('Reagents and consumables'!$O$2*F38,"") -> 0
B39: =Language!B186 -> HPE DL38X Gen10 high performance temperature fan kit (cooling) | F39: =C39*D39*E39 -> 0 | I39: =IFERROR(F39/G39,0) -> 0 | K39: =IFERROR('Reagents and consumables'!$O$2*F39,"") -> 0
B40: =Language!B187 -> HPE 800W Flex Slot Platinum Hot Plug Low Halogen power supply kit | F40: =C40*D40*E40 -> 0 | I40: =IFERROR(F40/G40,0) -> 0 | K40: =IFERROR('Reagents and consumables'!$O$2*F40,"") -> 0
... B42: =Language!B189 -> HPE DL380 Gen10 High Performance Heat Sink kit (cooling) | F42: =C42*D42*E42 -> 0 | I42: =IFERROR(F42/G42,0) -> 0 | K42: =IFERROR('Reagents and consumables'!$O$2*F42,"") -> 0
A43: =Language!$B$197 -> Low/mid processing workstation | B43: =Language!$B$198 -> Computer workstation for bioinformatic analysis processing and storage | C43: 7028 | D43: 1 | E43: 1 | F43: =C43*D43*E43 -> 7028 | G43: 5 | H43: 2 | I43: =IFERROR(F43/G43,0) -> 1405.6 | K43: =IFERROR('Reagents and consumables'!$O$2*F43,"") -> 0
B44: =Language!$B$199 -> Intel Xeon processor 6226R 2.9GHz 2933MHz 16C 150W CPU | F44: =C44*D44*E44 -> 0 | I44: =IFERROR(F44/G44,0) -> 0 | K44: =IFERROR('Reagents and consumables'!$O$2*F44,"") -> 0
B45: =Language!$B$200 -> Intel Xeon processor 6226R 2.9GHz 2933MHz 16C 150W CPU | F45: =C45*D45*E45 -> 0 | I45: =IFERROR(F45/G45,0) -> 0 | K45: =IFERROR('Reagents and consumables'!$O$2*F45,"") -> 0
B46: =Language!$B$201 -> Memory drive – 128GB (4x32GB) DDR4 2933 DIMM ECC | F46: =C46*D46*E46 -> 0 | I46: =IFERROR(F46/G46,0) -> 0 | K46: =IFERROR('Reagents and consumables'!$O$2*F46,"") -> 0
B47: =Language!$B$202 -> Storage drives – 8TB 7200RPM SATA 3.5in enterprise | F47: =C47*D47*E47 -> 0 | I47: =IFERROR(F47/G47,0) -> 0 | K47: =IFERROR('Reagents and consumables'!$O$2*F47,"") -> 0
B48: =Language!$B$203 -> Keyboard USB business slim wired keyboard | F48: =C48*D48*E48 -> 0 | I48: =IFERROR(F48/G48,0) -> 0 | K48: =IFERROR('Reagents and consumables'!$O$2*F48,"") -> 0
B49: =Language!$B$204 -> HP optical wired mouse USB | F49: =C49*D49*E49 -> 0 | I49: =IFERROR(F49/G49,0) -> 0 | K49: =IFERROR('Reagents and consumables'!$O$2*F49,"") -> 0
B50: =Language!$B$205 -> 9.5mm DVD-writer 1st ODD | F50: =C50*D50*E50 -> 0 | I50: =IFERROR(F50/G50,0) -> 0 | K50: =IFERROR('Reagents and consumables'!$O$2*F50,"") -> 0
B51: =Language!$B$206 -> HP SD card reader | F51: =C51*D51*E51 -> 0 | I51: =IFERROR(F51/G51,0) -> 0 | K51: =IFERROR('Reagents and consumables'!$O$2*F51,"") -> 0
B52: =Language!$B$207 -> HP Z6 G4 memory cooling solution | F52: =C52*D52*E52 -> 0 | I52: =IFERROR(F52/G52,0) -> 0 | K52: =IFERROR('Reagents and consumables'!$O$2*F52,"") -> 0
A53: =Language!$B$211 -> NAS | B53: =Language!$B$208 -> NAS drive – 64TB for storage | C53: 3380 | D53: 1 | E53: 1 | F53: =C53*D53*E53 -> 3380 | G53: 2 | H53: 1 | I53: =IFERROR(F53/G53,0) -> 1690 | K53: =IFERROR('Reagents and consumables'!$O$2*F53,"") -> 0
A54: =Language!$B$212 -> Monitor | B54: =Language!$B$209 -> Monitor for bioinformatic analysis | C54: 150 | D54: 1 | E54: 1 | F54: =C54*D54*E54 -> 150 | G54: 2 | H54: 1 | I54: =IFERROR(F54/G54,0) -> 75 | K54: =IFERROR('Reagents and consumables'!$O$2*F54,"") -> 0
A55: =Language!$B$213 -> External HDD | B55: =Language!$B$210 -> External HDD – 1TB for storage | C55: 52 | D55: 1 | E55: 0.5 | F55: =C55*D55*E55 -> 26 | G55: 2 | H55: 1 | I55: =IFERROR(F55/G55,0) -> 13 | K55: =IFERROR('Reagents and consumables'!$O$2*F55,"") -> 0
A56: =Language!B193 -> Server maintenance | B56: =Language!B191 -> Server including maintenance fees | F56: =C56*D56*E56 -> 0 | G56: 2 | H56: 1 | I56: =IFERROR(F56/G56,0) -> 0 | K56: =IFERROR('Reagents and consumables'!$O$2*F56,"") -> 0
F57: =C57*D57*E57 -> 0 | I57: =IFERROR(F57/G57,0) -> 0 | K57: =IFERROR('Reagents and consumables'!$O$2*F57,"") -> 0
F58: =C58*D58*E58 -> 0 | I58: =IFERROR(F58/G58,0) -> 0 | K58: =IFERROR('Reagents and consumables'!$O$2*F58,"") -> 0
F59: =C59*D59*E59 -> 0 | I59: =IFERROR(F59/G59,0) -> 0 | K59: =IFERROR('Reagents and consumables'!$O$2*F59,"") -> 0
F60: =C60*D60*E60 -> 0 | I60: =IFERROR(F60/G60,0) -> 0 | K60: =IFERROR('Reagents and consumables'!$O$2*F60,"") -> 0
F61: =C61*D61*E61 -> 0 | I61: =IFERROR(F61/G61,0) -> 0 | K61: =IFERROR('Reagents and consumables'!$O$2*F61,"") -> 0
F62: =C62*D62*E62 -> 0 | I62: =IFERROR(F62/G62,0) -> 0 | K62: =IFERROR('Reagents and consumables'!$O$2*F62,"") -> 0
F63: =C63*D63*E63 -> 0 | I63: =IFERROR(F63/G63,0) -> 0 | K63: =IFERROR('Reagents and consumables'!$O$2*F63,"") -> 0
F64: =C64*D64*E64 -> 0 | I64: =IFERROR(F64/G64,0) -> 0 | K64: =IFERROR('Reagents and consumables'!$O$2*F64,"") -> 0
F65: =C65*D65*E65 -> 0 | I65: =IFERROR(F65/G65,0) -> 0 | K65: =IFERROR('Reagents and consumables'!$O$2*F65,"") -> 0
F66: =C66*D66*E66 -> 0 | I66: =IFERROR(F66/G66,0) -> 0 | K66: =IFERROR('Reagents and consumables'!$O$2*F66,"") -> 0
F67: =C67*D67*E67 -> 0 | I67: =IFERROR(F67/G67,0) -> 0 | K67: =IFERROR('Reagents and consumables'!$O$2*F67,"") -> 0
F68: =C68*D68*E68 -> 0 | I68: =IFERROR(F68/G68,0) -> 0 | K68: =IFERROR('Reagents and consumables'!$O$2*F68,"") -> 0
E70: =Language!B168 -> Total purchase cost | F70: =SUM(F28:F68) -> 10584 | H70: =Language!B195 -> Depreciation cost | I70: =SUM(I28:I68) -> 3183.6
E71: =Language!B169 -> Total cost per sample | F71: =I70/('Data entry'!$F$32) -> 3.9795
A73: =Language!B215 -> Hybrid, in-house and cloud-based | B73: =Language!B216 -> <-- for users with a combination from options above
B74: =Language!B221 -> Cloud-based
A75: =Language!B168 -> Total purchase cost | B75: =G23 -> 156.25
A76: =Language!B169 -> Total cost per sample | B76: =G24 -> 0.1953125
B78: =Language!B222 -> In-house
A79: =Language!B168 -> Total purchase cost | B79: =F70 -> 10584
A80: =Language!B217 -> Total depreciation cost | B80: =I70 -> 3183.6
A81: =Language!B169 -> Total cost per sample | B81: =F71 -> 3.9795
A83: =Language!B218 -> Total hybrid purchase cost | B83: =B75+B79 -> 10740.25
A84: =Language!B219 -> Total hybrid operational cost (cloud purchase + depreciation) | B84: =B75+B80 -> 3339.85
A85: =Language!B220 -> Total hybrid cost per sample | B85: =B84/('Data entry'!$F$32) -> 4.1748125

Sheet Quality management
B2: =Language!B230 -> Quality management
B3: =Language!B231 -> Quality management activity | C3: =Language!B232 -> Cost | D3: =Language!B233 -> Quantity | E3: =Language!B90 -> Percentage of use for sequencing of selected pathogens | F3: =Language!B234 -> Annual activity cost | G3: =Language!B235 -> Annual activity cost per sample | H3: =Language!B236 -> Comments | K3: =Language!B69 -> Local currency (reference only)
B4: Quality management activity | C4: Cost | D4: Quantity | E4: Column1 | F4: Annual activity cost | G4: Annual activity cost per sample | H4: Comments | K4: local currency (reference only)
B5: =Language!B237 -> ISO 15189 accreditation | C5: 4000 | D5: 1 | F5: =C5*D5*E5 -> 0 | G5: =IFERROR(F5/('Data entry'!$F$32),0) -> 0 | K5: =IFERROR('Reagents and consumables'!$O$2*F5,"") -> 0
B6: =Language!B238 -> External quality assessment – PCR | C6: 900 | D6: 1 | F6: =C6*D6*E6 -> 0 | G6: =IFERROR(F6/('Data entry'!$F$32),0) -> 0 | K6: =IFERROR('Reagents and consumables'!$O$2*F6,"") -> 0
B7: =Language!B239 -> External quality assessment – NGS | C7: 2300 | D7: 1 | F7: =C7*D7*E7 -> 0 | G7: =IFERROR(F7/('Data entry'!$F$32),0) -> 0 | H7: =Language!B241 -> Quarterly distribution, including logistics | K7: =IFERROR('Reagents and consumables'!$O$2*F7,"") -> 0
B8: =Language!B240 -> Annual BSC certification | C8: 300 | D8: 1 | E8: 0.5 | F8: =C8*D8*E8 -> 150 | G8: =IFERROR(F8/('Data entry'!$F$32),0) -> 0.1875 | H8: =Language!B329 -> Cost per BSC, including travel costs for the engineer | K8: =IFERROR('Reagents and consumables'!$O$2*F8,"") -> 0
B9: =Language!B371 -> Reference material: ATCC, Zeptometrix, Biohub, NCPV, NCTC, etc. | F9: =C9*D9*E9 -> 0 | G9: =IFERROR(F9/('Data entry'!$F$32),0) -> 0 | K9: =IFERROR('Reagents and consumables'!$O$2*F9,"") -> 0
B10: =Language!B372 -> Internal quality control material | C10: 200 | D10: 2 | E10: 0.1 | F10: =C10*D10*E10 -> 40 | G10: =IFERROR(F10/('Data entry'!$F$32),0) -> 0.05 | K10: =IFERROR('Reagents and consumables'!$O$2*F10,"") -> 0
B11: =Language!B373 -> Bioinformatics pipeline validation service (e.g. PHA4GE) | F11: =C11*D11*E11 -> 0 | G11: =IFERROR(F11/('Data entry'!$F$32),0) -> 0 | K11: =IFERROR('Reagents and consumables'!$O$2*F11,"") -> 0
F12: =C12*D12*E12 -> 0 | G12: =IFERROR(F12/('Data entry'!$F$32),0) -> 0 | K12: =IFERROR('Reagents and consumables'!$O$2*F12,"") -> 0
F13: =C13*D13*E13 -> 0 | G13: =IFERROR(F13/('Data entry'!$F$32),0) -> 0 | K13: =IFERROR('Reagents and consumables'!$O$2*F13,"") -> 0
F14: =C14*D14*E14 -> 0 | G14: =IFERROR(F14/('Data entry'!$F$32),0) -> 0 | K14: =IFERROR('Reagents and consumables'!$O$2*F14,"") -> 0
F15: =C15*D15*E15 -> 0 | G15: =IFERROR(F15/('Data entry'!$F$32),0) -> 0 | K15: =IFERROR('Reagents and consumables'!$O$2*F15,"") -> 0
F16: =C16*D16*E16 -> 0 | G16: =IFERROR(F16/('Data entry'!$F$32),0) -> 0 | K16: =IFERROR('Reagents and consumables'!$O$2*F16,"") -> 0
F17: =C17*D17*E17 -> 0 | G17: =IFERROR(F17/('Data entry'!$F$32),0) -> 0 | K17: =IFERROR('Reagents and consumables'!$O$2*F17,"") -> 0
F18: =C18*D18*E18 -> 0 | G18: =IFERROR(F18/('Data entry'!$F$32),0) -> 0 | K18: =IFERROR('Reagents and consumables'!$O$2*F18,"") -> 0
F19: =C19*D19*E19 -> 0 | G19: =IFERROR(F19/('Data entry'!$F$32),0) -> 0 | K19: =IFERROR('Reagents and consumables'!$O$2*F19,"") -> 0
F20: =C20*D20*E20 -> 0 | G20: =IFERROR(F20/('Data entry'!$F$32),0) -> 0 | K20: =IFERROR('Reagents and consumables'!$O$2*F20,"") -> 0
D23: =Language!B432 -> Calculated costs – Quality management
D24: =Language!B243 -> Total annual QMS cost | F24: =SUM(F5:F20) -> 190
D25: =Language!B244 -> QMS cost per sample | F25: =SUM(G5:G20) -> 0.2375

Sheet Results - USD
B2: =Language!B395 -> Results (in USD)
B4: =Language!$B$46 -> Output costs/results
B5: =Language!$B$48 -> Establishment costs (equipment and bioinformatics) | C5: =Equipment!$Q$103+(IF('Data entry'!$C$32='Annex1_Library Prep'!$AA$5, Bioinformatics!$B$75, IF('Data entry'!$C$32='Annex1_Library Prep'!$AA$6, Bioinformatics!$B$79, IF('Data entry'!$C$32='Annex1_Library Prep'!$AA$7, Bioinformatics!$B$83,0)))) -> 338444.06
B6: =Language!$B$92 -> Potential items for purchase to reach recommended equipment quantities | C6: =Equipment!$Q$104 -> 10790.172
B7: =Language!$B$49 -> Total operational cost (per year) | C7: ='Reagents and consumables'!$I$115+Equipment!$Q$107+$D$14+'Personnel and training'!$E$45+'Facility and transport'!$I$48+'Quality management'!$F$24 -> 271272.46
B9: =Language!$B$50 -> Costs per category | C9: =Language!$B$51 -> Cost per sample | D9: =Language!$B$52 -> Total
B10: =Language!$B$53 -> Reagents for sequencing and library preparation - Sequencer 1 (with sample retests) | C10: =IFERROR($D$10/('Data entry'!$C$16),0) -> 196.988 | D10: ='Reagents and consumables'!$J$110 -> 98494
B11: =Language!$B$336 -> Reagents for sequencing and library preparation – Sequencer 2 (with sample retests) | C11: =IFERROR($D$11/('Data entry'!$F$16),0) -> 0 | D11: ='Reagents and consumables'!$K$110 -> 0
B12: =Language!$B$54 -> Reagents and consumables (including sample retests) | C12: =D12/'Data entry'!$F$32 -> 191.31737 | D12: ='Reagents and consumables'!$I$115 -> 153053.9
B13: =Language!$B$382 -> Equipment operational cost | C13: =D13/'Data entry'!$F$32 -> 103.62339 | D13: =Equipment!$Q$107 -> 82898.714
B14: =Language!$B$56 -> Bioinformatics | C14: =D14/'Data entry'!$F$32 -> 4.1748125 | D14: =IF('Data entry'!$C$32='Annex1_Library Prep'!$AA$5, Bioinformatics!$G$23, IF('Data entry'!$C$32='Annex1_Library Prep'!$AA$6, Bioinformatics!$I$70, IF('Data entry'!$C$32='Annex1_Library Prep'!$AA$7, Bioinformatics!$B$84,0))) -> 3339.85 | E14: =IF(D14=0,Language!$B$350,"")
B15: =Language!$B$57 -> Personnel and training | C15: =D15/'Data entry'!$F$32 -> 31 | D15: ='Personnel and training'!$E$45 -> 24800 | E15: =IF(D15=0,Language!$B$351,"")
B16: =Language!$B$58 -> Facility and transport | C16: =D16/'Data entry'!$F$32 -> 8.7375 | D16: ='Facility and transport'!$I$48 -> 6990 | E16: =IF(D16=0,Language!$B$352,"")
B17: =Language!$B$59 -> Quality management | C17: =D17/'Data entry'!$F$32 -> 0.2375 | D17: ='Quality management'!$F$24 -> 190
B18: =Language!$B$52 -> Total | C18: =SUM(C12:C17) -> 339.09057 | D18: =SUM(D12:D17) -> 271272.46
B20: =Language!$B$60 -> Costs per lab workflow step | C20: =Language!$B$61 -> Cost per sample | D20: =Language!$B$52 -> Total | E20: =Language!$B$340
B21: =Language!$B$31 -> Sample receipt | C21: =D21/'Data entry'!$F$32 -> 26.76756 | D21: =SUMIF('Reagents and consumables'!$B$5:$B$105,"Yes",'Reagents and consumables'!$L$5:$L$105)+SUMIF(Equipment!$B$5:$B$99,"Yes",Equipment!$T$5:$T$99)+((SUM('Personnel and training'!$E$45+'Facility and transport'!$I$48+'Quality management'!$F$24))/6)+(SUM('Reagents and consumables'!$I$112)/6) -> 21414.048
B22: =Language!$B$32 -> Nucleic acid extraction | C22: =D22/'Data entry'!$F$32 -> 30.876295 | D22: =SUMIF('Reagents and consumables'!$C$5:$C$105,"Yes",'Reagents and consumables'!$L$5:$L$105)+SUMIF(Equipment!$C$5:$C$99,"Yes",Equipment!$T$5:$T$99)+((SUM('Personnel and training'!$E$45+'Facility and transport'!$I$48+'Quality management'!$F$24))/6)+(SUM('Reagents and consumables'!$I$112)/6) -> 24701.036
B23: =Language!$B$33 -> PCR testing | C23: =D23/'Data entry'!$F$32 -> 41.381946 | D23: =SUMIF('Reagents and consumables'!$D$5:$D$105,"Yes",'Reagents and consumables'!$L$5:$L$105)+SUMIF(Equipment!$D$5:$D$99,"Yes",Equipment!$T$5:$T$99)+((SUM('Personnel and training'!$E$45+'Facility and transport'!$I$48+'Quality management'!$F$24))/6)+(SUM('Reagents and consumables'!$I$112)/6) -> 33105.557
B24: =Language!$B$34 -> NGS library preparation | C24: =D24/'Data entry'!$F$32 -> 77.517733 | D24: =SUMIF('Reagents and consumables'!$E$5:$E$105,"Yes",'Reagents and consumables'!$L$5:$L$105)+SUMIF(Equipment!$E$5:$E$99,"Yes",Equipment!$T$5:$T$99)+((SUM('Personnel and training'!$E$45+'Facility and transport'!$I$48+'Quality management'!$F$24))/6)+(SUM('Reagents and consumables'!$I$112)/6) -> 62014.186
B25: =Language!$B$35 -> Sequencing | C25: =D25/'Data entry'!$F$32 -> 149.18163 | D25: =SUMIF('Reagents and consumables'!$F$5:$F$105,"Yes",'Reagents and consumables'!$L$5:$L$105)+SUMIF(Equipment!$F$5:$F$99,"Yes",Equipment!$T$5:$T$99)+((SUM('Personnel and training'!$E$45+'Facility and transport'!$I$48+'Quality management'!$F$24))/6)+(SUM('Reagents and consumables'!$I$112)/6) -> 119345.3
B26: =Language!$B$36 -> Bioinformatics | C26: =D26/'Data entry'!$F$32 -> 13.365412 | D26: =D14+((SUM('Personnel and training'!$E$45+'Facility and transport'!$I$48+'Quality management'!$F$24))/6)+(SUM('Reagents and consumables'!$I$112)/6) -> 10692.33
B27: =Language!$B$52 -> Total | C27: =SUM(C21:C26) -> 339.09057 | D27: =SUM(D21:D26) -> 271272.46

Sheet Results - local currency
B2: =Language!B410 -> Results (in local currency) - provided that the conversion rate from USD to local currency has been entered in cell O2 in the "Reagents and consumables" tab
B4: =Language!$B$46 -> Output costs/results
B5: =Language!$B$48 -> Establishment costs (equipment and bioinformatics) | C5: =(Equipment!$Q$103+(IF('Data entry'!$C$32='Annex1_Library Prep'!$AA$5, Bioinformatics!$B$75, IF('Data entry'!$C$32='Annex1_Library Prep'!$AA$6, Bioinformatics!$B$79, IF('Data entry'!$C$32='Annex1_Library Prep'!$AA$7, Bioinformatics!$B$83,0)))))*'Reagents and consumables'!O2 -> 0 | E5: =IF(C5=0,Language!B411,"") -> Make sure to enter conversion rate from USD to local currency in cell O2 in the "Reagents and consumables" tab
B6: =Language!$B$92 -> Potential items for purchase to reach recommended equipment quantities | C6: =Equipment!$Q$104*'Reagents and consumables'!O2 -> 0
B7: =Language!$B$49 -> Total operational cost (per year) | C7: =('Reagents and consumables'!$I$115+Equipment!$Q$107+$D$14+'Personnel and training'!$E$45+'Facility and transport'!$I$48+'Quality management'!$F$24)*'Reagents and consumables'!O2 -> 0
B9: =Language!$B$50 -> Costs per category | C9: =Language!$B$51 -> Cost per sample | D9: =Language!$B$52 -> Total
B10: =Language!$B$53 -> Reagents for sequencing and library preparation - Sequencer 1 (with sample retests) | C10: =IFERROR($D$10/('Data entry'!$C$16),0) -> 0 | D10: ='Reagents and consumables'!$J$110*'Reagents and consumables'!O2 -> 0
B11: =Language!$B$336 -> Reagents for sequencing and library preparation – Sequencer 2 (with sample retests) | C11: =IFERROR($D$11/('Data entry'!$F$16),0) -> 0 | D11: ='Reagents and consumables'!$K$110*'Reagents and consumables'!O2 -> 0
B12: =Language!$B$54 -> Reagents and consumables (including sample retests) | C12: =D12/'Data entry'!$F$32 -> 0 | D12: ='Reagents and consumables'!$I$115*'Reagents and consumables'!O2 -> 0
B13: =Language!$B$382 -> Equipment operational cost | C13: =D13/'Data entry'!$F$32 -> 0 | D13: =Equipment!$Q$107*'Reagents and consumables'!O2 -> 0
B14: =Language!$B$56 -> Bioinformatics | C14: =D14/'Data entry'!$F$32 -> 0 | D14: =(IF('Data entry'!$C$32='Annex1_Library Prep'!$AA$5, Bioinformatics!$G$23, IF('Data entry'!$C$32='Annex1_Library Prep'!$AA$6, Bioinformatics!$I$70, IF('Data entry'!$C$32='Annex1_Library Prep'!$AA$7, Bioinformatics!$B$84,0))))*'Reagents and consumables'!O2 -> 0 | E14: =IF(D14=0,Language!$B$350,"") -> Inputs into "Bioinformatics" tab needed to display cost
B15: =Language!$B$57 -> Personnel and training | C15: =D15/'Data entry'!$F$32 -> 0 | D15: ='Personnel and training'!$E$45*'Reagents and consumables'!O2 -> 0 | E15: =IF(D15=0,Language!$B$351,"") -> Inputs into "Personnel and training" tab needed to display cost
B16: =Language!$B$58 -> Facility and transport | C16: =D16/'Data entry'!$F$32 -> 0 | D16: ='Facility and transport'!$I$48*'Reagents and consumables'!O2 -> 0 | E16: =IF(D16=0,Language!$B$352,"") -> Inputs into "Facility and transport" tab needed to display cost
B17: =Language!$B$59 -> Quality management | C17: =D17/'Data entry'!$F$32 -> 0 | D17: ='Quality management'!$F$24*'Reagents and consumables'!O2 -> 0
B18: =Language!$B$52 -> Total | C18: =SUM(C12:C17) -> 0 | D18: =SUM(D12:D17) -> 0
B20: =Language!$B$60 -> Costs per lab workflow step | C20: =Language!$B$61 -> Cost per sample | D20: =Language!$B$52 -> Total | E20: =Language!$B$340
B21: =Language!$B$31 -> Sample receipt | C21: =D21/'Data entry'!$F$32 -> 0 | D21: =(SUMIF('Reagents and consumables'!$B$5:$B$105,"Yes",'Reagents and consumables'!$L$5:$L$105)+SUMIF(Equipment!$B$5:$B$99,"Yes",Equipment!$T$5:$T$99)+((SUM('Personnel and training'!$E$45+'Facility and transport'!$I$48+'Quality management'!$F$24))/6)+(SUM('Reagents and consumables'!$I$112)/6))*'Reagents and consumables'!O2 -> 0
B22: =Language!$B$32 -> Nucleic acid extraction | C22: =D22/'Data entry'!$F$32 -> 0 | D22: =(SUMIF('Reagents and consumables'!$C$5:$C$105,"Yes",'Reagents and consumables'!$L$5:$L$105)+SUMIF(Equipment!$C$5:$C$99,"Yes",Equipment!$T$5:$T$99)+((SUM('Personnel and training'!$E$45+'Facility and transport'!$I$48+'Quality management'!$F$24))/6)+(SUM('Reagents and consumables'!$I$112)/6))*'Reagents and consumables'!O2 -> 0
B23: =Language!$B$33 -> PCR testing | C23: =D23/'Data entry'!$F$32 -> 0 | D23: =(SUMIF('Reagents and consumables'!$D$5:$D$105,"Yes",'Reagents and consumables'!$L$5:$L$105)+SUMIF(Equipment!$D$5:$D$99,"Yes",Equipment!$T$5:$T$99)+((SUM('Personnel and training'!$E$45+'Facility and transport'!$I$48+'Quality management'!$F$24))/6)+(SUM('Reagents and consumables'!$I$112)/6))*'Reagents and consumables'!O2 -> 0
B24: =Language!$B$34 -> NGS library preparation | C24: =D24/'Data entry'!$F$32 -> 0 | D24: =(SUMIF('Reagents and consumables'!$E$5:$E$105,"Yes",'Reagents and consumables'!$L$5:$L$105)+SUMIF(Equipment!$E$5:$E$99,"Yes",Equipment!$T$5:$T$99)+((SUM('Personnel and training'!$E$45+'Facility and transport'!$I$48+'Quality management'!$F$24))/6)+(SUM('Reagents and consumables'!$I$112)/6))*'Reagents and consumables'!O2 -> 0
B25: =Language!$B$35 -> Sequencing | C25: =D25/'Data entry'!$F$32 -> 0 | D25: =(SUMIF('Reagents and consumables'!$F$5:$F$105,"Yes",'Reagents and consumables'!$L$5:$L$105)+SUMIF(Equipment!$F$5:$F$99,"Yes",Equipment!$T$5:$T$99)+((SUM('Personnel and training'!$E$45+'Facility and transport'!$I$48+'Quality management'!$F$24))/6)+(SUM('Reagents and consumables'!$I$112)/6))*'Reagents and consumables'!O2 -> 0
B26: =Language!$B$36 -> Bioinformatics | C26: =D26/'Data entry'!$F$32 -> 0 | D26: =D14+(((SUM('Personnel and training'!$E$45+'Facility and transport'!$I$48+'Quality management'!$F$24))/6)+(SUM('Reagents and consumables'!$I$112)/6))*'Reagents and consumables'!O2 -> 0
B27: =Language!$B$52 -> Total | C27: =SUM(C21:C26) -> 0 | D27: =SUM(D21:D26) -> 0

Sheet Annex1_Library Prep
B2: 1 | J2: 2 | K2: Seq1 | L2: Seq2 | M2: 3 | O2: Seq1 | S2: Seq2
B3: Category 1 (mix of DNA and RNA VIRUS library prep kits) | E3: Category 2 (bacteria) | H3: Category 3 (multi-pathogen kits) | J3: Pathogen check - Seq1 | K3: Pathogen-dependent sublists of lib prep kits | L3: Pathogen-dependent sublists of lib prep kits | M3: Flag | N3: Platform Check | O3: Sublists filtered by the supplier (with blanks) | P3: Sublists filtered by supplier (no blanks) | Q3: Flag | R3: Platform Check | S3: Sublists filtered by the supplier (with blanks) | T3: Sublists filtered by supplier (no blanks) | V3: Languages | W3: Pathogen type | X3: Sequencing method | Y3: Workflow | Z3: Y/N | AA3: Bioinformatics
B4: RNA or DNA virus (all but influenza and SARS-CoV-2) | C4: ='Annex4_Coverage Sample Calc'!C27 -> influenza virus | D4: ='Annex4_Coverage Sample Calc'!C38 -> severe acute respiratory syndrome coronavirus 2 (SARS-CoV-2) | E4: ='Annex1_Library Prep'!W6 -> Bacterial | F4: ='Annex4_Coverage Sample Calc'!C40 -> Mycobacterium tuberculosis (WGS) | G4: ='Annex4_Coverage Sample Calc'!C41 -> Mycobacterium tuberculosis (tNGS) | J4: ='Data entry'!$C$14 -> Salmonella spp. | K4: {=IF($J$4=$C$4, $C$5:$C$18, IF($J$4=$D$4, $D$5:$D$21, IF($J$4=$F$4, $F$5:$F$15, IF($J$4=$G$4, $G$5:$G$10, IF(AND(ISNUMBER(SEARCH("virus", $J$4)), ISERROR(SEARCH($C$4, $J$4)), ISERROR(SEARCH($D$4, $J$4))), $B$5:$B$16, IF('Data entry'!$C$13=$W$6, $E$5:$E$15, IF('Data entry'!$C$13=$W$7, $H$5:$H$9,"")))))))} -> Illumina DNA Prep, (M) Tagmentation (96 Samples, IPB) | L4: {=IF($J$9=$C$4, $C$5:$C$18, IF($J$9=$D$4, $D$5:$D$21, IF($J$9=$F$4, $F$5:$F$15, IF($J$9=$G$4, $G$5:$G$10, IF(AND(ISNUMBER(SEARCH("virus", $J$9)), ISERROR(SEARCH($C$4, $J$9)), ISERROR(SEARCH($D$4, $J$9))), $B$5:$B$16, IF('Data entry'!$F$13=$W$6, $E$5:$E$15, IF('Data entry'!$F$13=$W$7, $H$5:$H$9,"")))))))} -> Illumina DNA Prep, (M) Tagmentation (96 Samples, IPB) | M4: =ISNUMBER(SEARCH($N$4,'Data entry'!$C$17)) -> TRUE | N4: Illumina | O4: =IF(COUNTIF($M$4:$M$7, TRUE) = 0, IF(K4<>0, K4, ""), IF(ISNUMBER(SEARCH(INDEX($N$4:$N$7, MATCH(TRUE, $M$4:$M$7, 0)), K4)), K4, "")) -> Illumina DNA Prep, (M) Tagmentation (96 Samples, IPB) | P4: Other library preparation kit | Q4: =ISNUMBER(SEARCH($N$4,'Data entry'!$F$17)) -> FALSE | R4: Illumina | S4: =IF(COUNTIF($Q$4:$Q$7, TRUE) = 0, IF(L4<>0, L4, ""), IF(ISNUMBER(SEARCH(INDEX($R$4:$R$7, MATCH(TRUE, $Q$4:$Q$7, 0)), L4)), L4, "")) | T4: Other library preparation kit | V4: <blank> | W4: <blank> | X4: <blank> | Y4: <blank> | Z4: <blank> | AA4: <blank>
B5: =$D$55 -> Illumina DNA Prep, (M) Tagmentation (96 Samples, IPB) | C5: =$D$55 -> Illumina DNA Prep, (M) Tagmentation (96 Samples, IPB) | D5: =$D$52 -> Illumina: COVIDSeq Assay (96 Samples) | E5: =$D$55 -> Illumina DNA Prep, (M) Tagmentation (96 Samples, IPB) | F5: =$D$55 -> Illumina DNA Prep, (M) Tagmentation (96 Samples, IPB) | G5: =$D$78 -> Illumina and Genoscreen Deeplex Myc-TB Combo IDP Kit (48 samples) | H5: =$D$63 -> Illumina Microbial Amplicon Prep | K5: Nextera XT DNA Library Preparation Kit for Illumina | L5: Nextera XT DNA Library Preparation Kit for Illumina | M5: =ISNUMBER(SEARCH($N$5,'Data entry'!$C$17)) -> FALSE | N5: ONT | O5: =IF(COUNTIF($M$4:$M$7, TRUE) = 0, IF(K5<>0, K5, ""), IF(ISNUMBER(SEARCH(INDEX($N$4:$N$7, MATCH(TRUE, $M$4:$M$7, 0)), K5)), K5, "")) -> Nextera XT DNA Library Preparation Kit for Illumina | P5: {=IFERROR(INDEX($O$3:$O$24, SMALL(IF(($O$3:$O$24<>0)*($O$3:$O$24<>""), ROW($O$3:$O$24)-ROW($O$3)+1), ROW(A2))), "")} -> Illumina DNA Prep, (M) Tagmentation (96 Samples, IPB) | Q5: =ISNUMBER(SEARCH($N$5,'Data entry'!$F$17)) -> TRUE | R5: ONT | S5: =IF(COUNTIF($Q$4:$Q$7, TRUE) = 0, IF(L5<>0, L5, ""), IF(ISNUMBER(SEARCH(INDEX($R$4:$R$7, MATCH(TRUE, $Q$4:$Q$7, 0)), L5)), L5, "")) | T5: {=IFERROR(INDEX($S$3:$S$24, SMALL(IF(($S$3:$S$24<>0)*($S$3:$S$24<>""), ROW($S$3:$S$24)-ROW($S$3)+1), ROW(A2))),"")} -> ONT Ligation Sequencing Kit V14 protocol with Native Barcoding Kit 24 V14 | V5: =Language!C3 -> English | W5: Viral | X5: Whole genome | Y5: Sample receipt | Z5: Yes | AA5: Cloud-based analysis software
B6: =$D$67 -> Nextera XT DNA Library Preparation Kit for Illumina | C6: =$D$62 -> Illumina Microbial Amplicon Prep—Influenza A/B | D6: =$D$55 -> Illumina DNA Prep, (M) Tagmentation (96 Samples, IPB) | E6: =$D$67 -> Nextera XT DNA Library Preparation Kit for Illumina | F6: =$D$67 -> Nextera XT DNA Library Preparation Kit for Illumina | G6: =$D$82 -> Illumina and Genoscreen Deeplex Myc-TB Combo XT Kit (48 samples) | H6: =$D$71 -> Illumina: Respiratory Pathogen ID/AMR Enrichment Panel Kit | K6: NEBNext Ultra II DNA Library Prep with Sample Purification Beads for Illumina | L6: NEBNext Ultra II DNA Library Prep with Sample Purification Beads for Illumina | M6: =ISNUMBER(SEARCH($N$6,'Data entry'!$C$17)) -> FALSE | N6: Thermofisher | O6: =IF(COUNTIF($M$4:$M$7, TRUE) = 0, IF(K6<>0, K6, ""), IF(ISNUMBER(SEARCH(INDEX($N$4:$N$7, MATCH(TRUE, $M$4:$M$7, 0)), K6)), K6, "")) -> NEBNext Ultra II DNA Library Prep with Sample Purification Beads for Illumina | P6: {=IFERROR(INDEX($O$3:$O$24, SMALL(IF(($O$3:$O$24<>0)*($O$3:$O$24<>""), ROW($O$3:$O$24)-ROW($O$3)+1), ROW(A3))), "")} -> Nextera XT DNA Library Preparation Kit for Illumina | Q6: =ISNUMBER(SEARCH($N$6,'Data entry'!$F$17)) -> FALSE | R6: Thermofisher | S6: =IF(COUNTIF($Q$4:$Q$7, TRUE) = 0, IF(L6<>0, L6, ""), IF(ISNUMBER(SEARCH(INDEX($R$4:$R$7, MATCH(TRUE, $Q$4:$Q$7, 0)), L6)), L6, "")) | T6: {=IFERROR(INDEX($S$3:$S$24, SMALL(IF(($S$3:$S$24<>0)*($S$3:$S$24<>""), ROW($S$3:$S$24)-ROW($S$3)+1), ROW(A3))),"")} -> ONT Ligation Sequencing Kit V14 protocol with Native Barcoding Kit 96 V14 | V6: =Language!F3 -> French | W6: Bacterial | X6: Targeted genome | Y6: Nucleic acid extraction | Z6: No | AA6: In-house computing
B7: =$D$74 -> NEBNext Ultra II DNA Library Prep with Sample Purification Beads for Illumina | C7: =$D$67 -> Nextera XT DNA Library Preparation Kit for Illumina | D7: =$D$59 -> Illumina: COVIDSeq Test (RUO Version) (3072 Samples) | E7: =$D$74 -> NEBNext Ultra II DNA Library Prep with Sample Purification Beads for Illumina | F7: =$D$74 -> NEBNext Ultra II DNA Library Prep with Sample Purification Beads for Illumina | G7: =$D$144 -> TBSeq Mycobacterium nucleic acid and M. tuberculosis drug resistance gene detection kits for ONT | H7: =$D$73 -> Illumina Viral Surveillance Panel v2 Kit | K7: ONT Ligation Sequencing Kit V14 protocol with Native Barcoding Kit 24 V14 | L7: ONT Ligation Sequencing Kit V14 protocol with Native Barcoding Kit 24 V14 | M7: =ISNUMBER(SEARCH($N$7,'Data entry'!$C$17)) -> FALSE | N7: MGI | O7: =IF(COUNTIF($M$4:$M$7, TRUE) = 0, IF(K7<>0, K7, ""), IF(ISNUMBER(SEARCH(INDEX($N$4:$N$7, MATCH(TRUE, $M$4:$M$7, 0)), K7)), K7, "")) | P7: {=IFERROR(INDEX($O$3:$O$24, SMALL(IF(($O$3:$O$24<>0)*($O$3:$O$24<>""), ROW($O$3:$O$24)-ROW($O$3)+1), ROW(A4))), "")} -> NEBNext Ultra II DNA Library Prep with Sample Purification Beads for Illumina | Q7: =ISNUMBER(SEARCH($N$7,'Data entry'!$F$17)) -> FALSE | R7: MGI | S7: =IF(COUNTIF($Q$4:$Q$7, TRUE) = 0, IF(L7<>0, L7, ""), IF(ISNUMBER(SEARCH(INDEX($R$4:$R$7, MATCH(TRUE, $Q$4:$Q$7, 0)), L7)), L7, "")) -> ONT Ligation Sequencing Kit V14 protocol with Native Barcoding Kit 24 V14 | T7: {=IFERROR(INDEX($S$3:$S$24, SMALL(IF(($S$3:$S$24<>0)*($S$3:$S$24<>""), ROW($S$3:$S$24)-ROW($S$3)+1), ROW(A4))),"")} -> ONT Ligation Sequencing Kit XL V14 protocol with Native Barcoding Kit 96 V14 | V7: =Language!D3 -> Russian | W7: Capture-all (multiple pathogens) | Y7: PCR testing | Z7: Not applicable | AA7: Hybrid, in-house and cloud-based
B8: =$D$89 -> ONT Direct RNA Sequencing Kit | C8: =$D$74 -> NEBNext Ultra II DNA Library Prep with Sample Purification Beads for Illumina | D8: =$D$67 -> Nextera XT DNA Library Preparation Kit for Illumina | E8: =$D$98 -> ONT Ligation Sequencing Kit V14 protocol with Native Barcoding Kit 24 V14 | F8: =$D$98 -> ONT Ligation Sequencing Kit V14 protocol with Native Barcoding Kit 24 V14 | G8: =$D$147 -> ONT AmPORE TB | H8: =$D$66 -> Illumina Respiratory Virus Enrichment Kit | J8: Pathogen check-Seq2 | K8: ONT Ligation Sequencing Kit V14 protocol with Native Barcoding Kit 96 V14 | L8: ONT Ligation Sequencing Kit V14 protocol with Native Barcoding Kit 96 V14 | O8: =IF(COUNTIF($M$4:$M$7, TRUE) = 0, IF(K8<>0, K8, ""), IF(ISNUMBER(SEARCH(INDEX($N$4:$N$7, MATCH(TRUE, $M$4:$M$7, 0)), K8)), K8, "")) | P8: {=IFERROR(INDEX($O$3:$O$24, SMALL(IF(($O$3:$O$24<>0)*($O$3:$O$24<>""), ROW($O$3:$O$24)-ROW($O$3)+1), ROW(A5))), "")} | S8: =IF(COUNTIF($Q$4:$Q$7, TRUE) = 0, IF(L8<>0, L8, ""), IF(ISNUMBER(SEARCH(INDEX($R$4:$R$7, MATCH(TRUE, $Q$4:$Q$7, 0)), L8)), L8, "")) -> ONT Ligation Sequencing Kit V14 protocol with Native Barcoding Kit 96 V14 | T8: {=IFERROR(INDEX($S$3:$S$24, SMALL(IF(($S$3:$S$24<>0)*($S$3:$S$24<>""), ROW($S$3:$S$24)-ROW($S$3)+1), ROW(A5))),"")} -> ONT Rapid Barcoding Kit 24 V14 | V8: =Language!E3 -> Spanish | Y8: NGS library preparation
B9: =$D$98 -> ONT Ligation Sequencing Kit V14 protocol with Native Barcoding Kit 24 V14 | C9: =$D$89 -> ONT Direct RNA Sequencing Kit | D9: =$D$74 -> NEBNext Ultra II DNA Library Prep with Sample Purification Beads for Illumina | E9: =$D$105 -> ONT Ligation Sequencing Kit V14 protocol with Native Barcoding Kit 96 V14 | F9: =$D$105 -> ONT Ligation Sequencing Kit V14 protocol with Native Barcoding Kit 96 V14 | G9: =$D$194 -> MGI ATOPlex MTB Library Preparation Set | H9: 16S Barcoding Kit 24 | J9: ='Data entry'!$F$14 -> Escherichia coli | K9: ONT Ligation Sequencing Kit XL V14 protocol with Native Barcoding Kit 96 V14 | L9: ONT Ligation Sequencing Kit XL V14 protocol with Native Barcoding Kit 96 V14 | O9: =IF(COUNTIF($M$4:$M$7, TRUE) = 0, IF(K9<>0, K9, ""), IF(ISNUMBER(SEARCH(INDEX($N$4:$N$7, MATCH(TRUE, $M$4:$M$7, 0)), K9)), K9, "")) | P9: {=IFERROR(INDEX($O$3:$O$24, SMALL(IF(($O$3:$O$24<>0)*($O$3:$O$24<>""), ROW($O$3:$O$24)-ROW($O$3)+1), ROW(A6))), "")} | S9: =IF(COUNTIF($Q$4:$Q$7, TRUE) = 0, IF(L9<>0, L9, ""), IF(ISNUMBER(SEARCH(INDEX($R$4:$R$7, MATCH(TRUE, $Q$4:$Q$7, 0)), L9)), L9, "")) -> ONT Ligation Sequencing Kit XL V14 protocol with Native Barcoding Kit 96 V14 | T9: {=IFERROR(INDEX($S$3:$S$24, SMALL(IF(($S$3:$S$24<>0)*($S$3:$S$24<>""), ROW($S$3:$S$24)-ROW($S$3)+1), ROW(A6))),"")} -> ONT Rapid Barcoding Kit 96 V14 | V9: =Language!G3 -> Turkish | Y9: Sequencing
B10: =$D$105 -> ONT Ligation Sequencing Kit V14 protocol with Native Barcoding Kit 96 V14 | C10: =$D$98 -> ONT Ligation Sequencing Kit V14 protocol with Native Barcoding Kit 24 V14 | D10: =$D$86 -> ONT COVID Mini V14: 576 samples | E10: =$D$112 -> ONT Ligation Sequencing Kit XL V14 protocol with Native Barcoding Kit 96 V14 | F10: =$D$112 -> ONT Ligation Sequencing Kit XL V14 protocol with Native Barcoding Kit 96 V14 | G10: =$D$196 -> DeepChek Assay 13-Plex KB Drug Susceptibility Testing | K10: ONT Rapid Barcoding Kit 24 V14 | L10: ONT Rapid Barcoding Kit 24 V14 | O10: =IF(COUNTIF($M$4:$M$7, TRUE) = 0, IF(K10<>0, K10, ""), IF(ISNUMBER(SEARCH(INDEX($N$4:$N$7, MATCH(TRUE, $M$4:$M$7, 0)), K10)), K10, "")) | P10: {=IFERROR(INDEX($O$3:$O$24, SMALL(IF(($O$3:$O$24<>0)*($O$3:$O$24<>""), ROW($O$3:$O$24)-ROW($O$3)+1), ROW(A7))), "")} | S10: =IF(COUNTIF($Q$4:$Q$7, TRUE) = 0, IF(L10<>0, L10, ""), IF(ISNUMBER(SEARCH(INDEX($R$4:$R$7, MATCH(TRUE, $Q$4:$Q$7, 0)), L10)), L10, "")) -> ONT Rapid Barcoding Kit 24 V14 | T10: {=IFERROR(INDEX($S$3:$S$24, SMALL(IF(($S$3:$S$24<>0)*($S$3:$S$24<>""), ROW($S$3:$S$24)-ROW($S$3)+1), ROW(A7))),"")} -> ONT Rapid PCR Barcoding Kit 24 V14 protocol | Y10: Bioinformatics
B11: =$D$112 -> ONT Ligation Sequencing Kit XL V14 protocol with Native Barcoding Kit 96 V14 | C11: =$D$105 -> ONT Ligation Sequencing Kit V14 protocol with Native Barcoding Kit 96 V14 | D11: =$D$89 -> ONT Direct RNA Sequencing Kit | E11: =$D$131 -> ONT Rapid Barcoding Kit 24 V14 | F11: =$D$131 -> ONT Rapid Barcoding Kit 24 V14 | K11: ONT Rapid Barcoding Kit 96 V14 | L11: ONT Rapid Barcoding Kit 96 V14 | O11: =IF(COUNTIF($M$4:$M$7, TRUE) = 0, IF(K11<>0, K11, ""), IF(ISNUMBER(SEARCH(INDEX($N$4:$N$7, MATCH(TRUE, $M$4:$M$7, 0)), K11)), K11, "")) | P11: {=IFERROR(INDEX($O$3:$O$24, SMALL(IF(($O$3:$O$24<>0)*($O$3:$O$24<>""), ROW($O$3:$O$24)-ROW($O$3)+1), ROW(A8))), "")} | S11: =IF(COUNTIF($Q$4:$Q$7, TRUE) = 0, IF(L11<>0, L11, ""), IF(ISNUMBER(SEARCH(INDEX($R$4:$R$7, MATCH(TRUE, $Q$4:$Q$7, 0)), L11)), L11, "")) -> ONT Rapid Barcoding Kit 96 V14 | T11: {=IFERROR(INDEX($S$3:$S$24, SMALL(IF(($S$3:$S$24<>0)*($S$3:$S$24<>""), ROW($S$3:$S$24)-ROW($S$3)+1), ROW(A8))),"")}
B12: =$D$131 -> ONT Rapid Barcoding Kit 24 V14 | C12: =$D$112 -> ONT Ligation Sequencing Kit XL V14 protocol with Native Barcoding Kit 96 V14 | D12: =$D$98 -> ONT Ligation Sequencing Kit V14 protocol with Native Barcoding Kit 24 V14 | E12: =$D$135 -> ONT Rapid Barcoding Kit 96 V14 | F12: =$D$135 -> ONT Rapid Barcoding Kit 96 V14 | K12: ONT Rapid PCR Barcoding Kit 24 V14 protocol | L12: ONT Rapid PCR Barcoding Kit 24 V14 protocol | O12: =IF(COUNTIF($M$4:$M$7, TRUE) = 0, IF(K12<>0, K12, ""), IF(ISNUMBER(SEARCH(INDEX($N$4:$N$7, MATCH(TRUE, $M$4:$M$7, 0)), K12)), K12, "")) | P12: {=IFERROR(INDEX($O$3:$O$24, SMALL(IF(($O$3:$O$24<>0)*($O$3:$O$24<>""), ROW($O$3:$O$24)-ROW($O$3)+1), ROW(A9))), "")} | S12: =IF(COUNTIF($Q$4:$Q$7, TRUE) = 0, IF(L12<>0, L12, ""), IF(ISNUMBER(SEARCH(INDEX($R$4:$R$7, MATCH(TRUE, $Q$4:$Q$7, 0)), L12)), L12, "")) -> ONT Rapid PCR Barcoding Kit 24 V14 protocol | T12: {=IFERROR(INDEX($S$3:$S$24, SMALL(IF(($S$3:$S$24<>0)*($S$3:$S$24<>""), ROW($S$3:$S$24)-ROW($S$3)+1), ROW(A9))),"")}
B13: =$D$135 -> ONT Rapid Barcoding Kit 96 V14 | C13: =$D$131 -> ONT Rapid Barcoding Kit 24 V14 | D13: =$D$105 -> ONT Ligation Sequencing Kit V14 protocol with Native Barcoding Kit 96 V14 | E13: =$D$139 -> ONT Rapid PCR Barcoding Kit 24 V14 protocol | F13: =$D$139 -> ONT Rapid PCR Barcoding Kit 24 V14 protocol | K13: Thermofisher Ion Xpress Plus Fragment Library Kit | L13: Thermofisher Ion Xpress Plus Fragment Library Kit | O13: =IF(COUNTIF($M$4:$M$7, TRUE) = 0, IF(K13<>0, K13, ""), IF(ISNUMBER(SEARCH(INDEX($N$4:$N$7, MATCH(TRUE, $M$4:$M$7, 0)), K13)), K13, "")) | P13: {=IFERROR(INDEX($O$3:$O$24, SMALL(IF(($O$3:$O$24<>0)*($O$3:$O$24<>""), ROW($O$3:$O$24)-ROW($O$3)+1), ROW(A10))), "")} | S13: =IF(COUNTIF($Q$4:$Q$7, TRUE) = 0, IF(L13<>0, L13, ""), IF(ISNUMBER(SEARCH(INDEX($R$4:$R$7, MATCH(TRUE, $Q$4:$Q$7, 0)), L13)), L13, "")) | T13: {=IFERROR(INDEX($S$3:$S$24, SMALL(IF(($S$3:$S$24<>0)*($S$3:$S$24<>""), ROW($S$3:$S$24)-ROW($S$3)+1), ROW(A10))),"")}
B14: =$D$139 -> ONT Rapid PCR Barcoding Kit 24 V14 protocol | C14: =$D$135 -> ONT Rapid Barcoding Kit 96 V14 | D14: =$D$112 -> ONT Ligation Sequencing Kit XL V14 protocol with Native Barcoding Kit 96 V14 | E14: =$D$149 -> Thermofisher Ion Xpress Plus Fragment Library Kit | F14: =$D$149 -> Thermofisher Ion Xpress Plus Fragment Library Kit | K14: MGIEasy Fast FS DNA Library Prep Set V2.0 (96 RXN) | L14: MGIEasy Fast FS DNA Library Prep Set V2.0 (96 RXN) | O14: =IF(COUNTIF($M$4:$M$7, TRUE) = 0, IF(K14<>0, K14, ""), IF(ISNUMBER(SEARCH(INDEX($N$4:$N$7, MATCH(TRUE, $M$4:$M$7, 0)), K14)), K14, "")) | P14: {=IFERROR(INDEX($O$3:$O$24, SMALL(IF(($O$3:$O$24<>0)*($O$3:$O$24<>""), ROW($O$3:$O$24)-ROW($O$3)+1), ROW(A11))), "")} | S14: =IF(COUNTIF($Q$4:$Q$7, TRUE) = 0, IF(L14<>0, L14, ""), IF(ISNUMBER(SEARCH(INDEX($R$4:$R$7, MATCH(TRUE, $Q$4:$Q$7, 0)), L14)), L14, "")) | T14: {=IFERROR(INDEX($S$3:$S$24, SMALL(IF(($S$3:$S$24<>0)*($S$3:$S$24<>""), ROW($S$3:$S$24)-ROW($S$3)+1), ROW(A11))),"")}
B15: =$D$154 -> Thermofisher Ion AmpliSeq Library Plus Kit with 24 rxns | C15: =$D$139 -> ONT Rapid PCR Barcoding Kit 24 V14 protocol | D15: =$D$131 -> ONT Rapid Barcoding Kit 24 V14 | E15: =$D$181 -> MGIEasy Fast FS DNA Library Prep Set V2.0 (96 RXN) | F15: =$D$181 -> MGIEasy Fast FS DNA Library Prep Set V2.0 (96 RXN) | O15: =IF(COUNTIF($M$4:$M$7, TRUE) = 0, IF(K15<>0, K15, ""), IF(ISNUMBER(SEARCH(INDEX($N$4:$N$7, MATCH(TRUE, $M$4:$M$7, 0)), K15)), K15, "")) | P15: {=IFERROR(INDEX($O$3:$O$24, SMALL(IF(($O$3:$O$24<>0)*($O$3:$O$24<>""), ROW($O$3:$O$24)-ROW($O$3)+1), ROW(A12))), "")} | S15: =IF(COUNTIF($Q$4:$Q$7, TRUE) = 0, IF(L15<>0, L15, ""), IF(ISNUMBER(SEARCH(INDEX($R$4:$R$7, MATCH(TRUE, $Q$4:$Q$7, 0)), L15)), L15, "")) | T15: {=IFERROR(INDEX($S$3:$S$24, SMALL(IF(($S$3:$S$24<>0)*($S$3:$S$24<>""), ROW($S$3:$S$24)-ROW($S$3)+1), ROW(A12))),"")}
B16: =$D$181 -> MGIEasy Fast FS DNA Library Prep Set V2.0 (96 RXN) | C16: =$D$154 -> Thermofisher Ion AmpliSeq Library Plus Kit with 24 rxns | D16: =$D$135 -> ONT Rapid Barcoding Kit 96 V14 | O16: =IF(COUNTIF($M$4:$M$7, TRUE) = 0, IF(K16<>0, K16, ""), IF(ISNUMBER(SEARCH(INDEX($N$4:$N$7, MATCH(TRUE, $M$4:$M$7, 0)), K16)), K16, "")) | P16: {=IFERROR(INDEX($O$3:$O$24, SMALL(IF(($O$3:$O$24<>0)*($O$3:$O$24<>""), ROW($O$3:$O$24)-ROW($O$3)+1), ROW(A13))), "")} | S16: =IF(COUNTIF($Q$4:$Q$7, TRUE) = 0, IF(L16<>0, L16, ""), IF(ISNUMBER(SEARCH(INDEX($R$4:$R$7, MATCH(TRUE, $Q$4:$Q$7, 0)), L16)), L16, "")) | T16: {=IFERROR(INDEX($S$3:$S$24, SMALL(IF(($S$3:$S$24<>0)*($S$3:$S$24<>""), ROW($S$3:$S$24)-ROW($S$3)+1), ROW(A13))),"")}
C17: =$D$171 -> MGIEasy Respiratory Microorganisms Genome Library Preparation Set (16 RXN) | D17: =$D$139 -> ONT Rapid PCR Barcoding Kit 24 V14 protocol | O17: =IF(COUNTIF($M$4:$M$7, TRUE) = 0, IF(K17<>0, K17, ""), IF(ISNUMBER(SEARCH(INDEX($N$4:$N$7, MATCH(TRUE, $M$4:$M$7, 0)), K17)), K17, "")) | P17: {=IFERROR(INDEX($O$3:$O$24, SMALL(IF(($O$3:$O$24<>0)*($O$3:$O$24<>""), ROW($O$3:$O$24)-ROW($O$3)+1), ROW(A14))), "")} | S17: =IF(COUNTIF($Q$4:$Q$7, TRUE) = 0, IF(L17<>0, L17, ""), IF(ISNUMBER(SEARCH(INDEX($R$4:$R$7, MATCH(TRUE, $Q$4:$Q$7, 0)), L17)), L17, "")) | T17: {=IFERROR(INDEX($S$3:$S$24, SMALL(IF(($S$3:$S$24<>0)*($S$3:$S$24<>""), ROW($S$3:$S$24)-ROW($S$3)+1), ROW(A14))),"")}
C18: =$D$181 -> MGIEasy Fast FS DNA Library Prep Set V2.0 (96 RXN) | D18: =$D$154 -> Thermofisher Ion AmpliSeq Library Plus Kit with 24 rxns | O18: =IF(COUNTIF($M$4:$M$7, TRUE) = 0, IF(K18<>0, K18, ""), IF(ISNUMBER(SEARCH(INDEX($N$4:$N$7, MATCH(TRUE, $M$4:$M$7, 0)), K18)), K18, "")) | P18: {=IFERROR(INDEX($O$3:$O$24, SMALL(IF(($O$3:$O$24<>0)*($O$3:$O$24<>""), ROW($O$3:$O$24)-ROW($O$3)+1), ROW(A15))), "")} | S18: =IF(COUNTIF($Q$4:$Q$7, TRUE) = 0, IF(L18<>0, L18, ""), IF(ISNUMBER(SEARCH(INDEX($R$4:$R$7, MATCH(TRUE, $Q$4:$Q$7, 0)), L18)), L18, "")) | T18: {=IFERROR(INDEX($S$3:$S$24, SMALL(IF(($S$3:$S$24<>0)*($S$3:$S$24<>""), ROW($S$3:$S$24)-ROW($S$3)+1), ROW(A15))),"")}
D19: =$D$181 -> MGIEasy Fast FS DNA Library Prep Set V2.0 (96 RXN) | O19: =IF(COUNTIF($M$4:$M$7, TRUE) = 0, IF(K19<>0, K19, ""), IF(ISNUMBER(SEARCH(INDEX($N$4:$N$7, MATCH(TRUE, $M$4:$M$7, 0)), K19)), K19, "")) | P19: {=IFERROR(INDEX($O$3:$O$24, SMALL(IF(($O$3:$O$24<>0)*($O$3:$O$24<>""), ROW($O$3:$O$24)-ROW($O$3)+1), ROW(A16))), "")} | S19: =IF(COUNTIF($Q$4:$Q$7, TRUE) = 0, IF(L19<>0, L19, ""), IF(ISNUMBER(SEARCH(INDEX($R$4:$R$7, MATCH(TRUE, $Q$4:$Q$7, 0)), L19)), L19, "")) | T19: {=IFERROR(INDEX($S$3:$S$24, SMALL(IF(($S$3:$S$24<>0)*($S$3:$S$24<>""), ROW($S$3:$S$24)-ROW($S$3)+1), ROW(A16))),"")}
D20: =$D$185 -> MGI ATOPlex RNA Library Prep Set (96 RXN) | O20: =IF(COUNTIF($M$4:$M$7, TRUE) = 0, IF(K20<>0, K20, ""), IF(ISNUMBER(SEARCH(INDEX($N$4:$N$7, MATCH(TRUE, $M$4:$M$7, 0)), K20)), K20, "")) | P20: {=IFERROR(INDEX($O$3:$O$24, SMALL(IF(($O$3:$O$24<>0)*($O$3:$O$24<>""), ROW($O$3:$O$24)-ROW($O$3)+1), ROW(A17))), "")} | S20: =IF(COUNTIF($Q$4:$Q$7, TRUE) = 0, IF(L20<>0, L20, ""), IF(ISNUMBER(SEARCH(INDEX($R$4:$R$7, MATCH(TRUE, $Q$4:$Q$7, 0)), L20)), L20, "")) | T20: {=IFERROR(INDEX($S$3:$S$24, SMALL(IF(($S$3:$S$24<>0)*($S$3:$S$24<>""), ROW($S$3:$S$24)-ROW($S$3)+1), ROW(A17))),"")}
D21: =$D$189 -> MGI ATOPlex RNA Multiplex PCR-based Library Preparation Set V3.1 (96 RXN) | O21: =IF(COUNTIF($M$4:$M$7, TRUE) = 0, IF(K21<>0, K21, ""), IF(ISNUMBER(SEARCH(INDEX($N$4:$N$7, MATCH(TRUE, $M$4:$M$7, 0)), K21)), K21, "")) | P21: {=IFERROR(INDEX($O$3:$O$24, SMALL(IF(($O$3:$O$24<>0)*($O$3:$O$24<>""), ROW($O$3:$O$24)-ROW($O$3)+1), ROW(A18))), "")} | S21: =IF(COUNTIF($Q$4:$Q$7, TRUE) = 0, IF(L21<>0, L21, ""), IF(ISNUMBER(SEARCH(INDEX($R$4:$R$7, MATCH(TRUE, $Q$4:$Q$7, 0)), L21)), L21, "")) | T21: {=IFERROR(INDEX($S$3:$S$24, SMALL(IF(($S$3:$S$24<>0)*($S$3:$S$24<>""), ROW($S$3:$S$24)-ROW($S$3)+1), ROW(A18))),"")}
O22: =IF(COUNTIF($M$4:$M$7, TRUE) = 0, IF(K22<>0, K22, ""), IF(ISNUMBER(SEARCH(INDEX($N$4:$N$7, MATCH(TRUE, $M$4:$M$7, 0)), K22)), K22, "")) | P22: {=IFERROR(INDEX($O$3:$O$24, SMALL(IF(($O$3:$O$24<>0)*($O$3:$O$24<>""), ROW($O$3:$O$24)-ROW($O$3)+1), ROW(A19))), "")} | S22: =IF(COUNTIF($Q$4:$Q$7, TRUE) = 0, IF(L22<>0, L22, ""), IF(ISNUMBER(SEARCH(INDEX($R$4:$R$7, MATCH(TRUE, $Q$4:$Q$7, 0)), L22)), L22, "")) | T22: {=IFERROR(INDEX($S$3:$S$24, SMALL(IF(($S$3:$S$24<>0)*($S$3:$S$24<>""), ROW($S$3:$S$24)-ROW($S$3)+1), ROW(A19))),"")}
O23: =IF(COUNTIF($M$4:$M$7, TRUE) = 0, IF(K23<>0, K23, ""), IF(ISNUMBER(SEARCH(INDEX($N$4:$N$7, MATCH(TRUE, $M$4:$M$7, 0)), K23)), K23, "")) | P23: {=IFERROR(INDEX($O$3:$O$24, SMALL(IF(($O$3:$O$24<>0)*($O$3:$O$24<>""), ROW($O$3:$O$24)-ROW($O$3)+1), ROW(A20))), "")} | S23: =IF(COUNTIF($Q$4:$Q$7, TRUE) = 0, IF(L23<>0, L23, ""), IF(ISNUMBER(SEARCH(INDEX($R$4:$R$7, MATCH(TRUE, $Q$4:$Q$7, 0)), L23)), L23, "")) | T23: {=IFERROR(INDEX($S$3:$S$24, SMALL(IF(($S$3:$S$24<>0)*($S$3:$S$24<>""), ROW($S$3:$S$24)-ROW($S$3)+1), ROW(A20))),"")}
O24: =IF(COUNTIF($M$4:$M$7, TRUE) = 0, IF(K24<>0, K24, ""), IF(ISNUMBER(SEARCH(INDEX($N$4:$N$7, MATCH(TRUE, $M$4:$M$7, 0)), K24)), K24, "")) | P24: {=IFERROR(INDEX($O$3:$O$24, SMALL(IF(($O$3:$O$24<>0)*($O$3:$O$24<>""), ROW($O$3:$O$24)-ROW($O$3)+1), ROW(A21))), "")} | S24: =IF(COUNTIF($Q$4:$Q$7, TRUE) = 0, IF(L24<>0, L24, ""), IF(ISNUMBER(SEARCH(INDEX($R$4:$R$7, MATCH(TRUE, $Q$4:$Q$7, 0)), L24)), L24, "")) | T24: {=IFERROR(INDEX($S$3:$S$24, SMALL(IF(($S$3:$S$24<>0)*($S$3:$S$24<>""), ROW($S$3:$S$24)-ROW($S$3)+1), ROW(A21))),"")}
O25: =IF(J4=G4,G10,"") | P25: {=IFERROR(INDEX($O$3:$O$24, SMALL(IF(($O$3:$O$24<>0)*($O$3:$O$24<>""), ROW($O$3:$O$24)-ROW($O$3)+1), ROW(A22))), "")} | S25: =IF(J9=G4,G10,"") | T25: {=IFERROR(INDEX($S$3:$S$24, SMALL(IF(($S$3:$S$24<>0)*($S$3:$S$24<>""), ROW($S$3:$S$24)-ROW($S$3)+1), ROW(A22))),"")}
P26: {=IFERROR(INDEX($O$3:$O$24, SMALL(IF(($O$3:$O$24<>0)*($O$3:$O$24<>""), ROW($O$3:$O$24)-ROW($O$3)+1), ROW(A23))), "")} | T26: {=IFERROR(INDEX($S$3:$S$24, SMALL(IF(($S$3:$S$24<>0)*($S$3:$S$24<>""), ROW($S$3:$S$24)-ROW($S$3)+1), ROW(A23))),"")}
P27: {=IFERROR(INDEX($O$3:$O$24, SMALL(IF(($O$3:$O$24<>0)*($O$3:$O$24<>""), ROW($O$3:$O$24)-ROW($O$3)+1), ROW(A24))), "")} | T27: {=IFERROR(INDEX($S$3:$S$24, SMALL(IF(($S$3:$S$24<>0)*($S$3:$S$24<>""), ROW($S$3:$S$24)-ROW($S$3)+1), ROW(A24))),"")}
H48: EQUATION for #packs (including dead volume) = (1+%deadVolume)X(#samples+#controls) / (pack size)
H49: Sequencer 1 | I49: sequencer 2
G50: Number of controls per year --> | H50: ='Data entry'!$C$27*'Data entry'!$C$28 -> 106 | I50: ='Data entry'!$F$27*'Data entry'!$F$28 -> 42 | J50: using all available indices | K50: per index set
A51: A question on capture option from Toni: "My concern is a bacterial sample would require a higher read count. Do we just double the read count for kits that cover DNA/RNA?" Answer: this can be discussed in the next meeting | B51: Developer Notes | C51: Pathogen type | D51: Library preparation kit | E51: Kit + additional reagents to complete the kit | F51: Platform Compatability | G51: Pack size | H51: #Packs (for all samples) -Seq1 | I51: #Packs (for all samples) - Seq2 | J51: Barcoding limit per run | K51: Unit Price | L51: Enrichment included in kit (yes/no) | M51: catalog number
A52: allows you to do 96 individual samples or pool up to 96 samples on the same flowcell | B52: price is set for use of one index box set (ex. Index Set 1); set 3&4 omitted since are RUO | C52: SARS-CoV-2 | D52: Illumina: COVIDSeq Assay (96 Samples) | E52: Illumina COVIDSeq Assay (96 samples) index 1/index 2 | F52: iSeq 100(8), MiniSeq(48), MiSeq(48), NextSeq 1000/2000 (96) | G52: 96 | H52: =IF(Equipment!$I$42>=1,ROUNDUP(((1+'Data entry'!$C$33)*((1/$G52)*(('Data entry'!$C$16+'Data entry'!$C$16*'Data entry'!$C$23)+$H$50))),0),ROUNDUP((1/$G52)*(('Data entry'!$C$16+'Data entry'!$C$16*'Data entry'!$C$23)+$H$50),0)) -> 7 | I52: =IF(Equipment!$I$42>=1,ROUNDUP(((1+'Data entry'!$C$33)*((1/$G52)*(('Data entry'!$F$16+'Data entry'!$F$16*'Data entry'!$F$23)+$I$50))),0),ROUNDUP((1/$G52)*(('Data entry'!$F$16+'Data entry'!$F$16*'Data entry'!$F$23)+$I$50),0)) -> 4 | J52: 96 | K52: =3322 -> 3322 | L52: Yes | M52: 20049393; 20051772
A53: is this the PhiX Control v3 or something else? Normally the lab would run a EQA at very high Ct rather than but the control | B53: Calculation for number of packs for all samples is affected by the number of runs vs. number of samples | E53: COVIDSeq Positive Control | G53: 96 | H53: =IF(Equipment!$I$42>=1,ROUNDUP((1+'Data entry'!$C$33)*(1/G53)*'Data entry'!$C$28,0),ROUNDUP((1/$G53)*'Data entry'!$C$28,0)) -> 1 | I53: =IF(Equipment!$I$42>=1,ROUNDUP((1+'Data entry'!$C$33)*(1/$G53)*'Data entry'!$F$28,0),ROUNDUP((1/$G53)*'Data entry'!$F$28,0)) -> 1 | K53: 850 | M53: 20051775
A54: Target-specific primers included
B55: Beads included in this kit | C55: SARS-CoV-2, RSV, Influenza A, Influenza B | D55: Illumina DNA Prep, (M) Tagmentation (96 Samples, IPB) | E55: Illumina DNA Prep, (M) Tagmentation (96 Samples, IPB) | F55: All Illumina (up to 384) | G55: 96 | H55: =IF(Equipment!$I$42>=1,ROUNDUP(((1+'Data entry'!$C$33)*((1/G55)*(('Data entry'!$C$16+'Data entry'!$C$16*'Data entry'!$C$23)+$H$50))),0),ROUNDUP((1/G55)*(('Data entry'!$C$16+'Data entry'!$C$16*'Data entry'!$C$23)+$H$50),0)) -> 7 | I55: =IF(Equipment!$I$42>=1,ROUNDUP(((1+'Data entry'!$C$33)*((1/$G55)*(('Data entry'!$F$16+'Data entry'!$F$16*'Data entry'!$F$23)+$I$50))),0),ROUNDUP((1/$G55)*(('Data entry'!$F$16+'Data entry'!$F$16*'Data entry'!$F$23)+$I$50),0)) -> 4 | J55: 384 | K55: 4153 | L55: No | M55: 20060059
B56: price is set for use of one index box set (ex. Index Set A) | E56: Illumina DNA/RNA Unique Dual Indexes Sets A, B, C, D, Tagmentation (96 Indexes, 96 Samples/set) | G56: 96 | H56: =IF(Equipment!$I$42>=1,ROUNDUP(((1+'Data entry'!$C$33)*((1/G56)*(('Data entry'!$C$16+'Data entry'!$C$16*'Data entry'!$C$23)+$H$50))),0),ROUNDUP((1/G56)*(('Data entry'!$C$16+'Data entry'!$C$16*'Data entry'!$C$23)+$H$50),0)) -> 7 | I56: =IF(Equipment!$I$42>=1,ROUNDUP(((1+'Data entry'!$C$33)*((1/$G56)*(('Data entry'!$F$16+'Data entry'!$F$16*'Data entry'!$F$23)+$I$50))),0),ROUNDUP((1/$G56)*(('Data entry'!$F$16+'Data entry'!$F$16*'Data entry'!$F$23)+$I$50),0)) -> 4 | J56: 384 | K56: 408 | M56: 20091654, 20091656, 20091658, 20091660
B57: we assume it as LunaScript® RT SuperMix (M3010L) - 100 reactions/pack, 460$ per pack (Beatrix) | E57: RT-PCR reagents | G57: 100 | H57: =IF(Equipment!$I$42>=1,ROUNDUP(((1+'Data entry'!$C$33)*((1/G57)*(('Data entry'!$C$16+'Data entry'!$C$16*'Data entry'!$C$23)+$H$50))),0),ROUNDUP((1/G57)*(('Data entry'!$C$16+'Data entry'!$C$16*'Data entry'!$C$23)+$H$50),0)) -> 7 | I57: =IF(Equipment!$I$42>=1,ROUNDUP(((1+'Data entry'!$C$33)*((1/$G57)*(('Data entry'!$F$16+'Data entry'!$F$16*'Data entry'!$F$23)+$I$50))),0),ROUNDUP((1/$G57)*(('Data entry'!$F$16+'Data entry'!$F$16*'Data entry'!$F$23)+$I$50),0)) -> 4 | K57: 460 | M57: M3010L
B58: We assume Target specific primers - 1000 samples/pack; 65$ per pack (Beatrix) | E58: Target specific primers | G58: 1000 | H58: =IF(Equipment!$I$42>=1,ROUNDUP(((1+'Data entry'!$C$33)*((1/G58)*(('Data entry'!$C$16+'Data entry'!$C$16*'Data entry'!$C$23)+$H$50))),0),ROUNDUP((1/G58)*(('Data entry'!$C$16+'Data entry'!$C$16*'Data entry'!$C$23)+$H$50),0)) -> 1 | I58: =IF(Equipment!$I$42>=1,ROUNDUP(((1+'Data entry'!$C$33)*((1/$G58)*(('Data entry'!$F$16+'Data entry'!$F$16*'Data entry'!$F$23)+$I$50))),0),ROUNDUP((1/$G58)*(('Data entry'!$F$16+'Data entry'!$F$16*'Data entry'!$F$23)+$I$50),0)) -> 1 | K58: 65
C59: SAR-CoV-2 | D59: Illumina: COVIDSeq Test (RUO Version) (3072 Samples) | E59: Illumina COVIDSeq Test (RUO version) (3072 Samples) | F59: All Illumina (up to 384) | G59: 3072 | H59: =IF(Equipment!$I$42>=1,ROUNDUP(((1+'Data entry'!$C$33)*((1/G59)*(('Data entry'!$C$16+'Data entry'!$C$16*'Data entry'!$C$23)+$H$50))),0),ROUNDUP((1/G59)*(('Data entry'!$C$16+'Data entry'!$C$16*'Data entry'!$C$23)+$H$50),0)) -> 1 | I59: =IF(Equipment!$I$42>=1,ROUNDUP(((1+'Data entry'!$C$33)*((1/$G59)*(('Data entry'!$F$16+'Data entry'!$F$16*'Data entry'!$F$23)+$I$50))),0),ROUNDUP((1/$G59)*(('Data entry'!$F$16+'Data entry'!$F$16*'Data entry'!$F$23)+$I$50),0)) -> 1 | J59: 384 | K59: 35271.6 | L59: Yes | M59: 20043675
E60: IDT for Illumina PCR Unique Dual Indexes Sets 1-4, 384 samples | G60: 384 | H60: =IF(Equipment!$I$42>=1,ROUNDUP(((1+'Data entry'!$C$33)*((1/G60)*(('Data entry'!$C$16+'Data entry'!$C$16*'Data entry'!$C$23)+$H$50))),0),ROUNDUP((1/G60)*(('Data entry'!$C$16+'Data entry'!$C$16*'Data entry'!$C$23)+$H$50),0)) -> 2 | I60: =IF(Equipment!$I$42>=1,ROUNDUP(((1+'Data entry'!$C$33)*((1/$G60)*(('Data entry'!$F$16+'Data entry'!$F$16*'Data entry'!$F$23)+$I$50))),0),ROUNDUP((1/$G60)*(('Data entry'!$F$16+'Data entry'!$F$16*'Data entry'!$F$23)+$I$50),0)) -> 1 | J60: =96*4 -> 384 | K60: 1415 | M60: 20091654, 20091656, 20091658, 20091660
A61: Target-specific primers included
A62: The kit is based on the COVIDseq workflow. Contains: Universal Flu A/B primer pool, RT enzymes and PCR amp reagents + library prep reagents. | B62: kit includes primers, RT-PCR reagents, library prep reagents and indexes sufficient for 48 samples | C62: Influenza A and Influenza B | D62: Illumina Microbial Amplicon Prep—Influenza A/B | E62: Illumina Microbial Amplicon Prep—Influenza A/B (48 samples) | F62: All Illumina (up to 48 samples) | G62: 48 | H62: =IF(Equipment!$I$42>=1,ROUNDUP(((1+'Data entry'!$C$33)*((1/G62)*(('Data entry'!$C$16+'Data entry'!$C$16*'Data entry'!$C$23)+$H$50))),0),ROUNDUP((1/G62)*(('Data entry'!$C$16+'Data entry'!$C$16*'Data entry'!$C$23)+$H$50),0)) -> 14 | I62: =IF(Equipment!$I$42>=1,ROUNDUP(((1+'Data entry'!$C$33)*((1/$G62)*(('Data entry'!$F$16+'Data entry'!$F$16*'Data entry'!$F$23)+$I$50))),0),ROUNDUP((1/$G62)*(('Data entry'!$F$16+'Data entry'!$F$16*'Data entry'!$F$23)+$I$50),0)) -> 8 | J62: 48 | K62: 1468.8 | L62: Yes | M62: 20106305
A63: the kit includes reagents necessary for cDNA conversion, amplification, and library preparation | B63: 48-sample amplicon kit containing cDNA conversion, library prep, and indexes. Primers are not included | C63: SARS-CoV-2, RSV, Influenza A, Influenza B | D63: Illumina Microbial Amplicon Prep | E63: Illumina Microbial Amplicon Prep (48 samples) | F63: All Illumina (up to 48 samples) | G63: 48 | H63: =IF(Equipment!$I$42>=1,ROUNDUP(((1+'Data entry'!$C$33)*((1/G63)*(('Data entry'!$C$16+'Data entry'!$C$16*'Data entry'!$C$23)+$H$50))),0),ROUNDUP((1/G63)*(('Data entry'!$C$16+'Data entry'!$C$16*'Data entry'!$C$23)+$H$50),0)) -> 14 | I63: =IF(Equipment!$I$42>=1,ROUNDUP(((1+'Data entry'!$C$33)*((1/$G63)*(('Data entry'!$F$16+'Data entry'!$F$16*'Data entry'!$F$23)+$I$50))),0),ROUNDUP((1/$G63)*(('Data entry'!$F$16+'Data entry'!$F$16*'Data entry'!$F$23)+$I$50),0)) -> 8 | J63: 48 | K63: 1428 | L63: Yes | M63: 20097857
B64: we assume it as LunaScript® RT SuperMix (M3010L) - 100 reactions/pack, 460$ per pack (Beatrix) | E64: RT-PCR reagents | G64: 100 | H64: =IF(Equipment!$I$42>=1,ROUNDUP(((1+'Data entry'!$C$33)*((1/G64)*(('Data entry'!$C$16+'Data entry'!$C$16*'Data entry'!$C$23)+$H$50))),0),ROUNDUP((1/G64)*(('Data entry'!$C$16+'Data entry'!$C$16*'Data entry'!$C$23)+$H$50),0)) -> 7 | I64: =IF(Equipment!$I$42>=1,ROUNDUP(((1+'Data entry'!$C$33)*((1/$G64)*(('Data entry'!$F$16+'Data entry'!$F$16*'Data entry'!$F$23)+$I$50))),0),ROUNDUP((1/$G64)*(('Data entry'!$F$16+'Data entry'!$F$16*'Data entry'!$F$23)+$I$50),0)) -> 4 | K64: 460 | M64: M3010L
B65: We assume Target specific primers - 1000 samples/pack; 65$ per pack (Beatrix) | E65: Target specific primers | G65: 1000 | H65: =IF(Equipment!$I$42>=1,ROUNDUP(((1+'Data entry'!$C$33)*((1/G65)*(('Data entry'!$C$16+'Data entry'!$C$16*'Data entry'!$C$23)+$H$50))),0),ROUNDUP((1/G65)*(('Data entry'!$C$16+'Data entry'!$C$16*'Data entry'!$C$23)+$H$50),0)) -> 1 | I65: =IF(Equipment!$I$42>=1,ROUNDUP(((1+'Data entry'!$C$33)*((1/$G65)*(('Data entry'!$F$16+'Data entry'!$F$16*'Data entry'!$F$23)+$I$50))),0),ROUNDUP((1/$G65)*(('Data entry'!$F$16+'Data entry'!$F$16*'Data entry'!$F$23)+$I$50),0)) -> 1 | K65: 65
A66: Kits contain the Respiratory Virus Oligo Panel (RVOP) v2, Illumina RNA Prep with Enrichment, and one of four available unique dual indexing plates. - minimum 2M read / sample required | B66: omplete hybridization-based enrichment kit including Illumina RNA Prep with Enrichment library preparation and hybridization reagents, Respiratory Virus Oligo Panel v2, and IDT® for Illumina® DNA/RNA UD Indexes Set A. Each kit provides enough reagents for 96 samples in 32 hybridization reactions with 3 libraries per hybridization reaction | C66: 40 common respiratory viruses | D66: Illumina Respiratory Virus Enrichment Kit | E66: Illumina Respiratory Virus Enrichment Kit Sets A/B/C/D, 96 samples/set | F66: MiniSeq, MiSeq System, NextSeq 550, NextSeq 2000 (up to 384 samples) | G66: 96 | H66: =IF(Equipment!$I$42>=1,ROUNDUP(((1+'Data entry'!$C$33)*((1/G66)*(('Data entry'!$C$16+'Data entry'!$C$16*'Data entry'!$C$23)+$H$50))),0),ROUNDUP((1/G66)*(('Data entry'!$C$16+'Data entry'!$C$16*'Data entry'!$C$23)+$H$50),0)) -> 7 | I66: =IF(Equipment!$I$42>=1,ROUNDUP(((1+'Data entry'!$C$33)*((1/$G66)*(('Data entry'!$F$16+'Data entry'!$F$16*'Data entry'!$F$23)+$I$50))),0),ROUNDUP((1/$G66)*(('Data entry'!$F$16+'Data entry'!$F$16*'Data entry'!$F$23)+$I$50),0)) -> 4 | J66: 384 | K66: =8812.8 -> 8812.8 | L66: Yes | M66: 20100469, 20100470, 20100471, 20100472
A67: this is very similar to DNA prep and may be discontinued in teh future (the costing should be the same) | C67: SARS-CoV-2, RSV, Influenza A, Influenza B | D67: Nextera XT DNA Library Preparation Kit for Illumina | E67: Nextera XT DNA Library Preparation Kit (96 samples) | F67: All Illumina except NovaSeq (up to 384 samples) | G67: 96 | H67: =IF(Equipment!$I$42>=1,ROUNDUP(((1+'Data entry'!$C$33)*((1/G67)*(('Data entry'!$C$16+'Data entry'!$C$16*'Data entry'!$C$23)+$H$50))),0),ROUNDUP((1/G67)*(('Data entry'!$C$16+'Data entry'!$C$16*'Data entry'!$C$23)+$H$50),0)) -> 7 | I67: =IF(Equipment!$I$42>=1,ROUNDUP(((1+'Data entry'!$C$33)*((1/$G67)*(('Data entry'!$F$16+'Data entry'!$F$16*'Data entry'!$F$23)+$I$50))),0),ROUNDUP((1/$G67)*(('Data entry'!$F$16+'Data entry'!$F$16*'Data entry'!$F$23)+$I$50),0)) -> 4 | J67: 384 | K67: 3435 | L67: No | M67: FC-131-1096
B68: 100 ul per sample , as per NEB website | E68: Illumina DNA/RNA Unique Dual Indexes Sets A-D, 96 Samples/set | G68: 96 | H68: =IF(Equipment!$I$42>=1,ROUNDUP(((1+'Data entry'!$C$33)*((1/G68)*(('Data entry'!$C$16+'Data entry'!$C$16*'Data entry'!$C$23)+$H$50))),0),ROUNDUP((1/G68)*(('Data entry'!$C$16+'Data entry'!$C$16*'Data entry'!$C$23)+$H$50),0)) -> 7 | I68: =IF(Equipment!$I$42>=1,ROUNDUP(((1+'Data entry'!$C$33)*((1/$G68)*(('Data entry'!$F$16+'Data entry'!$F$16*'Data entry'!$F$23)+$I$50))),0),ROUNDUP((1/$G68)*(('Data entry'!$F$16+'Data entry'!$F$16*'Data entry'!$F$23)+$I$50),0)) -> 4 | J68: 384 | K68: 408 | M68: 20091654, 20091656, 20091658, 20091660
B69: we assume it as LunaScript® RT SuperMix (M3010L) - 100 reactions/pack, 460$ per pack (Beatrix) | E69: RT-PCR reagents | G69: 100 | H69: =IF(Equipment!$I$42>=1,ROUNDUP(((1+'Data entry'!$C$33)*((1/G69)*(('Data entry'!$C$16+'Data entry'!$C$16*'Data entry'!$C$23)+$H$50))),0),ROUNDUP((1/G69)*(('Data entry'!$C$16+'Data entry'!$C$16*'Data entry'!$C$23)+$H$50),0)) -> 7 | I69: =IF(Equipment!$I$42>=1,ROUNDUP(((1+'Data entry'!$C$33)*((1/$G69)*(('Data entry'!$F$16+'Data entry'!$F$16*'Data entry'!$F$23)+$I$50))),0),ROUNDUP((1/$G69)*(('Data entry'!$F$16+'Data entry'!$F$16*'Data entry'!$F$23)+$I$50),0)) -> 4 | K69: 460 | M69: M3010L
B70: We assume Target specific primers - 1000 samples/pack; 65$ per pack (Beatrix) | E70: Target specific primers | G70: 1000 | H70: =IF(Equipment!$I$42>=1,ROUNDUP(((1+'Data entry'!$C$33)*((1/G70)*(('Data entry'!$C$16+'Data entry'!$C$16*'Data entry'!$C$23)+$H$50))),0),ROUNDUP((1/G70)*(('Data entry'!$C$16+'Data entry'!$C$16*'Data entry'!$C$23)+$H$50),0)) -> 1 | I70: =IF(Equipment!$I$42>=1,ROUNDUP(((1+'Data entry'!$C$33)*((1/$G70)*(('Data entry'!$F$16+'Data entry'!$F$16*'Data entry'!$F$23)+$I$50))),0),ROUNDUP((1/$G70)*(('Data entry'!$F$16+'Data entry'!$F$16*'Data entry'!$F$23)+$I$50),0)) -> 1 | K70: 65
A71: 2M paired-end reads / sample required. (manually change the max # samples in the formula) | B71: primers included; assumes purchase of only 1 panel set | C71: >280 respiratory pathogens included and >2000 AMR markers | D71: Illumina: Respiratory Pathogen ID/AMR Enrichment Panel Kit | E71: Respiratory Pathogen ID/AMR Enrichment Kit Set A (RUO) - up to 4 panels of 96 samples/set each (A/B/C/D) | F71: MiniSeq, MiSeq, NextSeq 550 (up to 384 samples) | G71: 96 | H71: =IF(Equipment!$I$42>=1,ROUNDUP(((1+'Data entry'!$C$33)*((1/G71)*(('Data entry'!$C$16+'Data entry'!$C$16*'Data entry'!$C$23)+$H$50))),0),ROUNDUP((1/G71)*(('Data entry'!$C$16+'Data entry'!$C$16*'Data entry'!$C$23)+$H$50),0)) -> 7 | I71: =IF(Equipment!$I$42>=1,ROUNDUP(((1+'Data entry'!$C$33)*((1/$G71)*(('Data entry'!$F$16+'Data entry'!$F$16*'Data entry'!$F$23)+$I$50))),0),ROUNDUP((1/$G71)*(('Data entry'!$F$16+'Data entry'!$F$16*'Data entry'!$F$23)+$I$50),0)) -> 4 | J71: 384 | K71: 13579 | L71: Yes | M71: 20047050, 20046969, 20047051, 20047052
E72: AMPure XP beads 60ml | G72: 200 | H72: =IF(Equipment!$I$42>=1,ROUNDUP(((1+'Data entry'!$C$33)*((1/G72)*(('Data entry'!$C$16+'Data entry'!$C$16*'Data entry'!$C$23)+$H$50))),0),ROUNDUP((1/G72)*(('Data entry'!$C$16+'Data entry'!$C$16*'Data entry'!$C$23)+$H$50),0)) -> 4 | I72: =IF(Equipment!$I$42>=1,ROUNDUP(((1+'Data entry'!$C$33)*((1/$G72)*(('Data entry'!$F$16+'Data entry'!$F$16*'Data entry'!$F$23)+$I$50))),0),ROUNDUP((1/$G72)*(('Data entry'!$F$16+'Data entry'!$F$16*'Data entry'!$F$23)+$I$50),0)) -> 2 | K72: 2031 | M72: A63881
A73: The complete kits include everything needed for library prep and enrichment, including purification beads and index adapters. Minimum of 2M paired-end reads per sample with a read length of 150 bp. For more complex samples (eg: wastewater) a minimum of 8M paired-end reads per sample | B73: includes purification beads and index adapters | C73: >200 DNA/RNA VIRUS | D73: Illumina Viral Surveillance Panel v2 Kit | E73: Illumina Viral Surveillance Panel v2 Kit, Sets A/B/C/D, 96 samples/set | F73: All Illumina except NovaSeq (up to 384 samples) | G73: 96 | H73: =IF(Equipment!$I$42>=1,ROUNDUP(((1+'Data entry'!$C$33)*((1/G73)*(('Data entry'!$C$16+'Data entry'!$C$16*'Data entry'!$C$23)+$H$50))),0),ROUNDUP((1/G73)*(('Data entry'!$C$16+'Data entry'!$C$16*'Data entry'!$C$23)+$H$50),0)) -> 7 | I73: =IF(Equipment!$I$42>=1,ROUNDUP(((1+'Data entry'!$C$33)*((1/$G73)*(('Data entry'!$F$16+'Data entry'!$F$16*'Data entry'!$F$23)+$I$50))),0),ROUNDUP((1/$G73)*(('Data entry'!$F$16+'Data entry'!$F$16*'Data entry'!$F$23)+$I$50),0)) -> 4 | J73: 384 | K73: 13350 | L73: Yes | M73: 20108081, 20108082, 20108083, 20108084
A74: NEBNext Ultra II DNA Library Prep Kit for Illumina with sample purification beads (NEB #E7103) or NEBNext Ultra II DNA Library Prep Kit for Illumina then purchase AMPure® XP Bead | B74: if RNA - requires user to select reverse transcription included in R/C worksheet | C74: SARS-CoV-2, RSV, Influenza A, Influenza B | D74: NEBNext Ultra II DNA Library Prep with Sample Purification Beads for Illumina | E74: NEBNext Ultra II DNA Library Prep with Sample Purification Beads for Illumina (96 samples) | F74: All Illumina (up to 96 samples) | G74: 96 | H74: =IF(Equipment!$I$42>=1,ROUNDUP(((1+'Data entry'!$C$33)*((1/G74)*(('Data entry'!$C$16+'Data entry'!$C$16*'Data entry'!$C$23)+$H$50))),0),ROUNDUP((1/G74)*(('Data entry'!$C$16+'Data entry'!$C$16*'Data entry'!$C$23)+$H$50),0)) -> 7 | I74: =IF(Equipment!$I$42>=1,ROUNDUP(((1+'Data entry'!$C$33)*((1/$G74)*(('Data entry'!$F$16+'Data entry'!$F$16*'Data entry'!$F$23)+$I$50))),0),ROUNDUP((1/$G74)*(('Data entry'!$F$16+'Data entry'!$F$16*'Data entry'!$F$23)+$I$50),0)) -> 4 | J74: 96 | K74: 2532 | L74: No | M74: E7103L
E75: NEBNext Multiplex Oligos for Illumina (96 Unique Dual Index Primer Pairs) | G75: 96 | H75: =IF(Equipment!$I$42>=1,ROUNDUP(((1+'Data entry'!$C$33)*((1/G75)*(('Data entry'!$C$16+'Data entry'!$C$16*'Data entry'!$C$23)+$H$50))),0),ROUNDUP((1/G75)*(('Data entry'!$C$16+'Data entry'!$C$16*'Data entry'!$C$23)+$H$50),0)) -> 7 | I75: =IF(Equipment!$I$42>=1,ROUNDUP(((1+'Data entry'!$C$33)*((1/$G75)*(('Data entry'!$F$16+'Data entry'!$F$16*'Data entry'!$F$23)+$I$50))),0),ROUNDUP((1/$G75)*(('Data entry'!$F$16+'Data entry'!$F$16*'Data entry'!$F$23)+$I$50),0)) -> 4 | J75: 96 | K75: 625 | M75: E6440S
B76: we assume it as LunaScript® RT SuperMix (M3010L) - 100 reactions/pack, 460$ per pack (Beatrix) | E76: RT-PCR reagents | G76: 100 | H76: =IF(Equipment!$I$42>=1,ROUNDUP(((1+'Data entry'!$C$33)*((1/G76)*(('Data entry'!$C$16+'Data entry'!$C$16*'Data entry'!$C$23)+$H$50))),0),ROUNDUP((1/G76)*(('Data entry'!$C$16+'Data entry'!$C$16*'Data entry'!$C$23)+$H$50),0)) -> 7 | I76: =IF(Equipment!$I$42>=1,ROUNDUP(((1+'Data entry'!$C$33)*((1/$G76)*(('Data entry'!$F$16+'Data entry'!$F$16*'Data entry'!$F$23)+$I$50))),0),ROUNDUP((1/$G76)*(('Data entry'!$F$16+'Data entry'!$F$16*'Data entry'!$F$23)+$I$50),0)) -> 4 | K76: 460 | M76: M3010L
B77: We assume Target specific primers - 1000 samples/pack; 65$ per pack (Beatrix) | E77: Target specific primers | G77: 1000 | H77: =IF(Equipment!$I$42>=1,ROUNDUP(((1+'Data entry'!$C$33)*((1/G77)*(('Data entry'!$C$16+'Data entry'!$C$16*'Data entry'!$C$23)+$H$50))),0),ROUNDUP((1/G77)*(('Data entry'!$C$16+'Data entry'!$C$16*'Data entry'!$C$23)+$H$50),0)) -> 1 | I77: =IF(Equipment!$I$42>=1,ROUNDUP(((1+'Data entry'!$C$33)*((1/$G77)*(('Data entry'!$F$16+'Data entry'!$F$16*'Data entry'!$F$23)+$I$50))),0),ROUNDUP((1/$G77)*(('Data entry'!$F$16+'Data entry'!$F$16*'Data entry'!$F$23)+$I$50),0)) -> 1 | K77: 65
B78: Bundled kit - 20099512 | C78: TB | D78: Illumina and Genoscreen Deeplex Myc-TB Combo IDP Kit (48 samples) | E78: Illumina and Genoscreen Deeplex Myc-TB Combo Kit with IDP Library Prep, 48 sample | F78: iSeq 100 System (13 samples), MiniSeq System (21 samples), MiSeq System (45 samples), NextSeq 550 (372 samples) | G78: 48 | H78: =IF(Equipment!$I$42>=1,ROUNDUP(((1+'Data entry'!$C$33)*((1/G78)*(('Data entry'!$C$16+'Data entry'!$C$16*'Data entry'!$C$23)+$H$50))),0),ROUNDUP((1/G78)*(('Data entry'!$C$16+'Data entry'!$C$16*'Data entry'!$C$23)+$H$50),0)) -> 14 | I78: =IF(Equipment!$I$42>=1,ROUNDUP(((1+'Data entry'!$C$33)*((1/$G78)*(('Data entry'!$F$16+'Data entry'!$F$16*'Data entry'!$F$23)+$I$50))),0),ROUNDUP((1/$G78)*(('Data entry'!$F$16+'Data entry'!$F$16*'Data entry'!$F$23)+$I$50),0)) -> 8 | J78: 384 | K78: 3468 | L78: Not applicable | M78: GNSDMTB01
B79: Check whether bundled options include the pack sizes as stated here? Price for bundled? | E79: Illumina DNA Prep, (M) Tagmentation (96 Samples, IPB) | G79: 96 | H79: =IF(Equipment!$I$42>=1,ROUNDUP(((1+'Data entry'!$C$33)*((1/G79)*(('Data entry'!$C$16+'Data entry'!$C$16*'Data entry'!$C$23)+$H$50))),0),ROUNDUP((1/G79)*(('Data entry'!$C$16+'Data entry'!$C$16*'Data entry'!$C$23)+$H$50),0)) -> 7 | I79: =IF(Equipment!$I$42>=1,ROUNDUP(((1+'Data entry'!$C$33)*((1/$G79)*(('Data entry'!$F$16+'Data entry'!$F$16*'Data entry'!$F$23)+$I$50))),0),ROUNDUP((1/$G79)*(('Data entry'!$F$16+'Data entry'!$F$16*'Data entry'!$F$23)+$I$50),0)) -> 4 | K79: 0 | M79: 20060059
E80: Illumina DNA/RNA Unique Dual Indexes Sets A, B, C, D, Tagmentation (96 Indexes, 96 Samples/set) | G80: 96 | H80: =IF(Equipment!$I$42>=1,ROUNDUP(((1+'Data entry'!$C$33)*((1/G80)*(('Data entry'!$C$16+'Data entry'!$C$16*'Data entry'!$C$23)+$H$50))),0),ROUNDUP((1/G80)*(('Data entry'!$C$16+'Data entry'!$C$16*'Data entry'!$C$23)+$H$50),0)) -> 7 | I80: =IF(Equipment!$I$42>=1,ROUNDUP(((1+'Data entry'!$C$33)*((1/$G80)*(('Data entry'!$F$16+'Data entry'!$F$16*'Data entry'!$F$23)+$I$50))),0),ROUNDUP((1/$G80)*(('Data entry'!$F$16+'Data entry'!$F$16*'Data entry'!$F$23)+$I$50),0)) -> 4 | J80: 384 | K80: 0 | M80: 20091654, 20091656, 20091658, 20091660
E81: AMPure XP beads 60ml | G81: 200 | H81: =IF(Equipment!$I$42>=1,ROUNDUP(((1+'Data entry'!$C$33)*((1/G81)*(('Data entry'!$C$16+'Data entry'!$C$16*'Data entry'!$C$23)+$H$50))),0),ROUNDUP((1/G81)*(('Data entry'!$C$16+'Data entry'!$C$16*'Data entry'!$C$23)+$H$50),0)) -> 4 | I81: =IF(Equipment!$I$42>=1,ROUNDUP(((1+'Data entry'!$C$33)*((1/$G81)*(('Data entry'!$F$16+'Data entry'!$F$16*'Data entry'!$F$23)+$I$50))),0),ROUNDUP((1/$G81)*(('Data entry'!$F$16+'Data entry'!$F$16*'Data entry'!$F$23)+$I$50),0)) -> 2 | K81: 2031 | M81: A63881
B82: Bundled kit - 20090205 | C82: TB | D82: Illumina and Genoscreen Deeplex Myc-TB Combo XT Kit (48 samples) | E82: Illumina and Genoscreen Deeplex Myc-TB Combo Kit with Nextera XT library prep, 48 sample | F82: iSeq 100 System (13 samples), MiniSeq System (21 samples), MiSeq System (45 samples), NextSeq 550 (372 samples) | G82: 48 | H82: =IF(Equipment!$I$42>=1,ROUNDUP(((1+'Data entry'!$C$33)*((1/G82)*(('Data entry'!$C$16+'Data entry'!$C$16*'Data entry'!$C$23)+$H$50))),0),ROUNDUP((1/G82)*(('Data entry'!$C$16+'Data entry'!$C$16*'Data entry'!$C$23)+$H$50),0)) -> 14 | I82: =IF(Equipment!$I$42>=1,ROUNDUP(((1+'Data entry'!$C$33)*((1/$G82)*(('Data entry'!$F$16+'Data entry'!$F$16*'Data entry'!$F$23)+$I$50))),0),ROUNDUP((1/$G82)*(('Data entry'!$F$16+'Data entry'!$F$16*'Data entry'!$F$23)+$I$50),0)) -> 8 | J82: 384 | K82: 3468 | L82: Not applicable | M82: GNSDMTB01
B83: Check whether bundled options include the pack sizes as stated here? Price for bundled? | E83: Nextera XT DNA Library Preparation Kit (96 samples) | G83: 96 | H83: =IF(Equipment!$I$42>=1,ROUNDUP(((1+'Data entry'!$C$33)*((1/G83)*(('Data entry'!$C$16+'Data entry'!$C$16*'Data entry'!$C$23)+$H$50))),0),ROUNDUP((1/G83)*(('Data entry'!$C$16+'Data entry'!$C$16*'Data entry'!$C$23)+$H$50),0)) -> 7 | I83: =IF(Equipment!$I$42>=1,ROUNDUP(((1+'Data entry'!$C$33)*((1/$G83)*(('Data entry'!$F$16+'Data entry'!$F$16*'Data entry'!$F$23)+$I$50))),0),ROUNDUP((1/$G83)*(('Data entry'!$F$16+'Data entry'!$F$16*'Data entry'!$F$23)+$I$50),0)) -> 4 | K83: 0 | M83: FC-131-1096
E84: Nextera XT index kit v2 Sets A, B, C, D (96 indices,384 samples/set) | G84: 96 | H84: =IF(Equipment!$I$42>=1,ROUNDUP(((1+'Data entry'!$C$33)*((1/G84)*(('Data entry'!$C$16+'Data entry'!$C$16*'Data entry'!$C$23)+$H$50))),0),ROUNDUP((1/G84)*(('Data entry'!$C$16+'Data entry'!$C$16*'Data entry'!$C$23)+$H$50),0)) -> 7 | I84: =IF(Equipment!$I$42>=1,ROUNDUP(((1+'Data entry'!$C$33)*((1/$G84)*(('Data entry'!$F$16+'Data entry'!$F$16*'Data entry'!$F$23)+$I$50))),0),ROUNDUP((1/$G84)*(('Data entry'!$F$16+'Data entry'!$F$16*'Data entry'!$F$23)+$I$50),0)) -> 4 | J84: 384 | K84: 0 | M84: FC-131-2001, FC-131-2002, FC-131-2003, FC-131-2004
E85: AMPure XP beads 60ml | G85: 200 | H85: =IF(Equipment!$I$42>=1,ROUNDUP(((1+'Data entry'!$C$33)*((1/G85)*(('Data entry'!$C$16+'Data entry'!$C$16*'Data entry'!$C$23)+$H$50))),0),ROUNDUP((1/G85)*(('Data entry'!$C$16+'Data entry'!$C$16*'Data entry'!$C$23)+$H$50),0)) -> 4 | I85: =IF(Equipment!$I$42>=1,ROUNDUP(((1+'Data entry'!$C$33)*((1/$G85)*(('Data entry'!$F$16+'Data entry'!$F$16*'Data entry'!$F$23)+$I$50))),0),ROUNDUP((1/$G85)*(('Data entry'!$F$16+'Data entry'!$F$16*'Data entry'!$F$23)+$I$50),0)) -> 2 | K85: 2031 | M85: A63881
C86: SAR-CoV-2 | D86: ONT COVID Mini V14: 576 samples | E86: 6 x MinION/GridION Flow Cells (R10.4.1) | F86: MinION Mk1B MinION Mk1C GridION Mk1 | G86: 576 | H86: =IF(Equipment!$I$42>=1,ROUNDUP(((1+'Data entry'!$C$33)*((1/G86)*(('Data entry'!$C$16+'Data entry'!$C$16*'Data entry'!$C$23)+$H$50))),0),ROUNDUP((1/G86)*(('Data entry'!$C$16+'Data entry'!$C$16*'Data entry'!$C$23)+$H$50),0)) -> 2 | I86: =IF(Equipment!$I$42>=1,ROUNDUP(((1+'Data entry'!$C$33)*((1/$G86)*(('Data entry'!$F$16+'Data entry'!$F$16*'Data entry'!$F$23)+$I$50))),0),ROUNDUP((1/$G86)*(('Data entry'!$F$16+'Data entry'!$F$16*'Data entry'!$F$23)+$I$50),0)) -> 1 | J86: 96 | K86: 7284 | L86: Not applicable | M86: C19MINI114
E87: 2 x Rapid Barcoding Kit 96 V14 | G87: 576 | H87: =IF(Equipment!$I$42>=1,ROUNDUP(((1+'Data entry'!$C$33)*((1/G87)*(('Data entry'!$C$16+'Data entry'!$C$16*'Data entry'!$C$23)+$H$50))),0),ROUNDUP((1/G87)*(('Data entry'!$C$16+'Data entry'!$C$16*'Data entry'!$C$23)+$H$50),0)) -> 2 | I87: =IF(Equipment!$I$42>=1,ROUNDUP(((1+'Data entry'!$C$33)*((1/$G87)*(('Data entry'!$F$16+'Data entry'!$F$16*'Data entry'!$F$23)+$I$50))),0),ROUNDUP((1/$G87)*(('Data entry'!$F$16+'Data entry'!$F$16*'Data entry'!$F$23)+$I$50),0)) -> 1 | J87: 96 | K87: 0
E88: 1 x Midnight RT PCR Expansion | G88: 576 | H88: =IF(Equipment!$I$42>=1,ROUNDUP(((1+'Data entry'!$C$33)*((1/G88)*(('Data entry'!$C$16+'Data entry'!$C$16*'Data entry'!$C$23)+$H$50))),0),ROUNDUP((1/G88)*(('Data entry'!$C$16+'Data entry'!$C$16*'Data entry'!$C$23)+$H$50),0)) -> 2 | I88: =IF(Equipment!$I$42>=1,ROUNDUP(((1+'Data entry'!$C$33)*((1/$G88)*(('Data entry'!$F$16+'Data entry'!$F$16*'Data entry'!$F$23)+$I$50))),0),ROUNDUP((1/$G88)*(('Data entry'!$F$16+'Data entry'!$F$16*'Data entry'!$F$23)+$I$50),0)) -> 1 | J88: 96 | K88: 0
C89: A protocol for full-length polyadenylated RNA | D89: ONT Direct RNA Sequencing Kit | E89: Direct RNA Sequencing Kit, 6 rxns | F89: MinION Mk1B MinION Mk1C MinION Mk1D GridION PromethION | G89: 6 | H89: =IF(Equipment!$I$42>=1,ROUNDUP(((1+'Data entry'!$C$33)*((1/G89)*(('Data entry'!$C$16+'Data entry'!$C$16*'Data entry'!$C$23)+$H$50))),0),ROUNDUP((1/G89)*(('Data entry'!$C$16+'Data entry'!$C$16*'Data entry'!$C$23)+$H$50),0)) -> 106 | I89: =IF(Equipment!$I$42>=1,ROUNDUP(((1+'Data entry'!$C$33)*((1/$G89)*(('Data entry'!$F$16+'Data entry'!$F$16*'Data entry'!$F$23)+$I$50))),0),ROUNDUP((1/$G89)*(('Data entry'!$F$16+'Data entry'!$F$16*'Data entry'!$F$23)+$I$50),0)) -> 58 | J89: 24 | K89: 599 | L89: Not applicable | M89: SQK-RNA004
E90: NEBNext Blunt/TA Ligase Master Mix, 250 rxns | G90: 250 | H90: =IF(Equipment!$I$42>=1,ROUNDUP(((1+'Data entry'!$C$33)*((1/G90)*(('Data entry'!$C$16+'Data entry'!$C$16*'Data entry'!$C$23)+$H$50))),0),ROUNDUP((1/G90)*(('Data entry'!$C$16+'Data entry'!$C$16*'Data entry'!$C$23)+$H$50),0)) -> 3 | I90: =IF(Equipment!$I$42>=1,ROUNDUP(((1+'Data entry'!$C$33)*((1/$G90)*(('Data entry'!$F$16+'Data entry'!$F$16*'Data entry'!$F$23)+$I$50))),0),ROUNDUP((1/$G90)*(('Data entry'!$F$16+'Data entry'!$F$16*'Data entry'!$F$23)+$I$50),0)) -> 2 | K90: 427 | M90: M0367L
E91: T4 DNA Ligase 2M U/mL | G91: 200 | H91: =IF(Equipment!$I$42>=1,ROUNDUP(((1+'Data entry'!$C$33)*((1/G91)*(('Data entry'!$C$16+'Data entry'!$C$16*'Data entry'!$C$23)+$H$50))),0),ROUNDUP((1/G91)*(('Data entry'!$C$16+'Data entry'!$C$16*'Data entry'!$C$23)+$H$50),0)) -> 4 | I91: =IF(Equipment!$I$42>=1,ROUNDUP(((1+'Data entry'!$C$33)*((1/$G91)*(('Data entry'!$F$16+'Data entry'!$F$16*'Data entry'!$F$23)+$I$50))),0),ROUNDUP((1/$G91)*(('Data entry'!$F$16+'Data entry'!$F$16*'Data entry'!$F$23)+$I$50),0)) -> 2 | K91: 80 | M91: NEB M0202T/M
E92: Agencourt RNAClean XP beads | G92: 400 | H92: =IF(Equipment!$I$42>=1,ROUNDUP(((1+'Data entry'!$C$33)*((1/G92)*(('Data entry'!$C$16+'Data entry'!$C$16*'Data entry'!$C$23)+$H$50))),0),ROUNDUP((1/G92)*(('Data entry'!$C$16+'Data entry'!$C$16*'Data entry'!$C$23)+$H$50),0)) -> 2 | I92: =IF(Equipment!$I$42>=1,ROUNDUP(((1+'Data entry'!$C$33)*((1/$G92)*(('Data entry'!$F$16+'Data entry'!$F$16*'Data entry'!$F$23)+$I$50))),0),ROUNDUP((1/$G92)*(('Data entry'!$F$16+'Data entry'!$F$16*'Data entry'!$F$23)+$I$50),0)) -> 1 | K92: 1082 | M92: A63987
E93: NEBNext Quick Ligation Reaction Buffer, 2mL 5x | G93: 5 | H93: =IF(Equipment!$I$42>=1,ROUNDUP(((1+'Data entry'!$C$33)*((1/G93)*(('Data entry'!$C$16+'Data entry'!$C$16*'Data entry'!$C$23)+$H$50))),0),ROUNDUP((1/G93)*(('Data entry'!$C$16+'Data entry'!$C$16*'Data entry'!$C$23)+$H$50),0)) -> 127 | I93: =IF(Equipment!$I$42>=1,ROUNDUP(((1+'Data entry'!$C$33)*((1/$G93)*(('Data entry'!$F$16+'Data entry'!$F$16*'Data entry'!$F$23)+$I$50))),0),ROUNDUP((1/$G93)*(('Data entry'!$F$16+'Data entry'!$F$16*'Data entry'!$F$23)+$I$50),0)) -> 70 | K93: 49 | M93: NEB B6058
E94: Custom-ordered Reverse Transcription Adapter | G94: 500 | H94: =IF(Equipment!$I$42>=1,ROUNDUP(((1+'Data entry'!$C$33)*((1/G94)*(('Data entry'!$C$16+'Data entry'!$C$16*'Data entry'!$C$23)+$H$50))),0),ROUNDUP((1/G94)*(('Data entry'!$C$16+'Data entry'!$C$16*'Data entry'!$C$23)+$H$50),0)) -> 2 | I94: =IF(Equipment!$I$42>=1,ROUNDUP(((1+'Data entry'!$C$33)*((1/$G94)*(('Data entry'!$F$16+'Data entry'!$F$16*'Data entry'!$F$23)+$I$50))),0),ROUNDUP((1/$G94)*(('Data entry'!$F$16+'Data entry'!$F$16*'Data entry'!$F$23)+$I$50),0)) -> 1 | K94: 288
E95: Deoxynucleotide (dNTP) Solution Mix (10 mM, 8 µmol) | G95: 400 | H95: =IF(Equipment!$I$42>=1,ROUNDUP(((1+'Data entry'!$C$33)*((1/G95)*(('Data entry'!$C$16+'Data entry'!$C$16*'Data entry'!$C$23)+$H$50))),0),ROUNDUP((1/G95)*(('Data entry'!$C$16+'Data entry'!$C$16*'Data entry'!$C$23)+$H$50),0)) -> 2 | I95: =IF(Equipment!$I$42>=1,ROUNDUP(((1+'Data entry'!$C$33)*((1/$G95)*(('Data entry'!$F$16+'Data entry'!$F$16*'Data entry'!$F$23)+$I$50))),0),ROUNDUP((1/$G95)*(('Data entry'!$F$16+'Data entry'!$F$16*'Data entry'!$F$23)+$I$50),0)) -> 1 | K95: 69 | M95: N0447S
E96: RNase Inhibitor, Murine (15,000 units) | G96: 375 | H96: =IF(Equipment!$I$42>=1,ROUNDUP(((1+'Data entry'!$C$33)*((1/G96)*(('Data entry'!$C$16+'Data entry'!$C$16*'Data entry'!$C$23)+$H$50))),0),ROUNDUP((1/G96)*(('Data entry'!$C$16+'Data entry'!$C$16*'Data entry'!$C$23)+$H$50),0)) -> 2 | I96: =IF(Equipment!$I$42>=1,ROUNDUP(((1+'Data entry'!$C$33)*((1/$G96)*(('Data entry'!$F$16+'Data entry'!$F$16*'Data entry'!$F$23)+$I$50))),0),ROUNDUP((1/$G96)*(('Data entry'!$F$16+'Data entry'!$F$16*'Data entry'!$F$23)+$I$50),0)) -> 1 | K96: 308 | M96: M0314L
E97: Induro® Reverse Transcriptase (NEB, M0681) | G97: 25 | H97: =IF(Equipment!$I$42>=1,ROUNDUP(((1+'Data entry'!$C$33)*((1/G97)*(('Data entry'!$C$16+'Data entry'!$C$16*'Data entry'!$C$23)+$H$50))),0),ROUNDUP((1/G97)*(('Data entry'!$C$16+'Data entry'!$C$16*'Data entry'!$C$23)+$H$50),0)) -> 26 | I97: =IF(Equipment!$I$42>=1,ROUNDUP(((1+'Data entry'!$C$33)*((1/$G97)*(('Data entry'!$F$16+'Data entry'!$F$16*'Data entry'!$F$23)+$I$50))),0),ROUNDUP((1/$G97)*(('Data entry'!$F$16+'Data entry'!$F$16*'Data entry'!$F$23)+$I$50),0)) -> 14 | K97: 508 | M97: M0681L
C98: SARS-CoV-2, RSV, Influenza A, Influenza B | D98: ONT Ligation Sequencing Kit V14 protocol with Native Barcoding Kit 24 V14 | E98: Ligation Sequencing Kit V14, 6 rxns | F98: All ONT | G98: =24*6 -> 144 | H98: =IF(Equipment!$I$42>=1,ROUNDUP(((1+'Data entry'!$C$33)*((1/G98)*(('Data entry'!$C$16+'Data entry'!$C$16*'Data entry'!$C$23)+$H$50))),0),ROUNDUP((1/G98)*(('Data entry'!$C$16+'Data entry'!$C$16*'Data entry'!$C$23)+$H$50),0)) -> 5 | I98: =IF(Equipment!$I$42>=1,ROUNDUP(((1+'Data entry'!$C$33)*((1/$G98)*(('Data entry'!$F$16+'Data entry'!$F$16*'Data entry'!$F$23)+$I$50))),0),ROUNDUP((1/$G98)*(('Data entry'!$F$16+'Data entry'!$F$16*'Data entry'!$F$23)+$I$50),0)) -> 3 | J98: 24 | K98: 599 | L98: Not applicable | M98: SQK-LSK114
E99: Native Barcoding Kit 24 V14 - 6 rxns | G99: =24*6 -> 144 | H99: =IF(Equipment!$I$42>=1,ROUNDUP(((1+'Data entry'!$C$33)*((1/G99)*(('Data entry'!$C$16+'Data entry'!$C$16*'Data entry'!$C$23)+$H$50))),0),ROUNDUP((1/G99)*(('Data entry'!$C$16+'Data entry'!$C$16*'Data entry'!$C$23)+$H$50),0)) -> 5 | I99: =IF(Equipment!$I$42>=1,ROUNDUP(((1+'Data entry'!$C$33)*((1/$G99)*(('Data entry'!$F$16+'Data entry'!$F$16*'Data entry'!$F$23)+$I$50))),0),ROUNDUP((1/$G99)*(('Data entry'!$F$16+'Data entry'!$F$16*'Data entry'!$F$23)+$I$50),0)) -> 3 | J99: 24 | K99: 699 | M99: SQK-NBD114.24
B100: alternatively - can use Compnanion kit v2 as bundle instead of individual NEBNext reagents | E100: NEBNext Blunt/TA Ligase Master Mix, 250 rxns | G100: 250 | H100: =IF(Equipment!$I$42>=1,ROUNDUP(((1+'Data entry'!$C$33)*((1/G100)*(('Data entry'!$C$16+'Data entry'!$C$16*'Data entry'!$C$23)+$H$50))),0),ROUNDUP((1/G100)*(('Data entry'!$C$16+'Data entry'!$C$16*'Data entry'!$C$23)+$H$50),0)) -> 3 | I100: =IF(Equipment!$I$42>=1,ROUNDUP(((1+'Data entry'!$C$33)*((1/$G100)*(('Data entry'!$F$16+'Data entry'!$F$16*'Data entry'!$F$23)+$I$50))),0),ROUNDUP((1/$G100)*(('Data entry'!$F$16+'Data entry'!$F$16*'Data entry'!$F$23)+$I$50),0)) -> 2 | K100: 427 | M100: M0367L
E101: NEBNext Ultra II End Repair/dA-tailing module, 96 rxn | G101: 96 | H101: =IF(Equipment!$I$42>=1,ROUNDUP(((1+'Data entry'!$C$33)*((1/G101)*(('Data entry'!$C$16+'Data entry'!$C$16*'Data entry'!$C$23)+$H$50))),0),ROUNDUP((1/G101)*(('Data entry'!$C$16+'Data entry'!$C$16*'Data entry'!$C$23)+$H$50),0)) -> 7 | I101: =IF(Equipment!$I$42>=1,ROUNDUP(((1+'Data entry'!$C$33)*((1/$G101)*(('Data entry'!$F$16+'Data entry'!$F$16*'Data entry'!$F$23)+$I$50))),0),ROUNDUP((1/$G101)*(('Data entry'!$F$16+'Data entry'!$F$16*'Data entry'!$F$23)+$I$50),0)) -> 4 | K101: 811 | M101: E7546L
E102: NEBNext Quick Ligation Module, 100 rxns | G102: 100 | H102: =IF(Equipment!$I$42>=1,ROUNDUP(((1+'Data entry'!$C$33)*((1/G102)*(('Data entry'!$C$16+'Data entry'!$C$16*'Data entry'!$C$23)+$H$50))),0),ROUNDUP((1/G102)*(('Data entry'!$C$16+'Data entry'!$C$16*'Data entry'!$C$23)+$H$50),0)) -> 7 | I102: =IF(Equipment!$I$42>=1,ROUNDUP(((1+'Data entry'!$C$33)*((1/$G102)*(('Data entry'!$F$16+'Data entry'!$F$16*'Data entry'!$F$23)+$I$50))),0),ROUNDUP((1/$G102)*(('Data entry'!$F$16+'Data entry'!$F$16*'Data entry'!$F$23)+$I$50),0)) -> 4 | K102: 1376 | M102: E6056L
B103: we assume it as LunaScript® RT SuperMix (M3010L) - 100 reactions/pack, 460$ per pack (Beatrix) | E103: RT-PCR reagents | G103: 100 | H103: =IF(Equipment!$I$42>=1,ROUNDUP(((1+'Data entry'!$C$33)*((1/G103)*(('Data entry'!$C$16+'Data entry'!$C$16*'Data entry'!$C$23)+$H$50))),0),ROUNDUP((1/G103)*(('Data entry'!$C$16+'Data entry'!$C$16*'Data entry'!$C$23)+$H$50),0)) -> 7 | I103: =IF(Equipment!$I$42>=1,ROUNDUP(((1+'Data entry'!$C$33)*((1/$G103)*(('Data entry'!$F$16+'Data entry'!$F$16*'Data entry'!$F$23)+$I$50))),0),ROUNDUP((1/$G103)*(('Data entry'!$F$16+'Data entry'!$F$16*'Data entry'!$F$23)+$I$50),0)) -> 4 | K103: 460 | M103: M3010L
B104: We assume Target specific primers - 1000 samples/pack; 65$ per pack (Beatrix) | E104: Target specific primers | G104: 1000 | H104: =IF(Equipment!$I$42>=1,ROUNDUP(((1+'Data entry'!$C$33)*((1/G104)*(('Data entry'!$C$16+'Data entry'!$C$16*'Data entry'!$C$23)+$H$50))),0),ROUNDUP((1/G104)*(('Data entry'!$C$16+'Data entry'!$C$16*'Data entry'!$C$23)+$H$50),0)) -> 1 | I104: =IF(Equipment!$I$42>=1,ROUNDUP(((1+'Data entry'!$C$33)*((1/$G104)*(('Data entry'!$F$16+'Data entry'!$F$16*'Data entry'!$F$23)+$I$50))),0),ROUNDUP((1/$G104)*(('Data entry'!$F$16+'Data entry'!$F$16*'Data entry'!$F$23)+$I$50),0)) -> 1 | K104: 65
C105: SARS-CoV-2, RSV, Influenza A, Influenza B | D105: ONT Ligation Sequencing Kit V14 protocol with Native Barcoding Kit 96 V14 | E105: Ligation Sequencing Kit V14, 6 rxns | F105: All ONT | G105: =96*6 -> 576 | H105: =IF(Equipment!$I$42>=1,ROUNDUP(((1+'Data entry'!$C$33)*((1/G105)*(('Data entry'!$C$16+'Data entry'!$C$16*'Data entry'!$C$23)+$H$50))),0),ROUNDUP((1/G105)*(('Data entry'!$C$16+'Data entry'!$C$16*'Data entry'!$C$23)+$H$50),0)) -> 2 | I105: =IF(Equipment!$I$42>=1,ROUNDUP(((1+'Data entry'!$C$33)*((1/$G105)*(('Data entry'!$F$16+'Data entry'!$F$16*'Data entry'!$F$23)+$I$50))),0),ROUNDUP((1/$G105)*(('Data entry'!$F$16+'Data entry'!$F$16*'Data entry'!$F$23)+$I$50),0)) -> 1 | J105: 96 | K105: 599 | L105: Not applicable | M105: SQK-LSK114
E106: Native Barcoding Kit 96 V14, 3 rxns | G106: =96*3 -> 288 | H106: =IF(Equipment!$I$42>=1,ROUNDUP(((1+'Data entry'!$C$33)*((1/G106)*(('Data entry'!$C$16+'Data entry'!$C$16*'Data entry'!$C$23)+$H$50))),0),ROUNDUP((1/G106)*(('Data entry'!$C$16+'Data entry'!$C$16*'Data entry'!$C$23)+$H$50),0)) -> 3 | I106: =IF(Equipment!$I$42>=1,ROUNDUP(((1+'Data entry'!$C$33)*((1/$G106)*(('Data entry'!$F$16+'Data entry'!$F$16*'Data entry'!$F$23)+$I$50))),0),ROUNDUP((1/$G106)*(('Data entry'!$F$16+'Data entry'!$F$16*'Data entry'!$F$23)+$I$50),0)) -> 2 | J106: 96 | K106: 799 | M106: SQK-NBD114.96
B107: alternatively - can use Compnanion kit v2 as bundle instead of individual NEBNext reagents | E107: NEBNext Blunt/TA Ligase Master Mix, 250 rxns | G107: 250 | H107: =IF(Equipment!$I$42>=1,ROUNDUP(((1+'Data entry'!$C$33)*((1/G107)*(('Data entry'!$C$16+'Data entry'!$C$16*'Data entry'!$C$23)+$H$50))),0),ROUNDUP((1/G107)*(('Data entry'!$C$16+'Data entry'!$C$16*'Data entry'!$C$23)+$H$50),0)) -> 3 | I107: =IF(Equipment!$I$42>=1,ROUNDUP(((1+'Data entry'!$C$33)*((1/$G107)*(('Data entry'!$F$16+'Data entry'!$F$16*'Data entry'!$F$23)+$I$50))),0),ROUNDUP((1/$G107)*(('Data entry'!$F$16+'Data entry'!$F$16*'Data entry'!$F$23)+$I$50),0)) -> 2 | K107: 427 | M107: M0367L
E108: NEBNext Ultra II End Repair/dA-tailing module, 96 rxns | G108: 96 | H108: =IF(Equipment!$I$42>=1,ROUNDUP(((1+'Data entry'!$C$33)*((1/G108)*(('Data entry'!$C$16+'Data entry'!$C$16*'Data entry'!$C$23)+$H$50))),0),ROUNDUP((1/G108)*(('Data entry'!$C$16+'Data entry'!$C$16*'Data entry'!$C$23)+$H$50),0)) -> 7 | I108: =IF(Equipment!$I$42>=1,ROUNDUP(((1+'Data entry'!$C$33)*((1/$G108)*(('Data entry'!$F$16+'Data entry'!$F$16*'Data entry'!$F$23)+$I$50))),0),ROUNDUP((1/$G108)*(('Data entry'!$F$16+'Data entry'!$F$16*'Data entry'!$F$23)+$I$50),0)) -> 4 | K108: 811 | M108: E7546L
E109: NEBNext Quick Ligation Module, 100 rxns | G109: 100 | H109: =IF(Equipment!$I$42>=1,ROUNDUP(((1+'Data entry'!$C$33)*((1/G109)*(('Data entry'!$C$16+'Data entry'!$C$16*'Data entry'!$C$23)+$H$50))),0),ROUNDUP((1/G109)*(('Data entry'!$C$16+'Data entry'!$C$16*'Data entry'!$C$23)+$H$50),0)) -> 7 | I109: =IF(Equipment!$I$42>=1,ROUNDUP(((1+'Data entry'!$C$33)*((1/$G109)*(('Data entry'!$F$16+'Data entry'!$F$16*'Data entry'!$F$23)+$I$50))),0),ROUNDUP((1/$G109)*(('Data entry'!$F$16+'Data entry'!$F$16*'Data entry'!$F$23)+$I$50),0)) -> 4 | K109: 1376 | M109: E6056L
B110: we assume it as LunaScript® RT SuperMix (M3010L) - 100 reactions/pack, 460$ per pack (Beatrix) | E110: RT-PCR reagents | G110: 100 | H110: =IF(Equipment!$I$42>=1,ROUNDUP(((1+'Data entry'!$C$33)*((1/G110)*(('Data entry'!$C$16+'Data entry'!$C$16*'Data entry'!$C$23)+$H$50))),0),ROUNDUP((1/G110)*(('Data entry'!$C$16+'Data entry'!$C$16*'Data entry'!$C$23)+$H$50),0)) -> 7 | I110: =IF(Equipment!$I$42>=1,ROUNDUP(((1+'Data entry'!$C$33)*((1/$G110)*(('Data entry'!$F$16+'Data entry'!$F$16*'Data entry'!$F$23)+$I$50))),0),ROUNDUP((1/$G110)*(('Data entry'!$F$16+'Data entry'!$F$16*'Data entry'!$F$23)+$I$50),0)) -> 4 | K110: 460 | M110: M3010L
B111: We assume Target specific primers - 1000 samples/pack; 65$ per pack (Beatrix) | E111: Target specific primers | G111: 1000 | H111: =IF(Equipment!$I$42>=1,ROUNDUP(((1+'Data entry'!$C$33)*((1/G111)*(('Data entry'!$C$16+'Data entry'!$C$16*'Data entry'!$C$23)+$H$50))),0),ROUNDUP((1/G111)*(('Data entry'!$C$16+'Data entry'!$C$16*'Data entry'!$C$23)+$H$50),0)) -> 1 | I111: =IF(Equipment!$I$42>=1,ROUNDUP(((1+'Data entry'!$C$33)*((1/$G111)*(('Data entry'!$F$16+'Data entry'!$F$16*'Data entry'!$F$23)+$I$50))),0),ROUNDUP((1/$G111)*(('Data entry'!$F$16+'Data entry'!$F$16*'Data entry'!$F$23)+$I$50),0)) -> 1 | K111: 65
C112: SARS-CoV-2, RSV, Influenza A, Influenza B | D112: ONT Ligation Sequencing Kit XL V14 protocol with Native Barcoding Kit 96 V14 | E112: Ligation Sequencing Kit XL V14 - 48 reactions | F112: All ONT | G112: =96*48 -> 4608 | H112: =IF(Equipment!$I$42>=1,ROUNDUP(((1+'Data entry'!$C$33)*((1/G112)*(('Data entry'!$C$16+'Data entry'!$C$16*'Data entry'!$C$23)+$H$50))),0),ROUNDUP((1/G112)*(('Data entry'!$C$16+'Data entry'!$C$16*'Data entry'!$C$23)+$H$50),0)) -> 1 | I112: =IF(Equipment!$I$42>=1,ROUNDUP(((1+'Data entry'!$C$33)*((1/$G112)*(('Data entry'!$F$16+'Data entry'!$F$16*'Data entry'!$F$23)+$I$50))),0),ROUNDUP((1/$G112)*(('Data entry'!$F$16+'Data entry'!$F$16*'Data entry'!$F$23)+$I$50),0)) -> 1 | J112: 96 | K112: 4000 | L112: Not applicable | M112: SQK-LSK114-XL
E113: Native Barcoding Kit 96 V14 -3 reactions | G113: =96*3 -> 288 | H113: =IF(Equipment!$I$42>=1,ROUNDUP(((1+'Data entry'!$C$33)*((1/G113)*(('Data entry'!$C$16+'Data entry'!$C$16*'Data entry'!$C$23)+$H$50))),0),ROUNDUP((1/G113)*(('Data entry'!$C$16+'Data entry'!$C$16*'Data entry'!$C$23)+$H$50),0)) -> 3 | I113: =IF(Equipment!$I$42>=1,ROUNDUP(((1+'Data entry'!$C$33)*((1/$G113)*(('Data entry'!$F$16+'Data entry'!$F$16*'Data entry'!$F$23)+$I$50))),0),ROUNDUP((1/$G113)*(('Data entry'!$F$16+'Data entry'!$F$16*'Data entry'!$F$23)+$I$50),0)) -> 2 | J113: 96 | K113: 799 | M113: SQK-NBD114.96
B114: alternatively - can use Compnanion kit v2 as bundle instead of individual NEBNext reagents | E114: NEBNext Blunt/TA Ligase Master Mix, 250 rxns | G114: 250 | H114: =IF(Equipment!$I$42>=1,ROUNDUP(((1+'Data entry'!$C$33)*((1/G114)*(('Data entry'!$C$16+'Data entry'!$C$16*'Data entry'!$C$23)+$H$50))),0),ROUNDUP((1/G114)*(('Data entry'!$C$16+'Data entry'!$C$16*'Data entry'!$C$23)+$H$50),0)) -> 3 | I114: =IF(Equipment!$I$42>=1,ROUNDUP(((1+'Data entry'!$C$33)*((1/$G114)*(('Data entry'!$F$16+'Data entry'!$F$16*'Data entry'!$F$23)+$I$50))),0),ROUNDUP((1/$G114)*(('Data entry'!$F$16+'Data entry'!$F$16*'Data entry'!$F$23)+$I$50),0)) -> 2 | K114: 427 | M114: M0367L
E115: NEBNext Ultra II End Repair/dA-tailing module, 96 rxn | G115: 96 | H115: =IF(Equipment!$I$42>=1,ROUNDUP(((1+'Data entry'!$C$33)*((1/G115)*(('Data entry'!$C$16+'Data entry'!$C$16*'Data entry'!$C$23)+$H$50))),0),ROUNDUP((1/G115)*(('Data entry'!$C$16+'Data entry'!$C$16*'Data entry'!$C$23)+$H$50),0)) -> 7 | I115: =IF(Equipment!$I$42>=1,ROUNDUP(((1+'Data entry'!$C$33)*((1/$G115)*(('Data entry'!$F$16+'Data entry'!$F$16*'Data entry'!$F$23)+$I$50))),0),ROUNDUP((1/$G115)*(('Data entry'!$F$16+'Data entry'!$F$16*'Data entry'!$F$23)+$I$50),0)) -> 4 | K115: 811 | M115: E7546L
E116: NEBNext Quick Ligation Module, 100 rxns | G116: 100 | H116: =IF(Equipment!$I$42>=1,ROUNDUP(((1+'Data entry'!$C$33)*((1/G116)*(('Data entry'!$C$16+'Data entry'!$C$16*'Data entry'!$C$23)+$H$50))),0),ROUNDUP((1/G116)*(('Data entry'!$C$16+'Data entry'!$C$16*'Data entry'!$C$23)+$H$50),0)) -> 7 | I116: =IF(Equipment!$I$42>=1,ROUNDUP(((1+'Data entry'!$C$33)*((1/$G116)*(('Data entry'!$F$16+'Data entry'!$F$16*'Data entry'!$F$23)+$I$50))),0),ROUNDUP((1/$G116)*(('Data entry'!$F$16+'Data entry'!$F$16*'Data entry'!$F$23)+$I$50),0)) -> 4 | K116: 1376 | M116: E6056L
B117: we assume it as LunaScript® RT SuperMix (M3010L) - 100 reactions/pack, 460$ per pack (Beatrix) | E117: RT-PCR reagents | G117: 100 | H117: =IF(Equipment!$I$42>=1,ROUNDUP(((1+'Data entry'!$C$33)*((1/G117)*(('Data entry'!$C$16+'Data entry'!$C$16*'Data entry'!$C$23)+$H$50))),0),ROUNDUP((1/G117)*(('Data entry'!$C$16+'Data entry'!$C$16*'Data entry'!$C$23)+$H$50),0)) -> 7 | I117: =IF(Equipment!$I$42>=1,ROUNDUP(((1+'Data entry'!$C$33)*((1/$G117)*(('Data entry'!$F$16+'Data entry'!$F$16*'Data entry'!$F$23)+$I$50))),0),ROUNDUP((1/$G117)*(('Data entry'!$F$16+'Data entry'!$F$16*'Data entry'!$F$23)+$I$50),0)) -> 4 | K117: 460 | M117: M3010L
B118: We assume Target specific primers - 1000 samples/pack; 65$ per pack (Beatrix) | E118: Target specific primers | G118: 1000 | H118: =IF(Equipment!$I$42>=1,ROUNDUP(((1+'Data entry'!$C$33)*((1/G118)*(('Data entry'!$C$16+'Data entry'!$C$16*'Data entry'!$C$23)+$H$50))),0),ROUNDUP((1/G118)*(('Data entry'!$C$16+'Data entry'!$C$16*'Data entry'!$C$23)+$H$50),0)) -> 1 | I118: =IF(Equipment!$I$42>=1,ROUNDUP(((1+'Data entry'!$C$33)*((1/$G118)*(('Data entry'!$F$16+'Data entry'!$F$16*'Data entry'!$F$23)+$I$50))),0),ROUNDUP((1/$G118)*(('Data entry'!$F$16+'Data entry'!$F$16*'Data entry'!$F$23)+$I$50),0)) -> 1 | K118: 65
C119: Capture all (bacteria) | D119: 16S Barcoding Kit 24 V14 | E119: 16S Barcoding Kit 24 V14 | F119: Flongle MinION Mk1B MinION Mk1C MinION Mk1D GridION | G119: 24 | H119: =IF(Equipment!$I$42>=1,ROUNDUP(((1+'Data entry'!$C$33)*((1/G119)*(('Data entry'!$C$16+'Data entry'!$C$16*'Data entry'!$C$23)+$H$50))),0),ROUNDUP((1/G119)*(('Data entry'!$C$16+'Data entry'!$C$16*'Data entry'!$C$23)+$H$50),0)) -> 27 | I119: =IF(Equipment!$I$42>=1,ROUNDUP(((1+'Data entry'!$C$33)*((1/$G119)*(('Data entry'!$F$16+'Data entry'!$F$16*'Data entry'!$F$23)+$I$50))),0),ROUNDUP((1/$G119)*(('Data entry'!$F$16+'Data entry'!$F$16*'Data entry'!$F$23)+$I$50),0)) -> 15 | J119: 24 | K119: 900 | L119: Yes | M119: SQK-16S114.24
H120: =IF(Equipment!$I$42>=1,ROUNDUP(((1+'Data entry'!$C$33)*((1/G120)*(('Data entry'!$C$16+'Data entry'!$C$16*'Data entry'!$C$23)+$H$50))),0),ROUNDUP((1/G120)*(('Data entry'!$C$16+'Data entry'!$C$16*'Data entry'!$C$23)+$H$50),0)) -> #DIV/0! | I120: =IF(Equipment!$I$42>=1,ROUNDUP(((1+'Data entry'!$C$33)*((1/$G120)*(('Data entry'!$F$16+'Data entry'!$F$16*'Data entry'!$F$23)+$I$50))),0),ROUNDUP((1/$G120)*(('Data entry'!$F$16+'Data entry'!$F$16*'Data entry'!$F$23)+$I$50),0)) -> #DIV/0!
H121: =IF(Equipment!$I$42>=1,ROUNDUP(((1+'Data entry'!$C$33)*((1/G121)*(('Data entry'!$C$16+'Data entry'!$C$16*'Data entry'!$C$23)+$H$50))),0),ROUNDUP((1/G121)*(('Data entry'!$C$16+'Data entry'!$C$16*'Data entry'!$C$23)+$H$50),0)) -> #DIV/0! | I121: =IF(Equipment!$I$42>=1,ROUNDUP(((1+'Data entry'!$C$33)*((1/$G121)*(('Data entry'!$F$16+'Data entry'!$F$16*'Data entry'!$F$23)+$I$50))),0),ROUNDUP((1/$G121)*(('Data entry'!$F$16+'Data entry'!$F$16*'Data entry'!$F$23)+$I$50),0)) -> #DIV/0!
...

Sheet Annex2_Equipment
E1: ='Data entry'!F31 -> 831 | F1: <--Annual Number Samples - Sequencer 1 and Sequencer 2
B2: EQUIPMENT | E2: 5000 | F2: <--Annual Sample throughput after which liquid handler-lib prep is added to recommended equipment for Sequencer 1 only
